Workbook

Sheet Passo a Passo
A3: 1 | B3: Atualizar a aba de "Resultado" com dados extraídos do sistema ER System, de acordo com esse relatório:
A4: 2. | B4: Realizar o procedimento descrito no passo 1 acima, para todas as empresas
A17: 2 | B17: Atualizar a aba "Realizado" com os dados de resultado por produto, carteira de crédito, carteira de captação e dados de depreciação/amortização presentes na aba "TD_P&L (Total)" do check contábil
A18: 3 | B18: Atualizar a aba orçamento somente quando tiver outro orçamento vigente, nesse casos copia e cola o orçamento passado e faz o vínculo com o novo
A19: 4 | B19: Atualizar as abas "P&L Mensal" e "P&L Acumulado" com as datas do mês em análise
A20: 5 | B20: Análise das receitas operacionais: os arquivos de receita diária da contabilidade servem como base para identificar possiveis erros de roteiro, ou indicativo de outros problemas sistemicos
A21: 5.1 | B21: Os arquivos diários da contabilidade estão nos seguintes diretórios:
B22: G:\Drives compartilhados\Area - Contabilidade 2 Temp\02. CONCILIAÇÃO\1. BANCO BARI\RESULTADO\RECEITA\2025
B23: G:\Drives compartilhados\Area - Contabilidade 2\Contabilidade\05. FECHAMENTO CONTABIL\02. CONCILIAÇÃO\4. BARI CIA HIPOTECARIA\RESULTADO\2025
A24: 5.1.1 | B24: Analisar se há dias em que tem mais ou menos receitas de juros e correção monetária.
B25: Alguns pontos para relembrar:
B26: A taxa bonificada esta roteirizada para reduzir a correção monetária, o que pode levar até mesmo a negativação das receitas, principalemnte nos maiores venciemntos: 12, 18 e 20.
B27: As receitas são cálculadas em dias corridos e apropriadas em dias úteis, por isso na segunda há descarrego das receitas. Quando o fechamento do mês cai final de semana a apropriação é antecipada para sexta.
B28: A Sicred calcula em 365 os juros e o Prognum em 360. Por tanto, a forma que é apropriada gera distorção em relação ao orçado, conforme o quadro abaixo:
B30: Ano 365 dias | G30: Ano 366 dias (bissexto)
B31: Mês | C31: Qt. Dias | D31: Dias corridos | E31: Diferença de dias orçado x realizado | G31: Mês | H31: Qt. Dias | I31: Dias corridos | J31: Diferença de dias orçado x realizado
B32: janeiro | C32: 30 | D32: 31 | E32: =C32-D32 -> -1 | G32: janeiro | H32: 30 | I32: 31 | J32: =H32-I32 -> -1
B33: fevereiro | C33: 27 | D33: 28 | E33: =C33-D33 -> -1 | G33: fevereiro | H33: 28 | I33: 29 | J33: =H33-I33 -> -1
B34: março | C34: 33 | D34: 31 | E34: =C34-D34 -> 2 | G34: março | H34: 32 | I34: 31 | J34: =H34-I34 -> 1
B35: abril | C35: 29 | D35: 30 | E35: =C35-D35 -> -1 | G35: abril | H35: 29 | I35: 30 | J35: =H35-I35 -> -1
B36: maio | C36: 31 | D36: 31 | E36: =C36-D36 -> 0 | G36: maio | H36: 31 | I36: 31 | J36: =H36-I36 -> 0
B37: junho | C37: 29 | D37: 30 | E37: =C37-D37 -> -1 | G37: junho | H37: 29 | I37: 30 | J37: =H37-I37 -> -1
B38: julho | C38: 31 | D38: 31 | E38: =C38-D38 -> 0 | G38: julho | H38: 31 | I38: 31 | J38: =H38-I38 -> 0
B39: agosto | C39: 30 | D39: 31 | E39: =C39-D39 -> -1 | G39: agosto | H39: 30 | I39: 31 | J39: =H39-I39 -> -1
B40: setembro | C40: 29 | D40: 30 | E40: =C40-D40 -> -1 | G40: setembro | H40: 29 | I40: 30 | J40: =H40-I40 -> -1
B41: outubro | C41: 31 | D41: 31 | E41: =C41-D41 -> 0 | G41: outubro | H41: 31 | I41: 31 | J41: =H41-I41 -> 0
B42: novembro | C42: 29 | D42: 30 | E42: =C42-D42 -> -1 | G42: novembro | H42: 29 | I42: 30 | J42: =H42-I42 -> -1
B43: dezembro | C43: 31 | D43: 31 | E43: =C43-D43 -> 0 | G43: dezembro | H43: 31 | I43: 31 | J43: =H43-I43 -> 0
B44: Total | C44: 360 | D44: =SUM(D32:D43) -> 365 | E44: =SUM(E32:E43) -> -5 | G44: Total | H44: 360 | I44: =SUM(I32:I43) -> 366 | J44: =SUM(J32:J43) -> -6
A46: 5.1.1.1 | B46: Se precisar investigar melhor os contratos de forma análitica:
B48: Gerar Voucher p/todas as contas e verificar a descrição do movimento
B65: Gera o "Analitico por Lançamento" para verificar o evento se estiver concentrado em um único contrato, analisar para entender

Sheet Premissas
B2: Receita Externa Cebraco:
B3: Apresenta todas as receitas, exceto receita das ligadas: Banco e Hipo. Desconsidera Securitizadora, pois os valores são pagos em patrimônio separado, ou seja, a sec apenas faz a intermediação.
B4: Conta "7.1.7.99.00.000007", "RENDAS CALL CENTER (PESSOA FISICA)" do Balancete e do arquivo de Resultados da Contabilidade
B6: Receita de Serviços, Interchange e Comissão CRI
B7: Serviços >> Grupo 7.1.7 do cosif do Banco, da Hipotecária, da DI (conta cosif: 7.1.7.00.00), receita de despachante da Service (conta cosif: 7.1.7.80.00.000024) e receita Call Center da Poio (conta cosif: 7.1.7.80.00.000002) . No arquivo de "Receitas e Despesas Contabilidade", salvo no diretório "G:\Drives compartilhados\Area - FPA\FPA\29. Checks Contabilidade\2025" há toda a relação dos "de-paras" nas abas do BANCO e da HIPO.
B8: A conta cosif "7.1.7.99.00.00.000013 - COORDENADOR LÍDER", é alocada em Receita de CRI
B9: As contas cosif "7.1.7.99.00.00.000015 - RECEITA INTERCHANGE - FUNCAO CREDITO", "7.1.7.99.00.00.000016 - RECEITA INTERCHANGE - FUNCAO DEBITO" e "7.1.7.99.00.00.000017 - BOLETO DE DEPOSITO LIQUIDADO" são alocada em Receita de Interchange. A divisão entre Consignado e Imobiliário é feita da seguinte forma: 42,6% para Consignado e 57,4% para Imobiliário.
B11: Receita cobrança externa Cebraco
B12: Receitas de prestação de serviços das empresas terceiras.
B13: Valor extraído da planilha "TD_P&L (Total)" do check contábil, célula "D12"
B14: Esse valor deve coincidir com a soma das contas cosif (7.1.7.99.00.000005 e 7.1.7.99.00.000007) do balancete da Cebraco
B16: Resultado de Seguros
... B77: 2) As demais rúbricas contábeis do cartão são alocadas da seguinte forma: 1) 42,6% para o Consignado e 57,4% para o Imobiliário.
A79: Não estamos utilizando os critérios específicados dessa linha para baixo
B81: PART. CONTROLADAS (SEC)
B82: 1) O dados é o mesmo que está na planilha "RESULTADO" e correspondente ao lucro líquido da Sec
B84: Critério de Rateio Captação:
B85: Lógica até Abril/2023
B86: Cartão é o resultado da receita de float/despesa da carteira de crédito que gera juros (desconsidera Creliq).
B87: Imobiliário --> LCI + CDB/LC - IPCA e IGPM + Resultado de Swap.
B88: Consignado --> CDB/LC - Pré/DI
B89: Outros (Receita Financeira, FGC, DPGE, e LFS) --> rateado pela carteira de consignado e imobiliário.
B90: Lógica após Maio/2023
B91: Cartão é o resultado da receita de float/despesa da carteira de crédito.
B92: Consignado --> Consome a despesa até fechar a carteira de ativa e passiva, na seguinte ordem quanto faltar carteira: CDB/LC - Pré, CDB/LC - DI, LCI - Pré e LCI - DI e Resultado Swap (DI x Pré)
B93: Imobiliário --> LCI + CDB/LC - IPCA e IGPM + Resultado de Swap (DI x IPCA), e o restante LCI Pré e DI que não forem utilizadas para fechar a carteira do consignado.
... B108: A partir de julho/24: versão de Março/24 adequando os rateios para retirada do banco digital.

Sheet RESULTADO
B2: Mês | C2: =EOMONTH(D2,-1) -> 44926 | D2: 44957 | E2: 44985 | F2: 45016 | G2: 1º TRIM | I2: =EOMONTH(F2:F2,1) -> 45046 | J2: =EOMONTH(I2:I2,1) -> 45077 | K2: =EOMONTH(J2:J2,1) -> 45107 | M2: 2º TRIM | O2: 1º SEM | Q2: =EOMONTH(K2,1) -> 45138 | R2: =EOMONTH(Q2:Q2,1) -> 45169 | S2: =EOMONTH(R2:R2,1) -> 45199 | U2: 3º TRIM | W2: =EOMONTH(S2:S2,1) -> 45230 | X2: 45260 | Y2: =EOMONTH(X2:X2,1) -> 45291 | AA2: 4º TRIM | AC2: 2º SEM | AE2: 2023 | AG2: 45322 | AH2: =EOMONTH(AG2,1) -> 45351 | AI2: =EOMONTH(AH2,1) -> 45382 | AK2: 1º TRIM | AM2: =EOMONTH(AI2:AI2,1) -> 45412 | AN2: =EOMONTH(AM2:AM2,1) -> 45443 | AO2: =EOMONTH(AN2:AN2,1) -> 45473 | AQ2: 2º TRIM | AS2: 1º SEM | AU2: =EOMONTH(AO2,1) -> 45504 | AV2: =EOMONTH(AU2:AU2,1) -> 45535 | AW2: =EOMONTH(AV2:AV2,1) -> 45565 | AY2: 3º TRIM | BA2: =EOMONTH(AW2:AW2,1) -> 45596 | BB2: =EOMONTH(BA2:BA2,1) -> 45626 | BC2: =EOMONTH(BB2:BB2,1) -> 45657 | BE2: 4º TRIM | BG2: 2º SEM | BI2: 2024 | BJ2: =EOMONTH(BC2,1) -> 45688 | BK2: =EOMONTH(BJ2,1) -> 45716 | BL2: =EOMONTH(BK2,1) -> 45747 | BM2: =EOMONTH(BL2:BL2,1) -> 45777 | BN2: =EOMONTH(BM2:BM2,1) -> 45808 | BO2: =EOMONTH(BN2:BN2,1) -> 45838 | BP2: =EOMONTH(BO2,1) -> 45869 | BQ2: =EOMONTH(BP2:BP2,1) -> 45900 | BR2: 45930 | BS2: =EOMONTH(BR2:BR2,1) -> 45961 | BT2: =EOMONTH(BS2,1) -> 45991 | BU2: =EOMONTH(BT2,1) -> 46022 | BW2: 4º TRIM | BY2: 2º SEM | CA2: YTD | CC2: =EOMONTH(BU2,1) -> 46053 | CD2: =EOMONTH(CC2,1) -> 46081 | CE2: =EOMONTH(CD2,1) -> 46112
B3: Banco | C3: -1225882.7 | D3: -2256281.8 | E3: -551555.87 | F3: 6437130.8 | G3: =SUM(D3:F3) -> 3629293.1 | I3: -1840435.7 | J3: 471919.39 | K3: 2444762.5 | M3: =SUM(I3:K3) -> 1076246.2 | O3: =SUM(I3:K3,D3:F3) -> 4705539.4 | Q3: -13238.56 | R3: -260697.35 | S3: 5983559.6 | U3: =SUM(Q3:S3) -> 5709623.7 | W3: 2301934.6 | X3: 2390376.4 | Y3: 7139953.1 | AA3: =SUM(W3:Y3) -> 11832264 | AC3: =SUM(W3:Y3,Q3:S3) -> 17541888 | AE3: =O3+AC3 -> 22247427 | AG3: 135333.08 | AH3: 1351348.1 | AI3: 1607493.6 | AK3: =SUM(AG3:AI3) -> 3094174.8 | AM3: 1778241.2 | AN3: 668906.43 | AO3: 4951864.8 | AQ3: =SUM(AM3:AO3) -> 7399012.4 | AS3: =SUM(AM3:AO3,AG3:AI3) -> 10493187 | AU3: 1208517.6 | AV3: 1317888.3 | AW3: 3497673 | AY3: =SUM(AU3:AW3) -> 6024078.8 | BA3: 407091.3 | BB3: 2060889.3 | BC3: 9185197.5 | BE3: =SUM(BA3:BC3) -> 11653178 | BG3: =SUM(BA3:BC3,AU3:AW3) -> 17677257 | BI3: =AS3+BG3 -> 28170444 | BJ3: 1184338 | BK3: 476737.52 | BL3: 5719093.2 | BM3: 4177224.8 | BN3: 2356700.7 | BO3: 4784053.5 | BP3: 2422631.3 | BQ3: 2180653 | BR3: 3140838.3 | BS3: 462356.73 | BT3: 3972262 | BU3: 4603577 | BW3: =SUM(BS3:BU3) -> 9038195.8 | BY3: =SUM(BS3:BU3,BP3:BR3) -> 16782318 | CA3: =SUM(BJ3:BU3) -> 35480466 | CC3: 1868086.1 | CD3: 2667098.7 | CE3: 4416073.4
B4: Equiv.Patr. | C4: 453185.32 | D4: 771628.33 | E4: 1431454.9 | F4: 2102188.9 | G4: =SUM(D4:F4) -> 4305272.2 | I4: 436785.4 | J4: 417689.25 | K4: 2852793 | M4: =SUM(I4:K4) -> 3707267.6 | O4: =SUM(I4:K4,D4:F4) -> 8012539.8 | Q4: 554506.77 | R4: 852807.67 | S4: -43758.08 | U4: =SUM(Q4:S4) -> 1363556.4 | W4: 944140.65 | X4: 1170510.6 | Y4: -2091085.1 | AA4: =SUM(W4:Y4) -> 23566.16 | AC4: =SUM(W4:Y4,Q4:S4) -> 1387122.5 | AE4: =O4+AC4 -> 9399662.3 | AG4: 172056.15 | AH4: 533427.26 | AI4: 444797.31 | AK4: =SUM(AG4:AI4) -> 1150280.7 | AM4: 485176.53 | AN4: 762992.45 | AO4: 512552.2 | AQ4: =SUM(AM4:AO4) -> 1760721.2 | AS4: =SUM(AM4:AO4,AG4:AI4) -> 2911001.9 | AU4: 754648.1 | AV4: 477878.87 | AW4: -268578.25 | AY4: =SUM(AU4:AW4) -> 963948.72 | BA4: -655785.64 | BB4: 745429.73 | BC4: 1669542.1 | BE4: =SUM(BA4:BC4) -> 1759186.2 | BG4: =SUM(BA4:BC4,AU4:AW4) -> 2723134.9 | BI4: =AS4+BG4 -> 5634136.8 | BJ4: 541079.53 | BK4: 991900.92 | BL4: 1442485.3 | BM4: 1665618.3 | BN4: 1190816.5 | BO4: 1675707.9 | BP4: 1137988.6 | BQ4: 322307.46 | BR4: 869987.47 | BS4: 382306.92 | BT4: 1854232.9 | BU4: 1765324.5 | BW4: =SUM(BS4:BU4) -> 4001864.3 | BY4: =SUM(BS4:BU4,BP4:BR4) -> 6332147.9 | CA4: =SUM(BJ4:BU4) -> 13839756 | CC4: 1404277.8 | CD4: 1441916.6 | CE4: 1955492.4
B5: JCP + Dividendos | C5: 191960.21 | D5: 0 | E5: 0 | F5: 0 | G5: =SUM(D5:F5) -> 0 | I5: 0 | J5: 0 | K5: 0 | M5: =SUM(I5:K5) -> 0 | O5: =SUM(I5:K5,D5:F5) -> 0 | Q5: 0 | R5: 0 | S5: 0 | U5: =SUM(Q5:S5) -> 0 | W5: 0 | X5: 0 | Y5: 4864009.9 | AA5: =SUM(W5:Y5) -> 4864009.9 | AC5: =SUM(W5:Y5,Q5:S5) -> 4864009.9 | AE5: =O5+AC5 -> 4864009.9 | AG5: 0 | AH5: 0 | AI5: 0 | AK5: =SUM(AG5:AI5) -> 0 | AM5: 0 | AN5: 0 | AO5: 1018230.3 | AQ5: =SUM(AM5:AO5) -> 1018230.3 | AS5: =SUM(AM5:AO5,AG5:AI5) -> 1018230.3 | AU5: 0 | AV5: 0 | AW5: 0 | AY5: =SUM(AU5:AW5) -> 0 | BA5: 0 | BB5: 0 | BC5: 683065.86 | BE5: =SUM(BA5:BC5) -> 683065.86 | BG5: =SUM(BA5:BC5,AU5:AW5) -> 683065.86 | BI5: =AS5+BG5 -> 1701296.2 | BJ5: 0 | BK5: 0 | BL5: 0 | BM5: 0 | BN5: 0 | BO5: 0 | BP5: 0 | BQ5: 0 | BR5: 0 | BS5: 0 | BT5: 0 | BU5: 0 | BW5: =SUM(BS5:BU5) -> 0 | BY5: =SUM(BS5:BU5,BP5:BR5) -> 0 | CA5: =SUM(BJ5:BU5) -> 0 | CC5: 0 | CD5: 0 | CE5: 0
B6: Resultado Banco | C6: -1871028.2 | D6: =D3-D4-D5 -> -3027910.1 | E6: =E3-E4-E5 -> -1983010.8 | F6: =F3-F4-F5 -> 4334941.8 | G6: =SUM(D6:F6) -> -675979.02 | I6: =I3-I4-I5 -> -2277221.1 | J6: =J3-J4-J5 -> 54230.14 | K6: =K3-K4-K5 -> -408030.44 | M6: =SUM(I6:K6) -> -2631021.4 | O6: =O3-O4-O5 -> -3307000.4 | Q6: =Q3-Q4-Q5 -> -567745.33 | R6: =R3-R4-R5 -> -1113505 | S6: =S3-S4-S5 -> 6027317.7 | U6: =SUM(Q6:S6) -> 4346067.3 | W6: 1357793.9 | X6: 1219865.8 | Y6: 4367028.2 | AA6: =SUM(W6:Y6) -> 6944688 | AC6: =AC3-AC4-AC5 -> 11290755 | AE6: =AE3-AE4-AE5 -> 7983754.9 | AG6: -36723.07 | AH6: 817920.86 | AI6: 1162696.3 | AK6: =SUM(AG6:AI6) -> 1943894.1 | AM6: 1293064.6 | AN6: -94086.02 | AO6: 3421082.3 | AQ6: =SUM(AM6:AO6) -> 4620060.9 | AS6: =AS3-AS4-AS5 -> 6563955 | AU6: 453869.49 | AV6: 840009.4 | AW6: 3766251.2 | AY6: =SUM(AU6:AW6) -> 5060130.1 | BA6: 1062876.9 | BB6: 1315459.6 | BC6: 6832589.5 | BE6: =SUM(BA6:BC6) -> 9210926.1 | BG6: =BG3-BG4-BG5 -> 14271056 | BI6: =BI3-BI4-BI5 -> 20835011 | BJ6: 643258.46 | BK6: -515163.4 | BL6: 4276607.9 | BM6: 2511606.5 | BN6: 1165884.2 | BO6: 3108345.6 | BP6: 1284642.7 | BQ6: 1858345.5 | BR6: 2270850.8 | BS6: 80049.81 | BT6: 2118029.2 | BU6: 2838252.5 | BW6: =SUM(BS6:BU6) -> 5036331.4 | BY6: =BY3-BY4-BY5 -> 10450170 | CA6: =SUM(BJ6:BU6) -> 21640710 | CC6: 463808.25 | CD6: 1225182.2 | CE6: =CE3-CE4 -> 2460581.1
B7: Hipotecária | C7: 569477.66 | D7: 184324.92 | E7: 1250477.1 | F7: 2071688.5 | G7: =SUM(D7:F7) -> 3506490.6 | I7: 411267.6 | J7: -80452.38 | K7: 2556900.1 | M7: =SUM(I7:K7) -> 2887715.3 | O7: =SUM(I7:K7,D7:F7) -> 6394205.9 | Q7: 370274.9 | R7: 507165.18 | S7: -90122.92 | U7: =SUM(Q7:S7) -> 787317.16 | W7: 886582.6 | X7: 857060.12 | Y7: 2345408.5 | AA7: =SUM(W7:Y7) -> 4089051.2 | AC7: =SUM(W7:Y7,Q7:S7) -> 4876368.4 | AE7: =O7+AC7 -> 11270574 | AG7: 110976.49 | AH7: 411297.69 | AI7: 236500.31 | AK7: =SUM(AG7:AI7) -> 758774.49 | AM7: 434611.59 | AN7: 404507.76 | AO7: 1338115.9 | AQ7: =SUM(AM7:AO7) -> 2177235.2 | AS7: =SUM(AM7:AO7,AG7:AI7) -> 2936009.7 | AU7: 617707.85 | AV7: 430066.94 | AW7: -305419.29 | AY7: =SUM(AU7:AW7) -> 742355.5 | BA7: -811427.31 | BB7: 850419.33 | BC7: 1712350.7 | BE7: =SUM(BA7:BC7) -> 1751342.7 | BG7: =SUM(BA7:BC7,AU7:AW7) -> 2493698.2 | BI7: =AS7+BG7 -> 5429707.9 | BJ7: 464703.12 | BK7: 871800.97 | BL7: 1249780.1 | BM7: 1592797.9 | BN7: 1100442.5 | BO7: 1636029.5 | BP7: 1078640.2 | BQ7: 108896.66 | BR7: 685150.93 | BS7: 198757.09 | BT7: 1665017.2 | BU7: 1403074.8 | BW7: =SUM(BS7:BU7) -> 3266849.1 | BY7: =SUM(BS7:BU7,BP7:BR7) -> 5139537 | CA7: =SUM(BJ7:BU7) -> 12055091 | CC7: 1359401.9 | CD7: 1158533.6 | CE7: 2104762.7
B8: Resultado Congl. Financeiro | C8: -1301550.5 | D8: -2843585.2 | E8: -732533.64 | F8: 6406630.4 | G8: =SUM(D8:F8) -> 2830511.5 | I8: -1865953.5 | J8: -26222.24 | K8: 2148869.7 | M8: =SUM(I8:K8) -> 256693.93 | O8: =SUM(I8:K8,D8:F8) -> 3087205.5 | Q8: -197470.43 | R8: -606339.84 | S8: 5937194.8 | U8: =SUM(Q8:S8) -> 5133384.5 | W8: 2244376.5 | X8: 2076926 | Y8: 6712436.7 | AA8: =SUM(W8:Y8) -> 11033739 | AC8: =SUM(W8:Y8,Q8:S8) -> 16167124 | AE8: =O8+AC8 -> 19254329 | AG8: 74253.42 | AH8: 1229218.5 | AI8: 1399196.6 | AK8: =SUM(AG8:AI8) -> 2702668.6 | AM8: 1727676.2 | AN8: 310421.74 | AO8: 4759198.2 | AQ8: =SUM(AM8:AO8) -> 6797296.1 | AS8: =SUM(AM8:AO8,AG8:AI8) -> 9499964.7 | AU8: 1071577.3 | AV8: 1270076.3 | AW8: 3460831.9 | AY8: =SUM(AU8:AW8) -> 5802485.6 | BA8: 251449.63 | BB8: 2165878.9 | BC8: 8544940.2 | BE8: =SUM(BA8:BC8) -> 10962269 | BG8: =SUM(BA8:BC8,AU8:AW8) -> 16764754 | BI8: =AS8+BG8 -> 26264719 | BJ8: =SUM(BJ6:BJ7) -> 1107961.6 | BK8: =SUM(BK6:BK7) -> 356637.57 | BL8: =SUM(BL6:BL7) -> 5526388 | BM8: =SUM(BM6:BM7) -> 4104404.4 | BN8: =SUM(BN6:BN7) -> 2266326.7 | BO8: =SUM(BO6:BO7) -> 4744375.1 | BP8: =SUM(BP6:BP7) -> 2363282.9 | BQ8: =SUM(BQ6:BQ7) -> 1967242.2 | ... BU8: =SUM(BU6:BU7) -> 4241327.3 | BW8: =SUM(BS8:BU8) -> 8303180.6 | BY8: =SUM(BS8:BU8,BP8:BR8) -> 15589707 | CA8: =SUM(CA6:CA7) -> 33695801 | CC8: =CC6+CC7 -> 1823210.1 | CD8: =CD6+CD7 -> 2383715.7 | CE8: =CE6+CE7 -> 4565343.7
B10: Apoio | C10: 3097.06 | D10: 45761.36 | E10: 41357.84 | F10: 179237.57 | G10: =SUM(D10:F10) -> 266356.77 | I10: -41623.05 | J10: 187462.07 | K10: -169417.16 | M10: =SUM(I10:K10) -> -23578.14 | O10: =SUM(I10:K10,D10:F10) -> 242778.63 | Q10: 63133.63 | R10: -208725.83 | S10: -304926.61 | U10: =SUM(Q10:S10) -> -450518.81 | W10: 64962.49 | X10: -408320.5 | Y10: -388305.66 | AA10: =SUM(W10:Y10) -> -731663.67 | AC10: =SUM(W10:Y10,Q10:S10) -> -1182182.5 | AE10: =O10+AC10 -> -939403.85 | AG10: 97102.96 | AH10: 301216.36 | AI10: -88491.62 | AK10: =SUM(AG10:AI10) -> 309827.7 | AM10: 113308.82 | AN10: 67062.17 | AO10: -111222.36 | AQ10: =SUM(AM10:AO10) -> 69148.63 | AS10: =SUM(AM10:AO10,AG10:AI10) -> 378976.33 | AU10: 103829.47 | AV10: -140484.96 | AW10: 170123.99 | AY10: =SUM(AU10:AW10) -> 133468.5 | BA10: -220088.02 | BB10: 900.53 | BC10: 94783.98 | BE10: =SUM(BA10:BC10) -> -124403.51 | BG10: =SUM(BA10:BC10,AU10:AW10) -> 9064.99 | BI10: =AS10+BG10 -> 388041.32 | BJ10: 8662.4 | BK10: -46398.02 | BL10: -198223.76 | BM10: 286595.95 | BN10: 250051.98 | BO10: 454587.93 | BP10: 531355.39 | BQ10: 457762.47 | BR10: 267242.22 | BS10: 668876.32 | BT10: 368998.71 | BU10: -137032.85 | BW10: =SUM(BS10:BU10) -> 900842.18 | BY10: =SUM(BS10:BU10,BP10:BR10) -> 2157202.3 | CA10: =SUM(BJ10:BL10)+SUM(BM10:BO10)+SUM(BP10:BR10)+SUM(BS10:BU10) -> 2912478.7 | CC10: -67205.14 | CD10: 307562.98 | CE10: 558365.81
B11: Service | C11: -682901.3 | D11: 992683.36 | E11: -497496.4 | F11: 560056.26 | G11: =SUM(D11:F11) -> 1055243.2 | I11: 50070 | J11: 52449.68 | K11: -58278.43 | M11: =SUM(I11:K11) -> 44241.25 | O11: =SUM(I11:K11,D11:F11) -> 1099484.5 | Q11: -107595.78 | R11: -143340.37 | S11: -49664.58 | U11: =SUM(Q11:S11) -> -300600.73 | W11: -83197.01 | X11: -191600.36 | Y11: -144210.21 | AA11: =SUM(W11:Y11) -> -419007.58 | AC11: =SUM(W11:Y11,Q11:S11) -> -719608.31 | AE11: =O11+AC11 -> 379876.16 | AG11: -132549.64 | AH11: -53812.19 | AI11: -164625.97 | AK11: =SUM(AG11:AI11) -> -350987.8 | AM11: -198315.59 | AN11: -50199.64 | AO11: 12376.66 | AQ11: =SUM(AM11:AO11) -> -236138.57 | AS11: =SUM(AM11:AO11,AG11:AI11) -> -587126.37 | AU11: -117486.72 | AV11: -47222 | AW11: 7254.56 | AY11: =SUM(AU11:AW11) -> -157454.16 | BA11: -74550.02 | BB11: -39497.45 | BC11: 46645.51 | BE11: =SUM(BA11:BC11) -> -67401.96 | BG11: =SUM(BA11:BC11,AU11:AW11) -> -224856.12 | BI11: =AS11+BG11 -> -811982.49 | BJ11: 21886.98 | BK11: -131785.62 | BL11: 92197.89 | BM11: 39268.28 | BN11: 324440.4 | BO11: 182046.23 | BP11: 167219.5 | BQ11: 129182.02 | BR11: 203916.29 | BS11: 245380.69 | BT11: 172928.84 | BU11: 212227.37 | BW11: =SUM(BS11:BU11) -> 630536.9 | BY11: =SUM(BS11:BU11,BP11:BR11) -> 1130854.7 | CA11: =SUM(BJ11:BL11)+SUM(BM11:BO11)+SUM(BP11:BR11)+SUM(BS11:BU11) -> 1658908.9 | CC11: 336620.5 | CD11: 238788.3 | CE11: 348085
B12: Sec | C12: -117389.37 | D12: 403864.17 | E12: 37532.65 | F12: 35087.87 | G12: =SUM(D12:F12) -> 476484.69 | I12: 20981.69 | J12: 302749.95 | K12: 24903.45 | M12: =SUM(I12:K12) -> 348635.09 | O12: =SUM(I12:K12,D12:F12) -> 825119.78 | Q12: 22459.15 | R12: 373949.41 | S12: 92606.79 | U12: =SUM(Q12:S12) -> 489015.35 | W12: 96234.81 | X12: 284203.71 | Y12: 192942.88 | AA12: =SUM(W12:Y12) -> 573381.4 | AC12: =SUM(W12:Y12,Q12:S12) -> 1062396.8 | AE12: =O12+AC12 -> 1887516.5 | AG12: 93813.74 | AH12: 135265.85 | AI12: 219542.37 | AK12: =SUM(AG12:AI12) -> 448621.96 | AM12: 114837.02 | AN12: 356560.25 | AO12: 208072.75 | AQ12: =SUM(AM12:AO12) -> 679470.02 | AS12: =SUM(AM12:AO12,AG12:AI12) -> 1128092 | AU12: 123558.82 | AV12: 40796.91 | AW12: 65236.66 | AY12: =SUM(AU12:AW12) -> 229592.39 | BA12: 171614.12 | BB12: -77824.7 | BC12: 584288.66 | BE12: =SUM(BA12:BC12) -> 678078.08 | BG12: =SUM(BA12:BC12,AU12:AW12) -> 907670.47 | BI12: =AS12+BG12 -> 2035762.5 | BJ12: 55268.02 | BK12: 91252.77 | BL12: 263356.18 | BM12: 62767.15 | BN12: 98598.14 | BO12: 54470.74 | BP12: 91139.91 | BQ12: 214580.78 | BR12: 198117.49 | BS12: 178204.25 | BT12: 188001.86 | BU12: 387325.03 | BW12: =SUM(BS12:BU12) -> 753531.14 | BY12: =SUM(BS12:BU12,BP12:BR12) -> 1257369.3 | CA12: =SUM(BJ12:BL12)+SUM(BM12:BO12)+SUM(BP12:BR12)+SUM(BS12:BU12) -> 1883082.3 | CC12: 56226.37 | CD12: 243037.75 | CE12: 521291.11
B13: Cebraco | C13: 156241.1 | D13: 251871.21 | E13: 45403.03 | F13: 327936.67 | G13: =SUM(D13:F13) -> 625210.91 | I13: 138298.78 | J13: 144880.25 | K13: 186119.58 | M13: =SUM(I13:K13) -> 469298.61 | O13: =SUM(I13:K13,D13:F13) -> 1094509.5 | Q13: 141568.1 | R13: 89515.94 | S13: 134228.26 | U13: =SUM(Q13:S13) -> 365312.3 | W13: 216658.5 | X13: 190560.57 | Y13: 195389.68 | AA13: =SUM(W13:Y13) -> 602608.75 | AC13: =SUM(W13:Y13,Q13:S13) -> 967921.05 | AE13: =O13+AC13 -> 2062430.6 | AG13: 281362.26 | AH13: 228173.23 | AI13: 367935.48 | AK13: =SUM(AG13:AI13) -> 877470.97 | AM13: 416560.49 | AN13: 493559.89 | AO13: 254753.61 | AQ13: =SUM(AM13:AO13) -> 1164874 | AS13: =SUM(AM13:AO13,AG13:AI13) -> 2042345 | AU13: 414080.85 | AV13: 435825.79 | AW13: 431763.56 | AY13: =SUM(AU13:AW13) -> 1281670.2 | BA13: 305013.57 | BB13: 298153 | BC13: 244333.2 | BE13: =SUM(BA13:BC13) -> 847499.77 | BG13: =SUM(BA13:BC13,AU13:AW13) -> 2129170 | BI13: =AS13+BG13 -> 4171514.9 | BJ13: 383753.36 | BK13: 247766.94 | BL13: 197344.81 | BM13: 348062.45 | BN13: 323628.41 | BO13: 296101.84 | BP13: 214279.3 | BQ13: 295074.06 | BR13: 255574.77 | BS13: 270061.93 | BT13: 196618.29 | BU13: 334510.67 | BW13: =SUM(BS13:BU13) -> 801190.89 | BY13: =SUM(BS13:BU13,BP13:BR13) -> 1566119 | CA13: =SUM(BJ13:BL13)+SUM(BM13:BO13)+SUM(BP13:BR13)+SUM(BS13:BU13) -> 3362776.8 | CC13: 294487.17 | CD13: 193404.44 | CE13: 504122.76
B14: Marumbi | C14: -10022.49 | D14: 6101.14 | E14: 5599.87 | F14: 8798.99 | G14: =SUM(D14:F14) -> 20500 | I14: 7479.12 | J14: 9028.82 | K14: 91166.22 | M14: =SUM(I14:K14) -> 107674.16 | O14: =SUM(I14:K14,D14:F14) -> 128174.16 | Q14: -80984.46 | R14: 6475.46 | S14: -102983.23 | U14: =SUM(Q14:S14) -> -177492.23 | W14: 5833.58 | X14: 5190.32 | Y14: 4246.43 | AA14: =SUM(W14:Y14) -> 15270.33 | AC14: =SUM(W14:Y14,Q14:S14) -> -162221.9 | AE14: =O14+AC14 -> -34047.74 | AG14: 4972.24 | AH14: 4496.2 | AI14: -90847.58 | AK14: =SUM(AG14:AI14) -> -81379.14 | AM14: 4208.76 | AN14: 328.11 | AO14: 2786.93 | AQ14: =SUM(AM14:AO14) -> 7323.8 | AS14: =SUM(AM14:AO14,AG14:AI14) -> -74055.34 | AU14: -74768.8 | AV14: -131095.45 | AW14: 3837.14 | AY14: =SUM(AU14:AW14) -> -202027.11 | BA14: -100170.1 | BB14: -1819.17 | BC14: -2292.54 | BE14: =SUM(BA14:BC14) -> -104281.81 | BG14: =SUM(BA14:BC14,AU14:AW14) -> -306308.92 | BI14: =AS14+BG14 -> -380364.26 | BJ14: -2520.6 | BK14: -3154.34 | BL14: -2221.54 | BM14: -1911.07 | BN14: -1765.32 | BO14: -13358.99 | BP14: -12817.43 | BQ14: -13598.6 | BR14: -13542.27 | BS14: -13644.72 | BT14: -15611.28 | BU14: -14857.27 | BW14: =SUM(BS14:BU14) -> -44113.27 | BY14: =SUM(BS14:BU14,BP14:BR14) -> -84071.57 | CA14: =SUM(BJ14:BL14)+SUM(BM14:BO14)+SUM(BP14:BR14)+SUM(BS14:BU14) -> -109003.43 | CC14: -17113.78 | CD14: -14676.51 | CE14: -115574.2
B15: Tec | C15: -791480.18 | D15: 731451.37 | E15: -308631 | F15: 199923.47 | G15: =SUM(D15:F15) -> 622743.84 | I15: -21687.43 | J15: 10700.66 | K15: -2039.33 | M15: =SUM(I15:K15) -> -13026.1 | O15: =SUM(I15:K15,D15:F15) -> 609717.74 | Q15: -20611.62 | R15: 3981.71 | S15: 13111.09 | U15: =SUM(Q15:S15) -> -3518.82 | W15: -79586.88 | X15: -148771.42 | Y15: -71492.45 | AA15: =SUM(W15:Y15) -> -299850.75 | AC15: =SUM(W15:Y15,Q15:S15) -> -303369.57 | AE15: =O15+AC15 -> 306348.17 | AG15: -26043.14 | AH15: 8362.07 | AI15: 168585.77 | AK15: =SUM(AG15:AI15) -> 150904.7 | AM15: -24037.35 | AN15: -16277.97 | AO15: 1932.08 | AQ15: =SUM(AM15:AO15) -> -38383.24 | AS15: =SUM(AM15:AO15,AG15:AI15) -> 112521.46 | AU15: 45009.27 | AV15: -19884.46 | AW15: -1861.78 | AY15: =SUM(AU15:AW15) -> 23263.03 | BA15: -67172.13 | BB15: -2038.33 | BC15: -6070.28 | BE15: =SUM(BA15:BC15) -> -75280.74 | BG15: =SUM(BA15:BC15,AU15:AW15) -> -52017.71 | BI15: =AS15+BG15 -> 60503.75 | BJ15: -40549.83 | BK15: -34014.34 | BL15: 2298.89 | BM15: 253236.47 | BN15: -91675.21 | BO15: -113088.48 | BP15: -139859.02 | BQ15: -10120.06 | BR15: -59334.21 | BS15: 186513.9 | BT15: -75603.34 | BU15: 32313.39 | BW15: =SUM(BS15:BU15) -> 143223.95 | BY15: =SUM(BS15:BU15,BP15:BR15) -> -66089.34 | CA15: =SUM(BJ15:BU15) -> -89881.84 | CC15: 6528.27 | CD15: -37526.59 | CE15: 76283.56
B16: Bariseg | C16: 384459.99 | D16: 392200.68 | E16: 398056.12 | F16: 375279.68 | G16: =SUM(D16:F16) -> 1165536.5 | I16: -14816.54 | J16: -10399 | K16: -2698.56 | M16: =SUM(I16:K16) -> -27914.1 | O16: =SUM(I16:K16,D16:F16) -> 1137622.4 | Q16: -1222.42 | R16: 13842.24 | S16: 56539.34 | U16: =SUM(Q16:S16) -> 69159.16 | W16: 31595.86 | X16: 25703.99 | Y16: -205781.68 | AA16: =SUM(W16:Y16) -> -148481.83 | AC16: =SUM(W16:Y16,Q16:S16) -> -79322.67 | AE16: =O16+AC16 -> 1058299.7 | AG16: 57666.95 | AH16: 27904.34 | AI16: 66053.48 | AK16: =SUM(AG16:AI16) -> 151624.77 | AM16: 89488.39 | AN16: 112473.42 | AO16: 112826.47 | AQ16: =SUM(AM16:AO16) -> 314788.28 | AS16: =SUM(AM16:AO16,AG16:AI16) -> 466413.05 | AU16: 105280.44 | AV16: 143270.29 | AW16: 159460.57 | AY16: =SUM(AU16:AW16) -> 408011.3 | BA16: 151077.13 | BB16: 187338.62 | BC16: 197245.09 | BE16: =SUM(BA16:BC16) -> 535660.84 | BG16: =SUM(BA16:BC16,AU16:AW16) -> 943672.14 | BI16: =AS16+BG16 -> 1410085.2 | BJ16: 207239.06 | BK16: 195013.08 | BL16: 144849.37 | BM16: 714727.3 | BN16: 777002.52 | BO16: 744540.08 | BP16: 672727.21 | BQ16: 726660.72 | BR16: 786885.56 | BS16: 1080237.8 | BT16: 791082.68 | BU16: 885803.25 | BW16: =SUM(BS16:BU16) -> 2757123.8 | BY16: =SUM(BS16:BU16,BP16:BR16) -> 4943397.3 | CA16: =SUM(BJ16:BU16) -> 7726768.7 | CC16: 828615.88 | CD16: 743112.13 | CE16: 853652.17
B17: DI | C17: 109356.42 | D17: 301296.69 | E17: 139257.8 | F17: 232489.41 | G17: =SUM(D17:F17) -> 673043.9 | I17: 263989.08 | J17: 49350.59 | K17: 39650.02 | M17: =SUM(I17:K17) -> 352989.69 | O17: =SUM(I17:K17,D17:F17) -> 1026033.6 | Q17: 112270.02 | R17: 124876.76 | S17: 45239.83 | U17: =SUM(Q17:S17) -> 282386.61 | W17: 134299.5 | X17: 83571.06 | Y17: 57294.26 | AA17: =SUM(W17:Y17) -> 275164.82 | AC17: =SUM(W17:Y17,Q17:S17) -> 557551.43 | AE17: =O17+AC17 -> 1583585 | AG17: 466252.26 | AH17: 248335.25 | AI17: 203476.8 | AK17: =SUM(AG17:AI17) -> 918064.31 | AM17: 282459.26 | AN17: 245432.29 | AO17: 206602.16 | AQ17: =SUM(AM17:AO17) -> 734493.71 | AS17: =SUM(AM17:AO17,AG17:AI17) -> 1652558 | AU17: 270758.64 | AV17: 266385.47 | AW17: 271784.93 | AY17: =SUM(AU17:AW17) -> 808929.04 | BA17: 249579.28 | BB17: 275812.11 | BC17: 211510.14 | BE17: =SUM(BA17:BC17) -> 736901.53 | BG17: =SUM(BA17:BC17,AU17:AW17) -> 1545830.6 | BI17: =AS17+BG17 -> 3198388.6 | BJ17: 240407.82 | BK17: 411839.17 | BL17: 279665.81 | BM17: 373531.63 | BN17: 295129.34 | BO17: 298405.16 | BP17: 423635.39 | BQ17: 406830.35 | BR17: 414584.86 | BS17: 503719.17 | BT17: 349160.14 | BU17: 326824.55 | BW17: =SUM(BS17:BU17) -> 1179703.9 | BY17: =SUM(BS17:BU17,BP17:BR17) -> 2424754.5 | CA17: =SUM(BJ17:BU17) -> 4323733.4 | CC17: 397092.06 | CD17: 252933.85 | CE17: 478274.25
B18: Bari Capital | BJ18: 25293.19 | BK18: 19767.84 | BL18: 20060.59 | BM18: 30800.68 | BN18: 15422.58 | BO18: 26663.53 | BP18: 51975.09 | BQ18: 44285.86 | BR18: 86107.31 | BS18: 79295.22 | BT18: 68143.26 | BU18: 77136.36 | BW18: =SUM(BS18:BU18) -> 224574.84 | BY18: =SUM(BS18:BU18,BP18:BR18) -> 406943.1 | CA18: =SUM(BJ18:BU18) -> 544951.51 | CC18: 113327.59 | CD18: -629.72 | CE18: -202789.07
B19: Resultado Coligadas | C19: -647967.51 | D19: 3413438.7 | E19: 76555.93 | F19: 1854471.9 | G19: =SUM(D19:F19) -> 5344466.5 | I19: 947786.42 | J19: 1044795.3 | K19: 383120.09 | M19: =SUM(I19:K19) -> 2375701.8 | O19: =SUM(I19:K19,D19:F19) -> 7720168.3 | Q19: 370689.56 | R19: 260575.32 | S19: -115849.11 | U19: =SUM(Q19:S19) -> 515415.77 | W19: 386800.85 | X19: -159462.63 | Y19: -359916.75 | AA19: =SUM(W19:Y19) -> -132578.53 | AC19: =SUM(W19:Y19,Q19:S19) -> 382837.24 | AE19: =O19+AC19 -> 8103005.5 | AG19: 842577.63 | AH19: 899941.11 | AI19: 681628.73 | AK19: =SUM(AG19:AI19) -> 2424147.5 | AM19: 798509.8 | AN19: 1208938.5 | AO19: 688128.3 | AQ19: =SUM(AM19:AO19) -> 2695576.6 | AS19: =SUM(AM19:AO19,AG19:AI19) -> 5119724.1 | AU19: 870261.97 | AV19: 547591.59 | AW19: 1107599.6 | AY19: =SUM(AU19:AW19) -> 2525453.2 | BA19: 415303.83 | BB19: 641024.61 | BC19: 1370443.8 | BE19: =SUM(BA19:BC19) -> 2426772.2 | BG19: =SUM(BA19:BC19,AU19:AW19) -> 4952225.4 | BI19: =AS19+BG19 -> 10071949 | BJ19: =SUM(BJ10:BJ18) -> 899440.4 | BK19: =SUM(BK10:BK18) -> 750287.48 | BL19: =SUM(BL10:BL18) -> 799328.24 | BM19: =SUM(BM10:BM18) -> 2107078.8 | BN19: =SUM(BN10:BN18) -> 1990832.8 | BO19: =SUM(BO10:BO18) -> 1930368 | BP19: =SUM(BP10:BP18) -> 1999655.3 | BQ19: =SUM(BQ10:BQ18) -> 2250657.6 | ... BU19: =SUM(BU10:BU18) -> 2104250.5 | BW19: =SUM(BS19:BU19) -> 7346614.3 | BY19: =SUM(BS19:BU19,BP19:BR19) -> 13736479 | CA19: =SUM(CA10:CA18) -> 22213815 | CC19: =SUM(CC10:CC18) -> 1948578.9 | CD19: =SUM(CD10:CD18) -> 1926006.6 | CE19: =SUM(CE10:CE18) -> 3021711.4
B21: Resultado Congl. + Coligadas | C21: -1949518 | D21: 569853.53 | E21: -655977.71 | F21: 8261102.2 | G21: =SUM(D21:F21) -> 8174978.1 | I21: -918167.08 | J21: 1018573 | K21: 2531989.8 | M21: =SUM(I21:K21) -> 2632395.7 | O21: =SUM(I21:K21,D21:F21) -> 10807374 | Q21: 173219.13 | R21: -345764.52 | S21: 5821345.6 | U21: =SUM(Q21:S21) -> 5648800.2 | W21: 2631177.4 | X21: 1917463.3 | Y21: 6352520 | AA21: =SUM(W21:Y21) -> 10901161 | AC21: =SUM(W21:Y21,Q21:S21) -> 16549961 | AE21: =O21+AC21 -> 27357335 | AG21: 916831.05 | AH21: 2129159.7 | AI21: 2080825.3 | AK21: =SUM(AG21:AI21) -> 5126816 | AM21: 2526186 | AN21: 1519360.3 | AO21: 5447326.5 | AQ21: =SUM(AM21:AO21) -> 9492872.7 | AS21: =SUM(AM21:AO21,AG21:AI21) -> 14619689 | AU21: 1941839.3 | AV21: 1817667.9 | AW21: 4568431.6 | AY21: =SUM(AU21:AW21) -> 8327938.8 | BA21: 666753.46 | BB21: 2806903.5 | BC21: 9915384 | BE21: =SUM(BA21:BC21) -> 13389041 | BG21: =SUM(BA21:BC21,AU21:AW21) -> 21716980 | BI21: =AS21+BG21 -> 36336669 | BJ21: =BJ8+BJ19 -> 2007402 | BK21: =BK8+BK19 -> 1106925.1 | BL21: =BL8+BL19 -> 6325716.2 | BM21: =BM8+BM19 -> 6211483.2 | BN21: =BN8+BN19 -> 4257159.5 | BO21: =BO8+BO19 -> 6674743.2 | BP21: =BP8+BP19 -> 4362938.2 | BQ21: =BQ8+BQ19 -> 4217899.8 | ... BU21: =BU8+BU19 -> 6345577.8 | BW21: =SUM(BS21:BU21) -> 15649795 | BY21: =SUM(BS21:BU21,BP21:BR21) -> 29326187 | CA21: =CA19+CA8 -> 55909616 | CC21: =CC8+CC19 -> 3771789.1 | CD21: =CD8+CD19 -> 4309722.3 | CE21: =CE8+CE19 -> 7587055.1
B23: BR Cards | C23: -744679.01 | D23: 2842467.5 | E23: -84774.05 | F23: 1734470.1 | G23: =SUM(D23:F23) -> 4492163.5 | I23: 336223.28 | J23: 424533.92 | K23: 146560.61 | M23: =SUM(I23:K23) -> 907317.81 | O23: =SUM(I23:K23,D23:F23) -> 5399481.3 | Q23: 91429.05 | R23: -137973.28 | S23: -239435.31 | U23: =SUM(Q23:S23) -> -285979.54 | W23: 273119.44 | X23: -431524.45 | Y23: -600734.72 | AA23: =SUM(W23:Y23) -> -759139.73 | AC23: =SUM(W23:Y23,Q23:S23) -> -1045119.3 | AE23: =O23+AC23 -> 4354362 | AG23: 767440.02 | AH23: 750979.9 | AI23: 432757.06 | AK23: =SUM(AG23:AI23) -> 1951177 | AM23: 662524.89 | AN23: 842029.62 | AO23: 593382.21 | AQ23: =SUM(AM23:AO23) -> 2097936.7 | AS23: =SUM(AM23:AO23,AG23:AI23) -> 4049113.7 | AU23: 744180.93 | AV23: 486306.52 | AW23: 1014721.4 | AY23: =SUM(AU23:AW23) -> 2245208.9 | BA23: 214691.41 | BB23: 875982.28 | BC23: 798970.02 | BE23: =SUM(BA23:BC23) -> 1889643.7 | BG23: =SUM(BA23:BC23,AU23:AW23) -> 4134852.6 | BI23: =AS23+BG23 -> 8183966.3 | BJ23: 828965.29 | BK23: 642854.08 | BL23: 537859.73 | BM23: 2092438.7 | BN23: 1856223.5 | BO23: 1915228.4 | BP23: 1829491.1 | BQ23: 2018509.1 | BR23: 2651795.3 | BS23: 2635218.8 | BT23: 1724928.1 | BU23: 1816891.3 | BW23: =SUM(BS23:BU23) -> 6177038.2 | BY23: =SUM(BS23:BU23,BP23:BR23) -> 12676834 | CA23: 21120255 | CC23: 1918146.6 | CD23: 1655619 | CE23: 2648896.4
B24: Resultado MEP | CC24: 1872781.9 | CD24: 1605888.7 | CE24: 2563268.6
B25: Resulta Br Cards | CA25: =CA23-#REF!-#REF! -> #REF! | CC25: 45364.75 | CD25: 49730.27 | CE25: =CE23-CE24 -> 85627.77
B26: RES. TOTAL | C26: =C21+#REF! -> #REF! | D26: =D21+#REF! -> #REF! | E26: =E21+#REF! -> #REF! | F26: =F21+#REF! -> #REF! | G26: =G21+#REF! -> #REF! | I26: =I21+#REF! -> #REF! | J26: =J21+#REF! -> #REF! | K26: =K21+#REF! -> #REF! | M26: =SUM(I26:K26) -> #REF! | O26: =SUM(I26:K26,D26:F26) -> #REF! | Q26: =Q21+#REF! -> #REF! | R26: =R21+#REF! -> #REF! | S26: =S21+#REF! -> #REF! | U26: =SUM(Q26:S26) -> #REF! | W26: =W21+#REF! -> #REF! | X26: =X21+#REF! -> #REF! | Y26: =Y21+#REF! -> #REF! | AA26: =SUM(W26:Y26) -> #REF! | AC26: =SUM(W26:Y26,Q26:S26) -> #REF! | AE26: =AE21+#REF! -> #REF! | AG26: =AG21+#REF! -> #REF! | AH26: =AH21+#REF! -> #REF! | AI26: =AI21+#REF! -> #REF! | AK26: =AK21+#REF! -> #REF! | AM26: =AM21+#REF! -> #REF! | AN26: =AN21+#REF! -> #REF! | AO26: =AO21+#REF! -> #REF! | AQ26: =SUM(AM26:AO26) -> #REF! | AS26: =SUM(AM26:AO26,AG26:AI26) -> #REF! | AU26: =AU21+#REF! -> #REF! | AV26: =AV21+#REF! -> #REF! | AW26: =AW21+#REF! -> #REF! | AY26: =SUM(AU26:AW26) -> #REF! | BA26: =BA21+#REF! -> #REF! | BB26: =BB21+#REF! -> #REF! | BC26: =BC21+#REF! -> #REF! | BE26: =SUM(BA26:BC26) -> #REF! | BG26: =SUM(BA26:BC26,AU26:AW26) -> #REF! | BI26: =BI21+#REF! -> #REF! | BJ26: =BJ21+#REF! -> #REF! | BK26: =BK21+#REF! -> #REF! | BL26: =BL21+#REF! -> #REF! | BM26: =BM21+#REF! -> #REF! | BN26: =BN21+#REF! -> #REF! | BO26: =BO21+#REF! -> #REF! | BP26: =BP21+#REF! -> #REF! | ... BU26: =BU21+#REF! -> #REF! | BW26: =SUM(BS26:BU26) -> #REF! | BY26: =#REF!+BW26 -> #REF! | CA26: =CA21+CA25 -> #REF! | CC26: =CC21+CC25 -> 3817153.8 | CD26: =CD21+CD25 -> 4359452.6 | CE26: =CE21+CE25 -> 7672682.9

Sheet P&L Mensal
B1: Data Base -> | F1: 46112
C3: CONSIGNADO | F3: IMOBILIARIO | I3: TOTAL | N3: IPCA
C4: Realizado | D4: Orçado | E4: ∆ (%) | F4: Realizado | G4: Orçado | H4: ∆ (%) | I4: Realizado | J4: Orçado | K4: ∆ (%) | L4: ∆ (R$) | O4: Realizado | P4: Orçado
B5: RECEITAS | C5: =C6+C13+C15+C16+C17+C18+C14+C19+C20 -> 7877352.9 | D5: =D6+D13+D15+D16+D17+D18+D14+D19+D20 -> 7759392.7 | E5: =IFERROR(C5/D5-1,"-") -> 0.015202255 | F5: =F6+F13+F15+F16+F17+F18+F14+F19+F20 -> 33774613 | G5: =G6+G13+G15+G16+G17+G18+G14+G19+G20 -> 29464374 | H5: =IFERROR(F5/G5-1,"-") -> 0.14628643 | I5: =I6+I13+I15+I16+I17+I18+I14+I19+I20 -> 41651965 | J5: =J6+J13+J15+J16+J17+J18+J14+J19+J20 -> 37223767 | K5: =IFERROR(I5/J5-1,"-") -> 0.11896159 | L5: =I5-J5 -> 4428198.4 | N5: 46023 | O5: 0.0033 | P5: 0.0033
B6: Operações de Crédito | C6: =SUM(C7:C12) -> 7868473.4 | D6: =SUM(D7:D12) -> 7746926.1 | E6: =IFERROR(C6/D6-1,"-") -> 0.015689749 | F6: =SUM(F7:F12) -> 29656161 | G6: =SUM(G7:G12) -> 26280606 | H6: =IFERROR(F6/G6-1,"-") -> 0.12844279 | I6: =C6+F6 -> 37524634 | J6: =D6+G6 -> 34027532 | K6: =IFERROR(I6/J6-1,"-") -> 0.10277271 | L6: =I6-J6 -> 3497101.8 | N6: 46054 | O6: 0.007 | P6: 0.0033
B7: Receita Juros | C7: =INDEX(Realizado!41:41,MATCH('P&L Mensal'!$F$1,Realizado!$2:$2,0))+INDEX(Realizado!42:42,MATCH('P&L Mensal'!$F$1,Realizado!$2:$2,0)) -> 6041460.8 | D7: =INDEX('Orçado '!44:44,MATCH('P&L Mensal'!$F$1,'Orçado '!$2:$2,0))+INDEX('Orçado '!45:45,MATCH('P&L Mensal'!$F$1,'Orçado '!$2:$2,0)) -> 6046154.6 | E7: =IFERROR(C7/D7-1,"-") -> -0.00077634449 | F7: =INDEX(Realizado!83:83,MATCH('P&L Mensal'!$F$1,Realizado!$2:$2,0))+INDEX(Realizado!84:84,MATCH('P&L Mensal'!$F$1,Realizado!$2:$2,0)) -> 21983325 | G7: =INDEX('Orçado '!85:85,MATCH('P&L Mensal'!$F$1,'Orçado '!$2:$2,0))+INDEX('Orçado '!86:86,MATCH('P&L Mensal'!$F$1,'Orçado '!$2:$2,0)) -> 20556772 | H7: =IFERROR(F7/G7-1,"-") -> 0.0693958 | I7: =C7+F7 -> 28024786 | J7: =D7+G7 -> 26602926 | K7: =IFERROR(I7/J7-1,"-") -> 0.053447493 | L7: =I7-J7 -> 1421859.7 | N7: 46082 | O7: 0.0088 | P7: 0.0033
B10: Receita CM - Crédito Imobiliário | C10: =INDEX(Realizado!43:43,MATCH('P&L Mensal'!$F$1,Realizado!$2:$2,0)) -> 0 | D10: =INDEX('Orçado '!46:46,MATCH('P&L Mensal'!$F$1,'Orçado '!$2:$2,0)) -> 0 | E10: =IFERROR(C10/D10-1,"-") -> - | F10: =INDEX(Realizado!85:85,MATCH('P&L Mensal'!$F$1,Realizado!$2:$2,0)) -> 7200722.4 | G10: =INDEX('Orçado '!87:87,MATCH('P&L Mensal'!$F$1,'Orçado '!$2:$2,0)) -> 5309468.9 | H10: =IFERROR(F10/G10-1,"-") -> 0.35620388 | I10: =C10+F10 -> 7200722.4 | J10: =D10+G10 -> 5309468.9 | K10: =IFERROR(I10/J10-1,"-") -> 0.35620388 | L10: =I10-J10 -> 1891253.4
B11: Multa + Mora - Crédito Imobiliário | C11: =INDEX(Realizado!44:44,MATCH('P&L Mensal'!$F$1,Realizado!$2:$2,0)) -> 0 | D11: =INDEX('Orçado '!47:47,MATCH('P&L Mensal'!$F$1,'Orçado '!$2:$2,0)) -> 0 | E11: =IFERROR(C11/D11-1,"-") -> - | F11: =INDEX(Realizado!86:86,MATCH('P&L Mensal'!$F$1,Realizado!$2:$2,0)) -> 394865.93 | G11: =INDEX('Orçado '!88:88,MATCH('P&L Mensal'!$F$1,'Orçado '!$2:$2,0)) -> 372913.43 | H11: =IFERROR(F11/G11-1,"-") -> 0.058867538 | I11: =C11+F11 -> 394865.93 | J11: =D11+G11 -> 372913.43 | K11: =IFERROR(I11/J11-1,"-") -> 0.058867538 | L11: =I11-J11 -> 21952.496
B12: Receita Juros - Cartão | C12: =INDEX(Realizado!45:45,MATCH('P&L Mensal'!$F$1,Realizado!$2:$2,0)) -> 1827012.7 | D12: =INDEX('Orçado '!48:48,MATCH('P&L Mensal'!$F$1,'Orçado '!$2:$2,0)) -> 1700771.4 | E12: =IFERROR(C12/D12-1,"-") -> 0.074225863 | F12: =INDEX(Realizado!87:87,MATCH('P&L Mensal'!$F$1,Realizado!$2:$2,0)) -> 77247.43 | G12: =INDEX('Orçado '!89:89,MATCH('P&L Mensal'!$F$1,'Orçado '!$2:$2,0)) -> 41452.468 | H12: =IFERROR(F12/G12-1,"-") -> 0.86351823 | I12: =C12+F12 -> 1904260.1 | J12: =D12+G12 -> 1742223.9 | K12: =IFERROR(I12/J12-1,"-") -> 0.093005376 | L12: =I12-J12 -> 162036.19
B13: Receita Serviços | C13: =INDEX(Realizado!46:46,MATCH('P&L Mensal'!$F$1,Realizado!$2:$2,0)) -> 0 | D13: =INDEX('Orçado '!49:49,MATCH('P&L Mensal'!$F$1,'Orçado '!$2:$2,0)) -> 0 | E13: =IFERROR(C13/D13-1,"-") -> - | F13: =INDEX(Realizado!88:88,MATCH('P&L Mensal'!$F$1,Realizado!$2:$2,0)) -> 2558364.6 | G13: =INDEX('Orçado '!90:90,MATCH('P&L Mensal'!$F$1,'Orçado '!$2:$2,0)) -> 1754400 | H13: =IFERROR(F13/G13-1,"-") -> 0.45825613 | I13: =C13+F13 -> 2558364.6 | J13: =D13+G13 -> 1754400 | K13: =IFERROR(I13/J13-1,"-") -> 0.45825613 | L13: =I13-J13 -> 803964.56
B14: Receita Interchange | C14: =INDEX(Realizado!47:47,MATCH('P&L Mensal'!$F$1,Realizado!$2:$2,0)) -> 8879.4971 | D14: =INDEX('Orçado '!52:52,MATCH('P&L Mensal'!$F$1,'Orçado '!$2:$2,0)) -> 12466.562 | E14: =IFERROR(C14/D14-1,"-") -> -0.28773487 | F14: =INDEX(Realizado!89:89,MATCH('P&L Mensal'!$F$1,Realizado!$2:$2,0)) -> 11964.393 | G14: =INDEX('Orçado '!93:93,MATCH('P&L Mensal'!$F$1,'Orçado '!$2:$2,0)) -> 16829.858 | H14: =IFERROR(F14/G14-1,"-") -> -0.28909723 | I14: =C14+F14 -> 20843.89 | J14: =D14+G14 -> 29296.42 | K14: =IFERROR(I14/J14-1,"-") -> -0.2885175 | L14: =I14-J14 -> -8452.53
B15: Receita Comissão CRI | C15: =INDEX(Realizado!48:48,MATCH('P&L Mensal'!$F$1,Realizado!$2:$2,0)) -> 0 | D15: =INDEX('Orçado '!53:53,MATCH('P&L Mensal'!$F$1,'Orçado '!$2:$2,0)) -> 0 | E15: =IFERROR(C15/D15-1,"-") -> - | F15: =INDEX(Realizado!90:90,MATCH('P&L Mensal'!$F$1,Realizado!$2:$2,0)) -> 0 | G15: =INDEX('Orçado '!94:94,MATCH('P&L Mensal'!$F$1,'Orçado '!$2:$2,0)) -> 0 | H15: =IFERROR(F15/G15-1,"-") -> - | I15: =C15+F15 -> 0 | J15: =D15+G15 -> 0 | K15: =IFERROR(I15/J15-1,"-") -> - | L15: =I15-J15 -> 0
B16: Receita Cobrança Ext. Cebraco | C16: =INDEX(Realizado!49:49,MATCH('P&L Mensal'!$F$1,Realizado!$2:$2,0)) -> 0 | D16: =INDEX('Orçado '!54:54,MATCH('P&L Mensal'!$F$1,'Orçado '!$2:$2,0)) -> 0 | E16: =IFERROR(C16/D16-1,"-") -> - | F16: =INDEX(Realizado!91:91,MATCH('P&L Mensal'!$F$1,Realizado!$2:$2,0)) -> 155899.01 | G16: =INDEX('Orçado '!95:95,MATCH('P&L Mensal'!$F$1,'Orçado '!$2:$2,0)) -> 282753.77 | H16: =IFERROR(F16/G16-1,"-") -> -0.44864039 | I16: =C16+F16 -> 155899.01 | J16: =D16+G16 -> 282753.77 | K16: =IFERROR(I16/J16-1,"-") -> -0.44864039 | L16: =I16-J16 -> -126854.76
B17: Resultado de Seguros | C17: =INDEX(Realizado!53:53,MATCH('P&L Mensal'!$F$1,Realizado!$2:$2,0)) -> 0 | D17: =INDEX('Orçado '!58:58,MATCH('P&L Mensal'!$F$1,'Orçado '!$2:$2,0)) -> 0 | E17: =IFERROR(C17/D17-1,"-") -> - | F17: =INDEX(Realizado!95:95,MATCH('P&L Mensal'!$F$1,Realizado!$2:$2,0)) -> 1006702.7 | G17: =INDEX('Orçado '!99:99,MATCH('P&L Mensal'!$F$1,'Orçado '!$2:$2,0)) -> 900000 | H17: =IFERROR(F17/G17-1,"-") -> 0.11855856 | I17: =C17+F17 -> 1006702.7 | J17: =D17+G17 -> 900000 | K17: =IFERROR(I17/J17-1,"-") -> 0.11855856 | L17: =I17-J17 -> 106702.7
B18: Resultado Brasil Cards | C18: =INDEX(Realizado!54:54,MATCH('P&L Mensal'!$F$1,Realizado!$2:$2,0)) -> 0 | D18: =INDEX('Orçado '!59:59,MATCH('P&L Mensal'!$F$1,'Orçado '!$2:$2,0)) -> 0 | E18: =IFERROR(C18/D18-1,"-") -> - | F18: =INDEX(Realizado!96:96,MATCH('P&L Mensal'!$F$1,Realizado!$2:$2,0)) -> 126708.72 | G18: =INDEX('Orçado '!100:100,MATCH('P&L Mensal'!$F$1,'Orçado '!$2:$2,0)) -> -163.435 | H18: =IFERROR(F18/G18-1,"-") -> -776.2851 | I18: =C18+F18 -> 126708.72 | J18: =D18+G18 -> -163.435 | K18: =IFERROR(I18/J18-1,"-") -> -776.2851 | L18: =I18-J18 -> 126872.15
B19: Resultado Bari Capital | C19: =INDEX(Realizado!55:55,MATCH('P&L Mensal'!$F$1,Realizado!$2:$2,0)) -> 0 | D19: =INDEX('Orçado '!60:60,MATCH('P&L Mensal'!$F$1,'Orçado '!$2:$2,0)) -> 0 | E19: =IFERROR(C19/D19-1,"-") -> - | F19: =INDEX(Realizado!97:97,MATCH('P&L Mensal'!$F$1,Realizado!$2:$2,0)) -> -262478.75 | G19: =INDEX('Orçado '!101:101,MATCH('P&L Mensal'!$F$1,'Orçado '!$2:$2,0)) -> 19800 | H19: =IFERROR(F19/G19-1,"-") -> -14.256503 | I19: =C19+F19 -> -262478.75 | J19: =D19+G19 -> 19800 | K19: =IFERROR(I19/J19-1,"-") -> -14.256503 | L19: =I19-J19 -> -282278.75
B20: Resultado Sec | C20: 0 | D20: 0 | E20: =IFERROR(C20/D20-1,"-") -> - | F20: =INDEX(Realizado!120:120,MATCH('P&L Mensal'!$F$1,Realizado!$2:$2,0)) -> 521291.11 | G20: =INDEX('Orçado '!102:102,MATCH('P&L Mensal'!$F$1,'Orçado '!$2:$2,0)) -> 210147.87 | H20: =IFERROR(F20/G20-1,"-") -> 1.480592 | I20: =C20+F20 -> 521291.11 | J20: =D20+G20 -> 210147.87 | K20: =IFERROR(I20/J20-1,"-") -> 1.480592 | L20: =I20-J20 -> 311143.24
B21: DESPESAS DE ORIGINAÇÃO | C21: =C22 -> -4803644.1 | D21: =D22 -> -4620516.9 | E21: =IFERROR(C21/D21-1,"-") -> 0.039633491 | F21: =F22 -> -17862654 | G21: =G22 -> -15301310 | H21: =IFERROR(F21/G21-1,"-") -> 0.16739376 | I21: =I22 -> -22666298 | J21: =J22 -> -19921827 | K21: =IFERROR(I21/J21-1,"-") -> 0.13776202 | L21: =ABS(I21)-ABS(J21) -> 2744471.1
B22: Despesa de Captação* | C22: =C23+C26+C27+C28 -> -4803644.1 | D22: =D23+D26+D27+D28 -> -4620516.9 | E22: =IFERROR(C22/D22-1,"-") -> 0.039633491 | F22: =F23+F26+F27+F28 -> -17862654 | G22: =G23+G26+G27+G28 -> -15301310 | H22: =IFERROR(F22/G22-1,"-") -> 0.16739376 | I22: =C22+F22 -> -22666298 | J22: =D22+G22 -> -19921827 | K22: =IFERROR(I22/J22-1,"-") -> 0.13776202 | L22: =ABS(I22)-ABS(J22) -> 2744471.1
B23: Inflação | C23: =INDEX(Realizado!58:58,MATCH('P&L Mensal'!$F$1,Realizado!$2:$2,0)) -> 0 | D23: =INDEX('Orçado '!63:63,MATCH('P&L Mensal'!$F$1,'Orçado '!$2:$2,0)) -> 0 | E23: =IFERROR(C23/D23-1,"-") -> - | F23: =INDEX(Realizado!100:100,MATCH('P&L Mensal'!$F$1,Realizado!$2:$2,0)) -> -6665373.2 | G23: =INDEX('Orçado '!105:105,MATCH('P&L Mensal'!$F$1,'Orçado '!$2:$2,0)) -> -5380522.2 | H23: =IFERROR(F23/G23-1,"-") -> 0.23879672 | I23: =C23+F23 -> -6665373.2 | J23: =D23+G23 -> -5380522.2 | K23: =IFERROR(I23/J23-1,"-") -> 0.23879672 | L23: =ABS(I23)-ABS(J23) -> 1284851
B24: Componente Juros | F24: =INDEX(Realizado!101:101,MATCH('P&L Mensal'!$F$1,Realizado!$2:$2,0)) -> 0 | G24: =INDEX('Orçado '!106:106,MATCH('P&L Mensal'!$F$1,'Orçado '!$2:$2,0)) -> -2734250.7 | I24: =C24+F24 -> 0 | J24: =D24+G24 -> -2734250.7
B25: Componente Inflação | F25: =INDEX(Realizado!102:102,MATCH('P&L Mensal'!$F$1,Realizado!$2:$2,0)) -> 0 | G25: =INDEX('Orçado '!107:107,MATCH('P&L Mensal'!$F$1,'Orçado '!$2:$2,0)) -> -1783873.7 | I25: =C25+F25 -> 0 | J25: =D25+G25 -> -1783873.7
B26: DI/Pré | C26: =INDEX(Realizado!59:59,MATCH('P&L Mensal'!$F$1,Realizado!$2:$2,0)) -> -5760280.5 | D26: =INDEX('Orçado '!64:64,MATCH('P&L Mensal'!$F$1,'Orçado '!$2:$2,0)) -> -5697287.1 | E26: =IFERROR(C26/D26-1,"-") -> 0.011056736 | F26: =INDEX(Realizado!103:103,MATCH('P&L Mensal'!$F$1,Realizado!$2:$2,0)) -> -13440654 | G26: =INDEX('Orçado '!108:108,MATCH('P&L Mensal'!$F$1,'Orçado '!$2:$2,0)) -> -12757576 | H26: =IFERROR(F26/G26-1,"-") -> 0.053542988 | I26: =C26+F26 -> -19200935 | J26: =D26+G26 -> -18454863 | K26: =IFERROR(I26/J26-1,"-") -> 0.040426859 | L26: =ABS(I26)-ABS(J26) -> 746072.13
B27: Receita Financeira + Outros | C27: =+INDEX(Realizado!60:60,MATCH('P&L Mensal'!$F$1,Realizado!$2:$2,0)) -> 683833.18 | D27: =+INDEX('Orçado '!65:65,MATCH('P&L Mensal'!$F$1,'Orçado '!$2:$2,0)) -> 685924.94 | E27: =IFERROR(C27/D27-1,"-") -> -0.0030495583 | F27: =+INDEX(Realizado!104:104,MATCH('P&L Mensal'!$F$1,Realizado!$2:$2,0)) -> 2424498.8 | G27: =+INDEX('Orçado '!109:109,MATCH('P&L Mensal'!$F$1,'Orçado '!$2:$2,0)) -> 2565677.8 | H27: =IFERROR(F27/G27-1,"-") -> -0.055025999 | I27: =C27+F27 -> 3108332 | J27: =D27+G27 -> 3251602.8 | K27: =IFERROR(I27/J27-1,"-") -> -0.044061579 | L27: =ABS(I27)-ABS(J27) -> -143270.75
B28: Swap | C28: =+INDEX(Realizado!61:61,MATCH('P&L Mensal'!$F$1,Realizado!$2:$2,0)) -> 272803.21 | D28: =+INDEX('Orçado '!66:66,MATCH('P&L Mensal'!$F$1,'Orçado '!$2:$2,0)) -> 390845.25 | E28: =IFERROR(C28/D28-1,"-") -> -0.30201734 | F28: =+INDEX(Realizado!105:105,MATCH('P&L Mensal'!$F$1,Realizado!$2:$2,0)) -> -181125.23 | G28: =+INDEX('Orçado '!110:110,MATCH('P&L Mensal'!$F$1,'Orçado '!$2:$2,0)) -> 271109.87 | H28: =IFERROR(F28/G28-1,"-") -> -1.6680879 | I28: =C28+F28 -> 91677.98 | J28: =D28+G28 -> 661955.12 | K28: =IFERROR(I28/J28-1,"-") -> -0.86150424 | L28: =ABS(I28)-ABS(J28) -> -570277.14
B29: Impostos Diretos | C29: =INDEX(Realizado!62:62,MATCH('P&L Mensal'!$F$1,Realizado!$2:$2,0)) -> -220529.89 | D29: =INDEX('Orçado '!67:67,MATCH('P&L Mensal'!$F$1,'Orçado '!$2:$2,0)) -> -169005.8 | E29: =IFERROR(C29/D29-1,"-") -> 0.30486581 | F29: =INDEX(Realizado!106:106,MATCH('P&L Mensal'!$F$1,Realizado!$2:$2,0)) -> -871661.11 | G29: =INDEX('Orçado '!111:111,MATCH('P&L Mensal'!$F$1,'Orçado '!$2:$2,0)) -> -599202.39 | H29: =IFERROR(F29/G29-1,"-") -> 0.45470232 | I29: =C29+F29 -> -1092191 | J29: =D29+G29 -> -768208.19 | K29: =IFERROR(I29/J29-1,"-") -> 0.42173829 | L29: =ABS(I29)-ABS(J29) -> 323982.81
B30: MARGEM INTERMEDIAÇÃO | C30: =C5+C21+C29 -> 2853178.9 | D30: =D5+D21+D29 -> 2969870 | E30: =IFERROR(C30/D30-1,"-") -> -0.039291633 | F30: =F5+F21+F29 -> 15040297 | G30: =G5+G21+G29 -> 13563862 | H30: =IFERROR(F30/G30-1,"-") -> 0.10885068 | I30: =I5+I21+I29 -> 17893476 | J30: =J5+J21+J29 -> 16533732 | K30: =IFERROR(I30/J30-1,"-") -> 0.082240631 | L30: =ABS(I30)-ABS(J30) -> 1359744.5
B31: Provisões | C31: =SUM(C32:C33) -> -610260.52 | D31: =SUM(D32:D33) -> -577819.12 | E31: =IFERROR(C31/D31-1,"-") -> 0.056144559 | F31: =SUM(F32:F33) -> -439697.65 | G31: =SUM(G32:G33) -> -1292046.2 | H31: =IFERROR(F31/G31-1,"-") -> -0.65968892 | I31: =C31+F31 -> -1049958.2 | J31: =D31+G31 -> -1869865.4 | K31: =IFERROR(I31/J31-1,"-") -> -0.43848461 | L31: =ABS(I31)-ABS(J31) -> -819907.19
B32: Provisões | C32: =INDEX(Realizado!65:65,MATCH('P&L Mensal'!$F$1,Realizado!$2:$2,0)) -> -610260.52 | D32: =INDEX('Orçado '!69:69,MATCH('P&L Mensal'!$F$1,'Orçado '!$2:$2,0)) -> -577819.12 | E32: =IFERROR(C32/D32-1,"-") -> 0.056144559 | F32: =INDEX(Realizado!109:109,MATCH('P&L Mensal'!$F$1,Realizado!$2:$2,0)) -> -439697.65 | G32: =INDEX('Orçado '!113:113,MATCH('P&L Mensal'!$F$1,'Orçado '!$2:$2,0)) -> -1292046.2 | H32: =IFERROR(F32/G32-1,"-") -> -0.65968892 | I32: =C32+F32 -> -1049958.2 | J32: =D32+G32 -> -1869865.4 | K32: =IFERROR(I32/J32-1,"-") -> -0.43848461 | L32: =ABS(I32)-ABS(J32) -> -819907.19
B33: Desvalorização de BNDU | C33: =INDEX(Realizado!66:66,MATCH('P&L Mensal'!$F$1,Realizado!$2:$2,0)) -> 0 | D33: 0 | E33: =IFERROR(C33/D33-1,"-") -> - | F33: =INDEX(Realizado!110:110,MATCH('P&L Mensal'!$F$1,Realizado!$2:$2,0)) -> 0 | G33: 0 | H33: =IFERROR(F33/G33-1,"-") -> - | I33: =C33+F33 -> 0 | J33: =D33+G33 -> 0 | K33: =IFERROR(I33/J33-1,"-") -> - | L33: =I33-J33 -> 0
B34: MG INTERMEDIAÇÃO LIQ | C34: =C30+C31 -> 2242918.4 | D34: =D30+D31 -> 2392050.8 | E34: =IFERROR(C34/D34-1,"-") -> -0.062345013 | F34: =F30+F31 -> 14600600 | G34: =G30+G31 -> 12271816 | H34: =IFERROR(F34/G34-1,"-") -> 0.18976688 | I34: =I30+I31 -> 16843518 | J34: =J30+J31 -> 14663866 | K34: =IFERROR(I34/J34-1,"-") -> 0.148641 | L34: =ABS(I34)-ABS(J34) -> 2179651.7
B35: Despesas Administrativas Diretas | C35: =INDEX(Realizado!68:68,MATCH('P&L Mensal'!$F$1,Realizado!$2:$2,0)) -> -466515.01 | D35: =INDEX('Orçado '!71:71,MATCH('P&L Mensal'!$F$1,'Orçado '!$2:$2,0)) -> -486890.14 | E35: =IFERROR(C35/D35-1,"-") -> -0.041847489 | F35: =INDEX(Realizado!112:112,MATCH('P&L Mensal'!$F$1,Realizado!$2:$2,0)) -> -1829214.4 | G35: =INDEX('Orçado '!115:115,MATCH('P&L Mensal'!$F$1,'Orçado '!$2:$2,0)) -> -2394625.7 | H35: =IFERROR(F35/G35-1,"-") -> -0.23611677 | I35: =C35+F35 -> -2295729.4 | J35: =D35+G35 -> -2881515.8 | K35: =IFERROR(I35/J35-1,"-") -> -0.20329106 | L35: =ABS(I35)-ABS(J35) -> -585786.41
B36: Comissão (Apoio - Comercial - Mídia Paga) | C36: =INDEX(Realizado!70:70,MATCH('P&L Mensal'!$F$1,Realizado!$2:$2,0)) -> -40765.595 | D36: =INDEX('Orçado '!72:72,MATCH('P&L Mensal'!$F$1,'Orçado '!$2:$2,0)) -> 0 | E36: =IFERROR(C36/D36-1,"-") -> - | F36: =INDEX(Realizado!114:114,MATCH('P&L Mensal'!$F$1,Realizado!$2:$2,0)) -> -144532.27 | G36: =INDEX('Orçado '!116:116,MATCH('P&L Mensal'!$F$1,'Orçado '!$2:$2,0)) -> -233766.23 | H36: =IFERROR(F36/G36-1,"-") -> -0.38172309 | I36: =C36+F36 -> -185297.86 | J36: =D36+G36 -> -233766.23 | K36: =IFERROR(I36/J36-1,"-") -> -0.20733693 | L36: =ABS(I36)-ABS(J36) -> -48468.374
B37: MG CONTRIBUIÇÃO DIRETA | C37: =C34+C35+C36 -> 1735637.8 | D37: =D34+D35+D36 -> 1905160.7 | E37: =IFERROR(C37/D37-1,"-") -> -0.088980896 | F37: =F34+F35+F36 -> 12626853 | G37: =G34+G35+G36 -> 9643423.6 | H37: =IFERROR(F37/G37-1,"-") -> 0.30937451 | I37: =I34+I35+I36 -> 14362491 | J37: =J34+J35+J36 -> 11548584 | K37: =IFERROR(I37/J37-1,"-") -> 0.24365813 | L37: =ABS(I37)-ABS(J37) -> 2813906.5
B38: Desp. Administrativas Indiretas | C38: =INDEX(Realizado!72:72,MATCH('P&L Mensal'!$F$1,Realizado!$2:$2,0)) -> -533709.79 | D38: =INDEX('Orçado '!74:74,MATCH('P&L Mensal'!$F$1,'Orçado '!$2:$2,0)) -> -575798.96 | E38: =IFERROR(C38/D38-1,"-") -> -0.073096977 | F38: =INDEX(Realizado!116:116,MATCH('P&L Mensal'!$F$1,Realizado!$2:$2,0)) -> -1806616 | G38: =INDEX('Orçado '!118:118,MATCH('P&L Mensal'!$F$1,'Orçado '!$2:$2,0)) -> -2041469 | H38: =IFERROR(F38/G38-1,"-") -> -0.11504117 | I38: =C38+F38 -> -2340325.8 | J38: =D38+G38 -> -2617268 | K38: =IFERROR(I38/J38-1,"-") -> -0.10581345 | L38: =ABS(I38)-ABS(J38) -> -276942.15
B39: Amortização | C39: =+INDEX(Realizado!69:69,MATCH('P&L Mensal'!$F$1,Realizado!$2:$2,0)) -> -93401.924 | D39: =INDEX('Orçado '!75:75,MATCH('P&L Mensal'!$F$1,'Orçado '!$2:$2,0)) -> -88082.166 | E39: =IFERROR(C39/D39-1,"-") -> 0.060395399 | F39: =+INDEX(Realizado!113:113,MATCH('P&L Mensal'!$F$1,Realizado!$2:$2,0)) -> -331152.28 | G39: =INDEX('Orçado '!119:119,MATCH('P&L Mensal'!$F$1,'Orçado '!$2:$2,0)) -> -312291.32 | H39: =IFERROR(F39/G39-1,"-") -> 0.060395399 | I39: =C39+F39 -> -424554.2 | J39: =D39+G39 -> -400373.48 | K39: =IFERROR(I39/J39-1,"-") -> 0.060395399 | L39: =ABS(I39)-ABS(J39) -> 24180.716
B40: RESULTADO ANTES IMPOSTO | C40: =C37+C38+C39 -> 1108526.1 | D40: =D37+D38+D39 -> 1241279.6 | E40: =IFERROR(C40/D40-1,"-") -> -0.10694891 | F40: =F37+F38+F39 -> 10489085 | G40: =G37+G38+G39 -> 7289663.3 | H40: =IFERROR(F40/G40-1,"-") -> 0.43889838 | I40: =I37+I38+I39 -> 11597611 | J40: =J37+J38+J39 -> 8530942.9 | K40: =IFERROR(I40/J40-1,"-") -> 0.35947585 | L40: =ABS(I40)-ABS(J40) -> 3066667.9
B41: Impostos (IR/CSLL) | C41: =INDEX(Realizado!74:74,MATCH('P&L Mensal'!$F$1,Realizado!$2:$2,0)) -> -375153.56 | D41: =INDEX('Orçado '!77:77,MATCH('P&L Mensal'!$F$1,'Orçado '!$2:$2,0)) -> -487969.93 | E41: =IFERROR(C41/D41-1,"-") -> -0.23119534 | F41: =INDEX(Realizado!118:118,MATCH('P&L Mensal'!$F$1,Realizado!$2:$2,0)) -> -3549774.4 | G41: =INDEX('Orçado '!121:121,MATCH('P&L Mensal'!$F$1,'Orçado '!$2:$2,0)) -> -1730075.2 | H41: =IFERROR(F41/G41-1,"-") -> 1.0518035 | I41: =C41+F41 -> -3924927.9 | J41: =D41+G41 -> -2218045.1 | K41: =IFERROR(I41/J41-1,"-") -> 0.76954374 | L41: =I41-J41 -> -1706882.8
B42: RESULTADO CONTÁBIL | C42: =C40+C41 -> 733372.52 | D42: =D40+D41 -> 753309.65 | E42: =IFERROR(C42/D42-1,"-") -> -0.026466044 | F42: =F40+F41 -> 6939310.4 | G42: =G40+G41 -> 5559588.1 | H42: =IFERROR(F42/G42-1,"-") -> 0.24816988 | I42: =I40+I41 -> 7672682.9 | J42: =J40+J41 -> 6312897.7 | K42: =IFERROR(I42/J42-1,"-") -> 0.21539794 | L42: =ABS(I42)-ABS(J42) -> 1359785.2 | N42: Dif: | O42: =RESULTADO!CE26-'P&L Mensal'!I42 -> 0
A43: 2 | B43: RESULTADO ANTES IMPOSTO RECORRENTE | C43: =C40+#REF!+C39-#REF! -> #REF! | D43: =D40+#REF!+D39-#REF! -> #REF! | E43: =IFERROR(C43/D43-1,"-") -> - | F43: =F40+#REF!+F39-#REF! -> #REF! | G43: =G40+#REF!+G39-#REF! -> #REF! | H43: =IFERROR(F43/G43-1,"-") -> - | I43: =C43+F43 -> #REF! | J43: =D43+G43 -> #REF! | K43: =IFERROR(I43/J43-1,"-") -> - | L43: =ABS(I43)-ABS(J43) -> #REF!
B44: Margem Bruta | C44: =((C30/C49)*12) -> 0.083519809 | D44: =((D30/D49)*12) -> 0.086426297 | E44: =IFERROR(C44-D44,"-")*100 -> -0.29064877 | F44: =((F30/F49)*12) -> 0.11378117 | G44: =((G30/G49)*12) -> 0.10533598 | H44: =IFERROR(F44-G44,"-")*100 -> 0.84451929 | I44: =((I30/I49)*12) -> 0.10756661 | J44: =((J30/J49)*12) -> 0.10135271 | K44: =IFERROR(I44-J44,"-")*100 -> 0.62139021
B45: Margem Liquida | C45: =((C34/C49)*12) -> 0.065655931 | D45: =((D34/D49)*12) -> 0.069611161 | E45: =IFERROR(C45-D45,"-")*100 -> -0.39552306 | F45: =((F34/F49)*12) -> 0.11045482 | G45: =((G34/G49)*12) -> 0.095302041 | H45: =IFERROR(F45-G45,"-")*100 -> 1.515278 | I45: =((I34/I49)*12) -> 0.10125479 | J45: =((J34/J49)*12) -> 0.089890326 | K45: =IFERROR(I45-J45,"-")*100 -> 1.136446
B46: Rácio de Eficiência | C46: =(C35+C38)/(C30) -> -0.35056505 | D46: =(D35+D38)/(D30) -> -0.35782344 | E46: =IFERROR(C46-D46,"-")*100 -> 0.72583961 | F46: =(F35+F38)/(F30) -> -0.24173927 | G46: =(G35+G38)/(G30) -> -0.32705249 | H46: =IFERROR(F46-G46,"-")*100 -> 8.5313219 | I46: =(I35+I38)/(I30) -> -0.25909193 | J46: =(J35+J38)/(J30) -> -0.33257972 | K46: =IFERROR(I46-J46,"-")*100 -> 7.3487789
B47: Rácio de Eficiência Recorrente | C47: =(C35+C38+C39)/C30 -> -0.38330114 | D47: =(D35+D38+D39)/D30 -> -0.38748204 | E47: =IFERROR(C47-D47,"-")*100 -> 0.41808991 | F47: =(F35+F38+F39)/F30 -> -0.26375693 | G47: =(G35+G38+G39)/G30 -> -0.35007626 | H47: =IFERROR(F47-G47,"-")*100 -> 8.6319327 | I47: =(I35+I38+I39)/I30 -> -0.28281869 | J47: =(J35+J38+J39)/J30 -> -0.35679527 | K47: =IFERROR(I47-J47,"-")*100 -> 7.3976584
B48: RPL - RES. CONTÁBIL | C48: =((C42/C56)*12) -> 0.20771829 | D48: =((D42/D56)*12) -> 0.19499663 | E48: =IFERROR(C48-D48,"-")*100 -> 1.2721663 | F48: =((F42/F56)*12) -> 0.50794877 | G48: =((G42/G56)*12) -> 0.3840441 | H48: =IFERROR(F48-G48,"-")*100 -> 12.390467 | I48: =((I42/I56)*12) -> 0.44629253 | J48: =((J42/J56)*12) -> 0.34422175 | K48: =IFERROR(I48-J48,"-")*100 -> 10.207078
B49: Carteira de Crédito Bruta Média | C49: =AVERAGE(INDEX(Realizado!$128:$128,MATCH($F$1,Realizado!$2:$2,0)),INDEX(Realizado!$128:$128,MATCH(EOMONTH($F$1,-1),Realizado!$2:$2,0))) -> 4.0994044e+08 | D49: =AVERAGE(INDEX('Orçado '!128:128,MATCH($F$1,'Orçado '!$2:$2,0)),INDEX('Orçado '!128:128,MATCH(EOMONTH($F$1,-1),'Orçado '!$2:$2,0))) -> 4.1235643e+08 | E49: =IFERROR(C49/D49-1,"-") -> -0.0058590008 | F49: =AVERAGE(INDEX(Realizado!$129:$129,MATCH($F$1,Realizado!$2:$2,0)),INDEX(Realizado!$129:$129,MATCH(EOMONTH($F$1,-1),Realizado!$2:$2,0))) -> 1.586234e+09 | G49: =AVERAGE(INDEX('Orçado '!129:129,MATCH($F$1,'Orçado '!$2:$2,0)),INDEX('Orçado '!129:129,MATCH(EOMONTH($F$1,-1),'Orçado '!$2:$2,0))) -> 1.5452113e+09 | H49: =IFERROR(F49/G49-1,"-") -> 0.026548329 | I49: =C49+F49 -> 1.9961745e+09 | J49: =D49+G49 -> 1.9575677e+09 | K49: =IFERROR(I49/J49-1,"-") -> 0.019721811 | L49: =J49-I49 -> -38606781
B50: Carteira de Crédito SD Cliente Média | C50: =AVERAGE(INDEX(Realizado!$132:$132,MATCH($F$1,Realizado!$2:$2,0)),INDEX(Realizado!$132:$132,MATCH(EOMONTH($F$1,-1),Realizado!$2:$2,0))) -> 4.0732782e+08 | D50: =AVERAGE(INDEX('Orçado '!134:134,MATCH($F$1,'Orçado '!$2:$2,0)),INDEX('Orçado '!134:134,MATCH(EOMONTH($F$1,-1),'Orçado '!$2:$2,0))) -> 4.1067494e+08 | E50: =IFERROR(C50/D50-1,"-") -> -0.0081502824 | F50: =AVERAGE(INDEX(Realizado!$133:$133,MATCH($F$1,Realizado!$2:$2,0)),INDEX(Realizado!$133:$133,MATCH(EOMONTH($F$1,-1),Realizado!$2:$2,0))) -> 1.5600256e+09 | G50: =AVERAGE(INDEX('Orçado '!135:135,MATCH($F$1,'Orçado '!$2:$2,0)),INDEX('Orçado '!135:135,MATCH(EOMONTH($F$1,-1),'Orçado '!$2:$2,0))) -> 1.5164872e+09 | H50: =IFERROR(F50/G50-1,"-") -> 0.028709993 | I50: =C50+F50 -> 1.9673534e+09 | J50: =D50+G50 -> 1.9271622e+09 | K50: =IFERROR(I50/J50-1,"-") -> 0.020855132 | L50: =J50-I50 -> -40191221
H51: =F50-G50 -> 43538338
B52: Taxa Média Carteira Bruta Média | C52: =C6/C49 -> 0.019194187 | D52: =D6/D49 -> 0.018786966 | F52: =F6/F49 -> 0.018695955 | G52: =G6/G49 -> 0.017007776 | I52: =I6/I49 -> 0.018798274 | J52: =J6/J49 -> 0.017382557
B53: Taxa Média Carteira SD Cliente Média | C53: =C6/C50 -> 0.019317299 | D53: =D6/D50 -> 0.018863888 | F53: =F6/F50 -> 0.019010048 | G53: =G6/G50 -> 0.017329923 | I53: =I6/I50 -> 0.019073662 | J53: =J6/J50 -> 0.017656808
B55: Rateio Carteira | C55: =C49/$I$49 -> 0.20536303 | D55: =D49/$J$49 -> 0.21064734 | E55: =IFERROR(C55/D55-1,"-") -> -0.025086069 | F55: =F49/$I$49 -> 0.79463697 | G55: =G49/$J$49 -> 0.78935266 | H55: =IFERROR(F55/G55-1,"-") -> 0.0066944905 | I55: =C55+F55 -> 1 | J55: =D55+G55 -> 1 | K55: =IFERROR(I55/J55-1,"-") -> 0
B56: Alocação de Capital | C56: =$I$58*C55 -> 42367335 | D56: =$J$58*D55 -> 46358319 | E56: =IFERROR(C56/D56-1,"-") -> -0.086089926 | F56: =$I$58*F55 -> 1.6393725e+08 | G56: =$J$58*G55 -> 1.7371718e+08 | H56: =IFERROR(F56/G56-1,"-") -> -0.05629799 | I56: =$I$58*I55 -> 2.0630459e+08 | J56: =$J$58*J55 -> 2.200755e+08 | K56: =IFERROR(I56/J56-1,"-") -> -0.062573582
B58: PL Médio (Banco + Hipo) | I58: =AVERAGE(INDEX(Realizado!$137:$137,MATCH($F$1,Realizado!$2:$2,0)),INDEX(Realizado!$137:$137,MATCH(EOMONTH($F$1,-1),Realizado!$2:$2,0))) -> 2.0630459e+08 | J58: =AVERAGE(INDEX('Orçado '!$137:$137,MATCH($F$1,'Orçado '!$2:$2,0)),INDEX('Orçado '!$137:$137,MATCH(EOMONTH($F$1,-1),'Orçado '!$2:$2,0))) -> 2.200755e+08 | K58: =IFERROR(I58/J58-1,"-") -> -0.062573582
B59: PL Médio (Prudencial + BRCards) | I59: =AVERAGE(INDEX(Realizado!$136:$136,MATCH($F$1,Realizado!$2:$2,0)),INDEX(Realizado!$136:$136,MATCH(EOMONTH($F$1,-1),Realizado!$2:$2,0))) -> 2.144601e+08
B61: Despesas Adm. Diretas + Indiretas | C61: =C35+C38 -> -1000224.8 | D61: =D35+D38 -> -1062689.1 | E61: =(C61/D61)-1 -> -0.058779461 | F61: =F35+F38 -> -3635830.5 | G61: =G35+G38 -> -4436094.7 | H61: =(F61/G61)-1 -> -0.18039837 | I61: =I35+I38 -> -4636055.3 | J61: =J35+J38 -> -5498783.8 | K61: =(I61/J61)-1 -> -0.15689443
B63: Alíquota de IR/CSLL | C63: =C41/C40 -> -0.33842556 | D63: =D41/D40 -> -0.39311847 | F63: =F41/F40 -> -0.33842556 | G63: =G41/G40 -> -0.23733266 | I63: =I41/I40 -> -0.33842556 | J63: =J41/J40 -> -0.26

Sheet Realizado
A2: Consignado | B2: =EOMONTH(C2,-1) -> 44895 | C2: =EOMONTH(D2,-1) -> 44926 | D2: 44957 | E2: =EOMONTH(D2,1) -> 44985 | F2: =EOMONTH(E2,1) -> 45016 | G2: =EOMONTH(F2,1) -> 45046 | H2: =EOMONTH(G2,1) -> 45077 | I2: =EOMONTH(H2,1) -> 45107 | J2: =EOMONTH(I2,1) -> 45138 | K2: =EOMONTH(J2,1) -> 45169 | L2: =EOMONTH(K2,1) -> 45199 | ... AH2: =EOMONTH(AG2,1) -> 45869 | AI2: 45900 | AJ2: 45930 | AK2: =EOMONTH(AJ2,1) -> 45961 | AL2: =EOMONTH(AK2,1) -> 45991 | AM2: =EOMONTH(AL2,1) -> 46022 | AN2: =EOMONTH(AM2,1) -> 46053 | AO2: =EOMONTH(AN2,1) -> 46081 | AP2: =EOMONTH(AO2,1) -> 46112 | AQ2: =EOMONTH(AP2,1) -> 46142 | AR2: =EOMONTH(AQ2,1) -> 46173 | ... AY2: =EOMONTH(AX2,1) -> 46387
A3: RECEITAS
A4: Operações de Crédito
A5: Receita Juros
A6: Receita CM - Crédito Imobiliário
A7: Multa + Mora - Crédito Imobiliário
A8: Receita Juros - Cartão
A9: Receita Serviços
A10: Receita Interchange
A11: Receita Comissão CRI
A12: Receita Cobrança Ext. Cebraco
A13: Barigui Veículos
A14: Honorários
... A38: RESULTADO CONTÁBIL
A39: RECEITAS | AL39: 7704640
A40: Operações de Crédito | AL40: 7667128
A41: Receita Juros | AK41: 5780803.1 | AL41: 5984628.9 | AM41: 6787327.2 | AN41: 6026159.9 | AO41: 5423105.9 | AP41: 6041460.8
A42: Comissão Diferida (TJEO) | AN42: -40115.11
A43: Receita CM - Crédito Imobiliário | AL43: 0
A44: Multa + Mora - Crédito Imobiliário | AL44: 0
A45: Receita Juros - Cartão | AK45: 1785340 | AL45: 1689706.2 | AM45: 1830512.4 | AN45: 1806981.4 | AO45: 1667454.8 | AP45: 1827012.7
A46: Receita Serviços | AL46: 0
A47: Receita Interchange | AL47: 11986.797 | AM47: 12480.275 | AN47: 9001.6569 | AO47: 8163.3698 | AP47: 8879.4971
A48: Receita Comissão CRI | AL48: 0
A49: Receita Cobrança Ext. Cebraco | AL49: 0
A50: Barigui Veículos | AL50: -
A51: Honorários | AL51: -
A52: Securitizadora (Patrimônio Separado) | AL52: -
A53: Resultado de Seguros | AL53: 0
A54: Resultado Brasil Cards | AL54: 0
A55: Resultado Bari Capital | AK55: 0 | AL55: 0 | AM55: 0
A56: DESPESAS DE ORIGINAÇÃO | AL56: -2876490
A57: Despesa de Captação | AL57: -2876490
A58: Inflação | AK58: 0 | AL58: 0
A59: DI/Pré | AK59: =-5871866.4330656-400000 -> -6271866.4 | AL59: -4850067.5 | AM59: =-5329177.64590947-200000 -> -5529177.6 | AN59: =-5284061.23845437+300000 -> -4984061.2 | AO59: -4152791.2 | AP59: -5760280.5
A60: Outros | AK60: =AK124*0.22 -> 525337.89 | AL60: =AL124*0.22 -> 361726.37 | AM60: =AM124*0.22 -> 569799.21 | AN60: =AN124*0.22 -> 533676.18 | AO60: 421756.82 | AP60: 683833.18
A61: Swap | AK61: 721180.7 | AL61: 815785 | AM61: 230403.36 | AN61: 334805.76 | AO61: 272496.22 | AP61: 272803.21
A62: Impostos Diretos | AK62: -158251.41 | AL62: -141845.04 | AM62: 45425.775 | AN62: =-82166.9288-100000 -> -182166.93 | AO62: =-156985.344-(83106.16*0.22) -> -175268.7 | AP62: -220529.89
A63: MARGEM INTERMEDIAÇÃO | AL63: 4626194
A64: Provisões | AL64: -625.627
A65: Provisões | AK65: =(-22914.15+590582.46)*-1 -> -567668.31 | AL65: =-625627.07 -> -625627.07 | AM65: =-407566.37+29100.91 -> -378465.46 | AN65: -725978.64 | AO65: -403888.51 | AP65: -610260.52
A66: Desvalorização e Recuperação de BNDU | AL66: 0
A67: MG INTERMEDIAÇÃO LIQ | AL67: 4000567
A68: Despesas Administrativas Diretas | AK68: =-372628.14 -> -372628.14 | AL68: =-380711.67 -> -380711.67 | AM68: =-382900.13 -> -382900.13 | AN68: =-412401.31 -> -412401.31 | AO68: -472978.66 | AP68: -466515.01
A69: Amortização (estoque - projeto banco) | AL69: - | AN69: -98141.795 | AO69: -95397.185 | AP69: -93401.924
A70: Comissão Correspondentes | AK70: =-38968.1248 -> -38968.125 | AL70: 0 | AN70: -37516.142 | AO70: -223720.53 | AP70: -40765.595
A71: MG CONTRIBUIÇÃO DIRETA | AL71: 2988682
A72: Desp. Administrativas Indiretas | AK72: -640653.6 | AL72: -788752.47 | AM72: -639065.17 | AN72: -676373.11 | AO72: -633048.18 | AP72: -533709.79
A73: RESULTADO ANTES IMPOSTO | AL73: 2168549
A74: Impostos (IR/CSLL) | AK74: 93602.12 | AL74: -232806.66 | AM74: -241015.19 | AN74: -115374.99 | AO74: -544207.13 | AP74: =-375153.558064992 -> -375153.56
A75: RESULTADO ANTES PARTICIPAÇÃO | AL75: 1725628
A76: PART. CONTROLADAS (GESTAO + SEC) | AL76: -
A77: ELO | AL77: 83.999
A78: RESULTADO CONTÁBIL | AL78: 1809628
A80: Imobiliário | AK80: =AK2 -> 45961 | AL80: =AL2 -> 45991 | AM80: =AM2 -> 46022 | AN80: =AN2 -> 46053 | AO80: =AO2 -> 46081 | AP80: =AP2 -> 46112 | AQ80: =AQ2 -> 46142 | AR80: =AR2 -> 46173 | ... AY80: =AY2 -> 46387
A81: RECEITAS | AL81: 23069690
A82: Operações de Crédito | AL82: 20069895
A83: Receita Juros | AK83: 15129457 | AL83: 16276045 | AM83: 18282393 | AN83: 18215602 | AO83: 17032219 | AP83: 21983325
A84: Comissão Diferida (TJEO) | AN84: -435215.04
A85: Receita CM - Crédito Imobiliário | AK85: 2615363.8 | AL85: 3308278.8 | AM85: 1504020.8 | AN85: 2865754.8 | AO85: 3752222.7 | AP85: 7200722.4
A86: Multa + Mora - Crédito Imobiliário | AK86: 331602.45 | AL86: 341631.8 | AM86: 294014.7 | AN86: 348775.09 | AO86: 312401.05 | AP86: 394865.93
A87: Receita Juros - Cartão | AL87: 73896.46 | AM87: 40493.393 | AN87: 41388.299 | AO87: 41006.606 | AP87: 77247.43
A88: Receita Serviços | AK88: 1989120.9 | AL88: 1885440.9 | AM88: 2035535.8 | AN88: 1148925 | AO88: =1590823-41870.32-127748.64 -> 1421204 | AP88: 2558364.6
A89: Receita Interchange | AK89: 27526.77 | AL89: 16151.223 | AM89: 16816.145 | AN89: 12128.993 | AO89: 10999.47 | AP89: 11964.393
A90: Receita Comissão CRI | AK90: 26068.07 | AL90: 0 | AM90: 0
A91: Receita Cobrança Ext. Cebraco | AK91: 220437.96 | AL91: 251558 | AM91: 294718 | AN91: 364301.13 | AO91: =195519.48-26958.13 -> 168561.35 | AP91: 155899.01
A92: Barigui Veículos | AL92: 28.16
A93: Honorários | AL93: 199.594
A94: Securitizadora (Patrimônio Separado) | AL94: 23.805
A95: Resultado de Seguros | AK95: 1080237.8 | AL95: 791082.68 | AM95: 885803.25 | AN95: 976784.38 | AO95: 743112.13 | AP95: 1006702.7
A96: Resultado Brasil Cards | AK96: 115983.11 | AL96: -143757.6 | AM96: -38583.43 | AN96: 65704.18 | AO96: 49730.27 | AP96: 126708.72
A97: Resultado Bari Capital | AK97: 0 | AL97: 0 | AM97: 544951.51 | AN97: 168678.17 | AO97: -629.72 | AP97: -262478.75
A98: DESPESAS DE ORIGINAÇÃO | AL98: -11257301
A99: Despesa de Captação | AL99: -11257301
A100: Inflação | AK100: -4912892 | AL100: -2980190.3 | AM100: -3828963.9 | AN100: -4338842.1 | AO100: -2862311.8 | AP100: -6665373.2
A101: Componente Juros | AK101: -2942201.4 | AL101: -2345832.2 | AM101: -2769084 | AN101: -2698465
A102: Componente Inflação | AK102: -1970690.6 | AL102: -634358.04 | AM102: -1059879.9 | AN102: -1640377.1
A103: DI/Pré | AK103: =-10458885.1069344+400000 -> -10058885 | AL103: -9714852.7 | AM103: =-10986708.1140905+200000 -> -10786708 | AN103: =-11489043.8815456-300000 -> -11789044 | AO103: -10408000 | AP103: -13440654
A104: Outros | AK104: =AK124*0.78 -> 1862561.6 | AL104: 1266042.3 | AM104: 2172631.2 | AN104: 1892124.6 | AO104: 1687027.3 | AP104: 2424498.8
A105: Swap | AK105: 83290.4 | AL105: 622699 | AM105: 321881.48 | AN105: 342468.2 | AO105: 389061.42 | AP105: -181125.23
A106: Impostos Diretos | AK106: -561073.17 | AL106: -644204.1 | AM106: -65273.675 | AN106: =-495690.1212+100000 -> -395690.12 | AO106: =-627941.376-(83106.16*0.78) -> -692764.18 | AP106: -871661.11
A107: MARGEM INTERMEDIAÇÃO | AL107: 11206913
A108: Provisões | AL108: -1055180
A109: Provisões | AK109: =(-17988.32+970911.48)*-1 -> -952923.16 | AL109: =-1055179.74 -> -1055179.7 | AM109: =-11054.68-1044087.94 -> -1055142.6 | AN109: -1516697.2 | AO109: -1775414.1 | AP109: -439697.65
A110: Desvalorização e Recuperação de BNDU | AK110: -143241.9 | AL110: 0
A111: MG INTERMEDIAÇÃO LIQ | AL111: 10151733
A112: Despesas Administrativas Diretas | AK112: -1574188 | AL112: -1564266.4 | AM112: -1577285 | AN112: =-1446214.79 -> -1446214.8 | AO112: -2407184.8 | AP112: -1829214.4
A113: Amortização (estoque - projeto banco) | AL113: - | AN113: -349715.66 | AO113: -338226.38 | AP113: -331152.28
A114: Comissão Correspondentes | AK114: =-138159.7152 -> -138159.72 | AL114: -82840.51 | AN114: -133011.78 | AO114: -793190.98 | AP114: -144532.27
A115: MG CONTRIBUIÇÃO DIRETA | AL115: 7794736
A116: Desp. Administrativas Indiretas | AK116: -2444556.9 | AL116: -2324408.8 | AM116: -2564705 | AN116: -2282965.8 | AO116: -1700871.4 | AP116: -1806616
A117: RESULTADO ANTES IMPOSTO | AL117: 5821268
A118: Impostos (IR/CSLL) | AK118: -534246.27 | AL118: -1321704.1 | AM118: -952145.96 | AN118: -1463640.8 | AO118: -1604213.6 | AP118: =-3549774.351935 -> -3549774.4
A119: RESULTADO ANTES PARTICIPAÇÃO | AL119: 4632288
A120: PART. CONTROLADAS (GESTAO + SEC) | AK120: 178204.25 | AL120: 188001.86 | AM120: 387325.03 | AN120: 87060.33 | AO120: 243037.75 | AP120: 521291.11
A121: ELO | AL121: 113.399
A122: RESULTADO CONTÁBIL | AL122: 4745687
A124: Resultado Total | AK124: 2387899.5 | AL124: 1644210.8 | AM124: 2589996.4 | AN124: 2425800.8
A126: Carteira Mensal - Contábil Bruto
A127: Banco | AK127: =AJ127 -> 0 | AL127: =AK127 -> 0 | AM127: =AL127 -> 0
...

Sheet P&L Acumulado
B1: Data Base -> | F1: De: | G1: 46053 | H1: Até: | I1: 46112 | K1: Proporção anual para Indicadores -> | N1: =12/(MONTH(I1)-MONTH(G1)+1) -> 4
C3: BANCO DIGITAL | F3: CONSIGNADO | I3: IMOBILIARIO | L3: TOTAL
C4: Realizado | D4: Orçado | E4: ∆ (%) | F4: Realizado | G4: Orçado | H4: ∆ (%) | I4: Realizado | J4: Orçado | K4: ∆ (%) | L4: Realizado | M4: Orçado | N4: ∆ (%) | O4: ∆ (R$)
B5: RECEITAS | C5: =C6+C12+C14+C15+C20+C21+C13 -> 0 | D5: =D6+D12+D14+D15+D20+D21+D13 -> 0 | E5: =IFERROR(C5/D5-1,"-") -> - | F5: =F6+F12+F14+F15+F20+F21+F13+F22+F23 -> 22778105 | G5: =G6+G12+G14+G15+G20+G21+G13+G22+G23 -> 22452623 | H5: =IFERROR(F5/G5-1,"-") -> 0.014496375 | I5: =I6+I12+I14+I15+I20+I21+I13+I22+I23 -> 81408364 | J5: =J6+J12+J14+J15+J20+J21+J13+J22+J23 -> 77414896 | K5: =IFERROR(I5/J5-1,"-") -> 0.05158527 | L5: =L6+L12+L14+L15+L20+L21+L13+L22+L23 -> 1.0418647e+08 | M5: =M6+M12+M14+M15+M20+M21+M13+M22+M23 -> 99867519 | N5: =IFERROR(L5/M5-1,"-") -> 0.043246794 | O5: =L5-M5 -> 4318950
B6: Operações de Crédito | C6: =IFERROR(SUMIFS(Realizado!4:4,Realizado!$2:$2,">="&'P&L Acumulado'!$G$1,Realizado!$2:$2,"<="&'P&L Acumulado'!$I$1),0) -> 0 | D6: =IFERROR(SUMIFS('Orçado '!4:4,'Orçado '!$2:$2,">="&'P&L Acumulado'!$G$1,Realizado!$2:$2,"<="&'P&L Acumulado'!$I$1),0) -> 0 | E6: =IFERROR(C6/D6-1,"-") -> - | F6: =SUM(F7:F11) -> 22752060 | G6: =SUM(G7:G11) -> 22415224 | H6: =IFERROR(F6/G6-1,"-") -> 0.015027145 | I6: =SUM(I7:I11) -> 71830315 | J6: =SUM(J7:J11) -> 67855802 | K6: =IFERROR(I6/J6-1,"-") -> 0.058572932 | L6: =C6+F6+I6 -> 94582375 | M6: =D6+G6+J6 -> 90271025 | N6: =IFERROR(L6/M6-1,"-") -> 0.047760065 | O6: =L6-M6 -> 4311350.1
B7: Receita Juros | C7: =IFERROR(SUMIFS(Realizado!5:5,Realizado!$2:$2,">="&'P&L Acumulado'!$G$1,Realizado!$2:$2,"<="&'P&L Acumulado'!$I$1),0) -> 0 | D7: =IFERROR(SUMIFS('Orçado '!5:5,'Orçado '!$2:$2,">="&'P&L Acumulado'!$G$1,Realizado!$2:$2,"<="&'P&L Acumulado'!$I$1),0) -> 0 | E7: =IFERROR(C7/D7-1,"-") -> - | F7: =IFERROR(SUMIFS(Realizado!41:41,Realizado!$2:$2,">="&'P&L Acumulado'!$G$1,Realizado!$2:$2,"<="&'P&L Acumulado'!$I$1),0)+IFERROR(SUMIFS(Realizado!42:42,Realizado!$2:$2,">="&'P&L Acumulado'!$G$1,Realizado!$2:$2,"<="&'P&L Acumulado'!$I$1),0) -> 17450611 | G7: =IFERROR(SUMIFS('Orçado '!43:43,'Orçado '!$2:$2,">="&'P&L Acumulado'!$G$1,Realizado!$2:$2,"<="&'P&L Acumulado'!$I$1),0) -> 17438113 | H7: =IFERROR(F7/G7-1,"-") -> 0.00071675226 | I7: =IFERROR(SUMIFS(Realizado!83:83,Realizado!$2:$2,">="&'P&L Acumulado'!$G$1,Realizado!$2:$2,"<="&'P&L Acumulado'!$I$1),0)++IFERROR(SUMIFS(Realizado!84:84,Realizado!$2:$2,">="&'P&L Acumulado'!$G$1,Realizado!$2:$2,"<="&'P&L Acumulado'!$I$1),0) -> 56795931 | J7: =IFERROR(SUMIFS('Orçado '!84:84,'Orçado '!$2:$2,">="&'P&L Acumulado'!$G$1,Realizado!$2:$2,"<="&'P&L Acumulado'!$I$1),0) -> 54892046 | K7: =IFERROR(I7/J7-1,"-") -> 0.034684157 | L7: =C7+F7+I7 -> 74246542 | M7: =D7+G7+J7 -> 72330159 | N7: =IFERROR(L7/M7-1,"-") -> 0.026494939 | O7: =L7-M7 -> 1916383.2
B8: Receita CM - Crédito Imobiliário | C8: =IFERROR(SUMIFS(Realizado!6:6,Realizado!$2:$2,">="&'P&L Acumulado'!$G$1,Realizado!$2:$2,"<="&'P&L Acumulado'!$I$1),0) -> 0 | D8: =IFERROR(SUMIFS('Orçado '!6:6,'Orçado '!$2:$2,">="&'P&L Acumulado'!$G$1,Realizado!$2:$2,"<="&'P&L Acumulado'!$I$1),0) -> 0 | E8: =IFERROR(C8/D8-1,"-") -> - | F8: =IFERROR(SUMIFS(Realizado!43:43,Realizado!$2:$2,">="&'P&L Acumulado'!$G$1,Realizado!$2:$2,"<="&'P&L Acumulado'!$I$1),0) -> 0 | G8: =IFERROR(SUMIFS('Orçado '!46:46,'Orçado '!$2:$2,">="&'P&L Acumulado'!$G$1,Realizado!$2:$2,"<="&'P&L Acumulado'!$I$1),0) -> 0 | H8: =IFERROR(F8/G8-1,"-") -> - | I8: =IFERROR(SUMIFS(Realizado!85:85,Realizado!$2:$2,">="&'P&L Acumulado'!$G$1,Realizado!$2:$2,"<="&'P&L Acumulado'!$I$1),0) -> 13818700 | J8: =IFERROR(SUMIFS('Orçado '!87:87,'Orçado '!$2:$2,">="&'P&L Acumulado'!$G$1,Realizado!$2:$2,"<="&'P&L Acumulado'!$I$1),0) -> 11742056 | K8: =IFERROR(I8/J8-1,"-") -> 0.1768552 | L8: =C8+F8+I8 -> 13818700 | M8: =D8+G8+J8 -> 11742056 | N8: =IFERROR(L8/M8-1,"-") -> 0.1768552 | O8: =L8-M8 -> 2076643.7
B9: Multa + Mora - Crédito Imobiliário | C9: =IFERROR(SUMIFS(Realizado!7:7,Realizado!$2:$2,">="&'P&L Acumulado'!$G$1,Realizado!$2:$2,"<="&'P&L Acumulado'!$I$1),0) -> 0 | D9: =IFERROR(SUMIFS('Orçado '!7:7,'Orçado '!$2:$2,">="&'P&L Acumulado'!$G$1,Realizado!$2:$2,"<="&'P&L Acumulado'!$I$1),0) -> 0 | E9: =IFERROR(C9/D9-1,"-") -> - | F9: =IFERROR(SUMIFS(Realizado!44:44,Realizado!$2:$2,">="&'P&L Acumulado'!$G$1,Realizado!$2:$2,"<="&'P&L Acumulado'!$I$1),0) -> 0 | G9: =IFERROR(SUMIFS('Orçado '!47:47,'Orçado '!$2:$2,">="&'P&L Acumulado'!$G$1,Realizado!$2:$2,"<="&'P&L Acumulado'!$I$1),0) -> 0 | H9: =IFERROR(F9/G9-1,"-") -> - | I9: =IFERROR(SUMIFS(Realizado!86:86,Realizado!$2:$2,">="&'P&L Acumulado'!$G$1,Realizado!$2:$2,"<="&'P&L Acumulado'!$I$1),0) -> 1056042.1 | J9: =IFERROR(SUMIFS('Orçado '!88:88,'Orçado '!$2:$2,">="&'P&L Acumulado'!$G$1,Realizado!$2:$2,"<="&'P&L Acumulado'!$I$1),0) -> 1097341.8 | K9: =IFERROR(I9/J9-1,"-") -> -0.037636148 | L9: =C9+F9+I9 -> 1056042.1 | M9: =D9+G9+J9 -> 1097341.8 | N9: =IFERROR(L9/M9-1,"-") -> -0.037636148 | O9: =L9-M9 -> -41299.718
B11: Receita Juros - Cartão | C11: =IFERROR(SUMIFS(Realizado!8:8,Realizado!$2:$2,">="&'P&L Acumulado'!$G$1,Realizado!$2:$2,"<="&'P&L Acumulado'!$I$1),0) -> 0 | D11: =IFERROR(SUMIFS('Orçado '!8:8,'Orçado '!$2:$2,">="&'P&L Acumulado'!$G$1,Realizado!$2:$2,"<="&'P&L Acumulado'!$I$1),0) -> 0 | E11: =IFERROR(C11/D11-1,"-") -> - | F11: =IFERROR(SUMIFS(Realizado!45:45,Realizado!$2:$2,">="&'P&L Acumulado'!$G$1,Realizado!$2:$2,"<="&'P&L Acumulado'!$I$1),0) -> 5301448.9 | G11: =IFERROR(SUMIFS('Orçado '!48:48,'Orçado '!$2:$2,">="&'P&L Acumulado'!$G$1,Realizado!$2:$2,"<="&'P&L Acumulado'!$I$1),0) -> 4977110.9 | H11: =IFERROR(F11/G11-1,"-") -> 0.06516592 | I11: =IFERROR(SUMIFS(Realizado!87:87,Realizado!$2:$2,">="&'P&L Acumulado'!$G$1,Realizado!$2:$2,"<="&'P&L Acumulado'!$I$1),0) -> 159642.33 | J11: =IFERROR(SUMIFS('Orçado '!89:89,'Orçado '!$2:$2,">="&'P&L Acumulado'!$G$1,Realizado!$2:$2,"<="&'P&L Acumulado'!$I$1),0) -> 124357.4 | K11: =IFERROR(I11/J11-1,"-") -> 0.28373807 | L11: =C11+F11+I11 -> 5461091.2 | M11: =D11+G11+J11 -> 5101468.3 | N11: =IFERROR(L11/M11-1,"-") -> 0.070494007 | O11: =L11-M11 -> 359622.94
B12: Receita Serviços | C12: =IFERROR(SUMIFS(Realizado!9:9,Realizado!$2:$2,">="&'P&L Acumulado'!$G$1,Realizado!$2:$2,"<="&'P&L Acumulado'!$I$1),0) -> 0 | D12: =IFERROR(SUMIFS('Orçado '!9:9,'Orçado '!$2:$2,">="&'P&L Acumulado'!$G$1,Realizado!$2:$2,"<="&'P&L Acumulado'!$I$1),0) -> 0 | E12: =IFERROR(C12/D12-1,"-") -> - | F12: =IFERROR(SUMIFS(Realizado!46:46,Realizado!$2:$2,">="&'P&L Acumulado'!$G$1,Realizado!$2:$2,"<="&'P&L Acumulado'!$I$1),0) -> 0 | G12: =IFERROR(SUMIFS('Orçado '!49:49,'Orçado '!$2:$2,">="&'P&L Acumulado'!$G$1,Realizado!$2:$2,"<="&'P&L Acumulado'!$I$1),0) -> 0 | H12: =IFERROR(F12/G12-1,"-") -> - | I12: =IFERROR(SUMIFS(Realizado!88:88,Realizado!$2:$2,">="&'P&L Acumulado'!$G$1,Realizado!$2:$2,"<="&'P&L Acumulado'!$I$1),0) -> 5128493.6 | J12: =IFERROR(SUMIFS('Orçado '!90:90,'Orçado '!$2:$2,">="&'P&L Acumulado'!$G$1,Realizado!$2:$2,"<="&'P&L Acumulado'!$I$1),0) -> 4988000 | K12: =IFERROR(I12/J12-1,"-") -> 0.028166327 | L12: =C12+F12+I12 -> 5128493.6 | M12: =D12+G12+J12 -> 4988000 | N12: =IFERROR(L12/M12-1,"-") -> 0.028166327 | O12: =L12-M12 -> 140493.64
B13: Receita Interchange | C13: =IFERROR(SUMIFS(Realizado!10:10,Realizado!$2:$2,">="&'P&L Acumulado'!$G$1,Realizado!$2:$2,"<="&'P&L Acumulado'!$I$1),0) -> 0 | D13: =IFERROR(SUMIFS('Orçado '!12:12,'Orçado '!$2:$2,">="&'P&L Acumulado'!$G$1,Realizado!$2:$2,"<="&'P&L Acumulado'!$I$1),0) -> 0 | E13: =IFERROR(C13/D13-1,"-") -> - | F13: =IFERROR(SUMIFS(Realizado!47:47,Realizado!$2:$2,">="&'P&L Acumulado'!$G$1,Realizado!$2:$2,"<="&'P&L Acumulado'!$I$1),0) -> 26044.524 | G13: =IFERROR(SUMIFS('Orçado '!52:52,'Orçado '!$2:$2,">="&'P&L Acumulado'!$G$1,Realizado!$2:$2,"<="&'P&L Acumulado'!$I$1),0) -> 37399.685 | H13: =IFERROR(F13/G13-1,"-") -> -0.30361649 | I13: =IFERROR(SUMIFS(Realizado!89:89,Realizado!$2:$2,">="&'P&L Acumulado'!$G$1,Realizado!$2:$2,"<="&'P&L Acumulado'!$I$1),0) -> 35092.856 | J13: =IFERROR(SUMIFS('Orçado '!93:93,'Orçado '!$2:$2,">="&'P&L Acumulado'!$G$1,Realizado!$2:$2,"<="&'P&L Acumulado'!$I$1),0) -> 50489.575 | K13: =IFERROR(I13/J13-1,"-") -> -0.30494847 | L13: =C13+F13+I13 -> 61137.38 | M13: =D13+G13+J13 -> 87889.26 | N13: =IFERROR(L13/M13-1,"-") -> -0.30438167 | O13: =L13-M13 -> -26751.88
B14: Receita Comissão CRI | C14: =IFERROR(SUMIFS(Realizado!11:11,Realizado!$2:$2,">="&'P&L Acumulado'!$G$1,Realizado!$2:$2,"<="&'P&L Acumulado'!$I$1),0) -> 0 | D14: =IFERROR(SUMIFS('Orçado '!13:13,'Orçado '!$2:$2,">="&'P&L Acumulado'!$G$1,Realizado!$2:$2,"<="&'P&L Acumulado'!$I$1),0) -> 0 | E14: =IFERROR(C14/D14-1,"-") -> - | F14: =IFERROR(SUMIFS(Realizado!48:48,Realizado!$2:$2,">="&'P&L Acumulado'!$G$1,Realizado!$2:$2,"<="&'P&L Acumulado'!$I$1),0) -> 0 | G14: =IFERROR(SUMIFS('Orçado '!53:53,'Orçado '!$2:$2,">="&'P&L Acumulado'!$G$1,Realizado!$2:$2,"<="&'P&L Acumulado'!$I$1),0) -> 0 | H14: =IFERROR(F14/G14-1,"-") -> - | I14: =IFERROR(SUMIFS(Realizado!90:90,Realizado!$2:$2,">="&'P&L Acumulado'!$G$1,Realizado!$2:$2,"<="&'P&L Acumulado'!$I$1),0) -> 0 | J14: =IFERROR(SUMIFS('Orçado '!94:94,'Orçado '!$2:$2,">="&'P&L Acumulado'!$G$1,Realizado!$2:$2,"<="&'P&L Acumulado'!$I$1),0) -> 0 | K14: =IFERROR(I14/J14-1,"-") -> - | L14: =C14+F14+I14 -> 0 | M14: =D14+G14+J14 -> 0 | N14: =IFERROR(L14/M14-1,"-") -> - | O14: =L14-M14 -> 0
B15: Receita Cobrança Ext. Cebraco | C15: =IFERROR(SUMIFS(Realizado!12:12,Realizado!$2:$2,">="&'P&L Acumulado'!$G$1,Realizado!$2:$2,"<="&'P&L Acumulado'!$I$1),0) -> 0 | D15: =IFERROR(SUMIFS('Orçado '!14:14,'Orçado '!$2:$2,">="&'P&L Acumulado'!$G$1,Realizado!$2:$2,"<="&'P&L Acumulado'!$I$1),0) -> 0 | E15: =IFERROR(C15/D15-1,"-") -> - | F15: =IFERROR(SUMIFS(Realizado!49:49,Realizado!$2:$2,">="&'P&L Acumulado'!$G$1,Realizado!$2:$2,"<="&'P&L Acumulado'!$I$1),0) -> 0 | G15: =IFERROR(SUMIFS('Orçado '!54:54,'Orçado '!$2:$2,">="&'P&L Acumulado'!$G$1,Realizado!$2:$2,"<="&'P&L Acumulado'!$I$1),0) -> 0 | H15: =IFERROR(F15/G15-1,"-") -> - | I15: =IFERROR(SUMIFS(Realizado!91:91,Realizado!$2:$2,">="&'P&L Acumulado'!$G$1,Realizado!$2:$2,"<="&'P&L Acumulado'!$I$1),0) -> 688761.49 | J15: =IFERROR(SUMIFS('Orçado '!95:95,'Orçado '!$2:$2,">="&'P&L Acumulado'!$G$1,Realizado!$2:$2,"<="&'P&L Acumulado'!$I$1),0) -> 929808.68 | K15: =IFERROR(I15/J15-1,"-") -> -0.25924385 | L15: =C15+F15+I15 -> 688761.49 | M15: =D15+G15+J15 -> 929808.68 | N15: =IFERROR(L15/M15-1,"-") -> -0.25924385 | O15: =L15-M15 -> -241047.19
B16: Barigui Veículos | C16: =IFERROR(SUMIFS(Realizado!13:13,Realizado!$2:$2,">="&'P&L Acumulado'!$G$1,Realizado!$2:$2,"<="&'P&L Acumulado'!$I$1),0) -> 0 | D16: =IFERROR(SUMIFS('Orçado '!15:15,'Orçado '!$2:$2,">="&'P&L Acumulado'!$G$1,Realizado!$2:$2,"<="&'P&L Acumulado'!$I$1),0) -> 0 | E16: =IFERROR(C16/D16-1,"-") -> - | F16: =IFERROR(SUMIFS(Realizado!50:50,Realizado!$2:$2,">="&'P&L Acumulado'!$G$1,Realizado!$2:$2,"<="&'P&L Acumulado'!$I$1),0) -> 0 | G16: =IFERROR(SUMIFS('Orçado '!55:55,'Orçado '!$2:$2,">="&'P&L Acumulado'!$G$1,Realizado!$2:$2,"<="&'P&L Acumulado'!$I$1),0) -> 0 | H16: =IFERROR(F16/G16-1,"-") -> - | I16: =IFERROR(SUMIFS(Realizado!92:92,Realizado!$2:$2,">="&'P&L Acumulado'!$G$1,Realizado!$2:$2,"<="&'P&L Acumulado'!$I$1),0) -> 0 | J16: =IFERROR(SUMIFS('Orçado '!96:96,'Orçado '!$2:$2,">="&'P&L Acumulado'!$G$1,Realizado!$2:$2,"<="&'P&L Acumulado'!$I$1),0) -> 0 | K16: =IFERROR(I16/J16-1,"-") -> - | L16: =C16+F16+I16 -> 0 | M16: =D16+G16+J16 -> 0 | N16: =IFERROR(L16/M16-1,"-") -> - | O16: =L16-M16 -> 0
B17: Honorários | C17: =IFERROR(SUMIFS(Realizado!14:14,Realizado!$2:$2,">="&'P&L Acumulado'!$G$1,Realizado!$2:$2,"<="&'P&L Acumulado'!$I$1),0) -> 0 | D17: =IFERROR(SUMIFS('Orçado '!16:16,'Orçado '!$2:$2,">="&'P&L Acumulado'!$G$1,Realizado!$2:$2,"<="&'P&L Acumulado'!$I$1),0) -> 0 | E17: =IFERROR(C17/D17-1,"-") -> - | F17: =IFERROR(SUMIFS(Realizado!51:51,Realizado!$2:$2,">="&'P&L Acumulado'!$G$1,Realizado!$2:$2,"<="&'P&L Acumulado'!$I$1),0) -> 0 | G17: =IFERROR(SUMIFS('Orçado '!56:56,'Orçado '!$2:$2,">="&'P&L Acumulado'!$G$1,Realizado!$2:$2,"<="&'P&L Acumulado'!$I$1),0) -> 0 | H17: =IFERROR(F17/G17-1,"-") -> - | I17: =IFERROR(SUMIFS(Realizado!93:93,Realizado!$2:$2,">="&'P&L Acumulado'!$G$1,Realizado!$2:$2,"<="&'P&L Acumulado'!$I$1),0) -> 0 | J17: =IFERROR(SUMIFS('Orçado '!97:97,'Orçado '!$2:$2,">="&'P&L Acumulado'!$G$1,Realizado!$2:$2,"<="&'P&L Acumulado'!$I$1),0) -> 0 | K17: =IFERROR(I17/J17-1,"-") -> - | L17: =C17+F17+I17 -> 0 | M17: =D17+G17+J17 -> 0 | N17: =IFERROR(L17/M17-1,"-") -> - | O17: =L17-M17 -> 0
B18: Securitizadora (Patrimônio Separado) | C18: =IFERROR(SUMIFS(Realizado!15:15,Realizado!$2:$2,">="&'P&L Acumulado'!$G$1,Realizado!$2:$2,"<="&'P&L Acumulado'!$I$1),0) -> 0 | D18: =IFERROR(SUMIFS('Orçado '!17:17,'Orçado '!$2:$2,">="&'P&L Acumulado'!$G$1,Realizado!$2:$2,"<="&'P&L Acumulado'!$I$1),0) -> 0 | E18: =IFERROR(C18/D18-1,"-") -> - | F18: =IFERROR(SUMIFS(Realizado!52:52,Realizado!$2:$2,">="&'P&L Acumulado'!$G$1,Realizado!$2:$2,"<="&'P&L Acumulado'!$I$1),0) -> 0 | G18: =IFERROR(SUMIFS('Orçado '!57:57,'Orçado '!$2:$2,">="&'P&L Acumulado'!$G$1,Realizado!$2:$2,"<="&'P&L Acumulado'!$I$1),0) -> 0 | H18: =IFERROR(F18/G18-1,"-") -> - | I18: =IFERROR(SUMIFS(Realizado!94:94,Realizado!$2:$2,">="&'P&L Acumulado'!$G$1,Realizado!$2:$2,"<="&'P&L Acumulado'!$I$1),0) -> 0 | J18: =IFERROR(SUMIFS('Orçado '!98:98,'Orçado '!$2:$2,">="&'P&L Acumulado'!$G$1,Realizado!$2:$2,"<="&'P&L Acumulado'!$I$1),0) -> 0 | K18: =IFERROR(I18/J18-1,"-") -> - | L18: =C18+F18+I18 -> 0 | M18: =D18+G18+J18 -> 0 | N18: =IFERROR(L18/M18-1,"-") -> - | O18: =L18-M18 -> 0
B19: Resultado Cont. e Colig. | F19: =SUM(F20:F23) -> 0 | G19: =SUM(G20:G23) -> 0 | H19: =IFERROR(F19/G19-1,"-") -> - | I19: =SUM(I20:I23) -> 3725701.3 | J19: =SUM(J20:J23) -> 3590795.9 | K19: =IFERROR(I19/J19-1,"-") -> 0.037569761 | L19: =SUM(L20:L23) -> 3725701.3 | M19: =SUM(M20:M23) -> 3590795.9 | N19: =IFERROR(L19/M19-1,"-") -> 0.037569761 | O19: =L19-M19 -> 134905.34
B20: Resultado de Seguros | C20: =IFERROR(SUMIFS(Realizado!16:16,Realizado!$2:$2,">="&'P&L Acumulado'!$G$1,Realizado!$2:$2,"<="&'P&L Acumulado'!$I$1),0) -> 0 | D20: =IFERROR(SUMIFS('Orçado '!18:18,'Orçado '!$2:$2,">="&'P&L Acumulado'!$G$1,Realizado!$2:$2,"<="&'P&L Acumulado'!$I$1),0) -> 0 | E20: =IFERROR(C20/D20-1,"-") -> - | F20: =IFERROR(SUMIFS(Realizado!53:53,Realizado!$2:$2,">="&'P&L Acumulado'!$G$1,Realizado!$2:$2,"<="&'P&L Acumulado'!$I$1),0) -> 0 | G20: =IFERROR(SUMIFS('Orçado '!58:58,'Orçado '!$2:$2,">="&'P&L Acumulado'!$G$1,Realizado!$2:$2,"<="&'P&L Acumulado'!$I$1),0) -> 0 | H20: =IFERROR(F20/G20-1,"-") -> - | I20: =IFERROR(SUMIFS(Realizado!95:95,Realizado!$2:$2,">="&'P&L Acumulado'!$G$1,Realizado!$2:$2,"<="&'P&L Acumulado'!$I$1),0) -> 2726599.2 | J20: =IFERROR(SUMIFS('Orçado '!99:99,'Orçado '!$2:$2,">="&'P&L Acumulado'!$G$1,Realizado!$2:$2,"<="&'P&L Acumulado'!$I$1),0) -> 2776784.4 | K20: =IFERROR(I20/J20-1,"-") -> -0.018073125 | L20: =C20+F20+I20 -> 2726599.2 | M20: =D20+G20+J20 -> 2776784.4 | N20: =IFERROR(L20/M20-1,"-") -> -0.018073125 | O20: =L20-M20 -> -50185.17
B21: Resultado Brasil Cards | C21: =IFERROR(SUMIFS(Realizado!17:17,Realizado!$2:$2,">="&'P&L Acumulado'!$G$1,Realizado!$2:$2,"<="&'P&L Acumulado'!$I$1),0) -> 0 | D21: =IFERROR(SUMIFS('Orçado '!19:19,'Orçado '!$2:$2,">="&'P&L Acumulado'!$G$1,Realizado!$2:$2,"<="&'P&L Acumulado'!$I$1),0) -> 0 | E21: =IFERROR(C21/D21-1,"-") -> - | F21: =IFERROR(SUMIFS(Realizado!54:54,Realizado!$2:$2,">="&'P&L Acumulado'!$G$1,Realizado!$2:$2,"<="&'P&L Acumulado'!$I$1),0) -> 0 | G21: =IFERROR(SUMIFS('Orçado '!59:59,'Orçado '!$2:$2,">="&'P&L Acumulado'!$G$1,Realizado!$2:$2,"<="&'P&L Acumulado'!$I$1),0) -> 0 | H21: =IFERROR(F21/G21-1,"-") -> - | I21: =IFERROR(SUMIFS(Realizado!96:96,Realizado!$2:$2,">="&'P&L Acumulado'!$G$1,Realizado!$2:$2,"<="&'P&L Acumulado'!$I$1),0) -> 242143.17 | J21: =IFERROR(SUMIFS('Orçado '!100:100,'Orçado '!$2:$2,">="&'P&L Acumulado'!$G$1,Realizado!$2:$2,"<="&'P&L Acumulado'!$I$1),0) -> 65377.31 | K21: =IFERROR(I21/J21-1,"-") -> 2.70378 | L21: =C21+F21+I21 -> 242143.17 | M21: =D21+G21+J21 -> 65377.31 | N21: =IFERROR(L21/M21-1,"-") -> 2.70378 | O21: =L21-M21 -> 176765.86
B22: Resultado Bari Capital | F22: =IFERROR(SUMIFS(Realizado!55:55,Realizado!$2:$2,">="&'P&L Acumulado'!$G$1,Realizado!$2:$2,"<="&'P&L Acumulado'!$I$1),0) -> 0 | G22: =IFERROR(SUMIFS('Orçado '!60:60,'Orçado '!$2:$2,">="&'P&L Acumulado'!$G$1,Realizado!$2:$2,"<="&'P&L Acumulado'!$I$1),0) -> 0 | H22: =IFERROR(F22/G22-1,"-") -> - | I22: =IFERROR(SUMIFS(Realizado!97:97,Realizado!$2:$2,">="&'P&L Acumulado'!$G$1,Realizado!$2:$2,"<="&'P&L Acumulado'!$I$1),0) -> -94430.3 | J22: =IFERROR(SUMIFS('Orçado '!101:101,'Orçado '!$2:$2,">="&'P&L Acumulado'!$G$1,Realizado!$2:$2,"<="&'P&L Acumulado'!$I$1),0) -> 241278.17 | K22: =IFERROR(I22/J22-1,"-") -> -1.3913752 | L22: =C22+F22+I22 -> -94430.3 | M22: =D22+G22+J22 -> 241278.17 | N22: =IFERROR(L22/M22-1,"-") -> -1.3913752 | O22: =L22-M22 -> -335708.47
B23: Resultado Sec | C23: =IFERROR(SUMIFS(Realizado!37:37,Realizado!$2:$2,">="&'P&L Acumulado'!$G$1,Realizado!$2:$2,"<="&'P&L Acumulado'!$I$1),0) -> 0 | D23: =IFERROR(SUMIFS('Orçado '!37:37,'Orçado '!$2:$2,">="&'P&L Acumulado'!$G$1,Realizado!$2:$2,"<="&'P&L Acumulado'!$I$1),0) -> 0 | E23: =IFERROR(C23/D23-1,"-") -> - | F23: =IFERROR(SUMIFS(Realizado!76:76,Realizado!$2:$2,">="&'P&L Acumulado'!$G$1,Realizado!$2:$2,"<="&'P&L Acumulado'!$I$1),0) -> 0 | G23: =IFERROR(SUMIFS('Orçado '!#REF!,'Orçado '!$2:$2,">="&'P&L Acumulado'!$G$1,Realizado!$2:$2,"<="&'P&L Acumulado'!$I$1),0) -> 0 | H23: =IFERROR(F23/G23-1,"-") -> - | I23: =IFERROR(SUMIFS(Realizado!120:120,Realizado!$2:$2,">="&'P&L Acumulado'!$G$1,Realizado!$2:$2,"<="&'P&L Acumulado'!$I$1),0) -> 851389.19 | J23: =IFERROR(SUMIFS('Orçado '!102:102,'Orçado '!$2:$2,">="&'P&L Acumulado'!$G$1,Realizado!$2:$2,"<="&'P&L Acumulado'!$I$1),0) -> 507356.07 | K23: =IFERROR(I23/J23-1,"-") -> 0.6780901 | L23: =C23+F23+I23 -> 851389.19 | M23: =D23+G23+J23 -> 507356.07 | N23: =IFERROR(L23/M23-1,"-") -> 0.6780901 | O23: =ABS(L23)-ABS(M23) -> 344033.12
B24: DESPESAS DE ORIGINAÇÃO | C24: =C25 -> 0 | D24: =D25 -> 0 | E24: =IFERROR(C24/D24-1,"-") -> - | F24: =F25 -> -12377762 | G24: =G25 -> -11952518 | H24: =IFERROR(F24/G24-1,"-") -> 0.035577756 | I24: =I25 -> -42950170 | J24: =J25 -> -41901835 | K24: =IFERROR(I24/J24-1,"-") -> 0.025018829 | L24: =L25 -> -55327932 | M24: =M25 -> -53854353 | N24: =IFERROR(L24/M24-1,"-") -> 0.027362294 | O24: =ABS(L24)-ABS(M24) -> 1473578.6
B25: Despesa de Captação* | C25: =IFERROR(SUMIFS(Realizado!19:19,Realizado!$2:$2,">="&'P&L Acumulado'!$G$1,Realizado!$2:$2,"<="&'P&L Acumulado'!$I$1),0) -> 0 | D25: =IFERROR(SUMIFS('Orçado '!21:21,'Orçado '!$2:$2,">="&'P&L Acumulado'!$G$1,Realizado!$2:$2,"<="&'P&L Acumulado'!$I$1),0) -> 0 | E25: =IFERROR(C25/D25-1,"-") -> - | F25: =SUM(F26:F29) -> -12377762 | G25: =IFERROR(SUMIFS('Orçado '!62:62,'Orçado '!$2:$2,">="&'P&L Acumulado'!$G$1,Realizado!$2:$2,"<="&'P&L Acumulado'!$I$1),0) -> -11952518 | H25: =IFERROR(F25/G25-1,"-") -> 0.035577756 | I25: =SUM(I26:I29) -> -42950170 | J25: =IFERROR(SUMIFS('Orçado '!104:104,'Orçado '!$2:$2,">="&'P&L Acumulado'!$G$1,Realizado!$2:$2,"<="&'P&L Acumulado'!$I$1),0) -> -41901835 | K25: =IFERROR(I25/J25-1,"-") -> 0.025018829 | L25: =SUM(L26:L29) -> -55327932 | M25: =SUM(M26:M29) -> -53854353 | N25: =IFERROR(L25/M25-1,"-") -> 0.027362294 | O25: =ABS(L25)-ABS(M25) -> 1473578.6
B26: Inflação | C26: =IFERROR(SUMIFS(Realizado!20:20,Realizado!$2:$2,">="&'P&L Acumulado'!$G$1,Realizado!$2:$2,"<="&'P&L Acumulado'!$I$1),0) -> 0 | D26: =IFERROR(SUMIFS('Orçado '!22:22,'Orçado '!$2:$2,">="&'P&L Acumulado'!$G$1,Realizado!$2:$2,"<="&'P&L Acumulado'!$I$1),0) -> 0 | E26: =IFERROR(C26/D26-1,"-") -> - | F26: =IFERROR(SUMIFS(Realizado!58:58,Realizado!$2:$2,">="&'P&L Acumulado'!$G$1,Realizado!$2:$2,"<="&'P&L Acumulado'!$I$1),0) -> 0 | G26: =IFERROR(SUMIFS('Orçado '!63:63,'Orçado '!$2:$2,">="&'P&L Acumulado'!$G$1,Realizado!$2:$2,"<="&'P&L Acumulado'!$I$1),0) -> 0 | H26: =IFERROR(F26/G26-1,"-") -> - | I26: =IFERROR(SUMIFS(Realizado!100:100,Realizado!$2:$2,">="&'P&L Acumulado'!$G$1,Realizado!$2:$2,"<="&'P&L Acumulado'!$I$1),0) -> -13866527 | J26: =IFERROR(SUMIFS('Orçado '!105:105,'Orçado '!$2:$2,">="&'P&L Acumulado'!$G$1,Realizado!$2:$2,"<="&'P&L Acumulado'!$I$1),0) -> -14127529 | K26: =IFERROR(I26/J26-1,"-") -> -0.018474702 | L26: =C26+F26+I26 -> -13866527 | M26: =D26+G26+J26 -> -14127529 | N26: =IFERROR(L26/M26-1,"-") -> -0.018474702 | O26: =ABS(L26)-ABS(M26) -> -261001.88
B27: DI/Pré | C27: =IFERROR(SUMIFS(Realizado!21:21,Realizado!$2:$2,">="&'P&L Acumulado'!$G$1,Realizado!$2:$2,"<="&'P&L Acumulado'!$I$1),0) -> 0 | D27: =IFERROR(SUMIFS('Orçado '!23:23,'Orçado '!$2:$2,">="&'P&L Acumulado'!$G$1,Realizado!$2:$2,"<="&'P&L Acumulado'!$I$1),0) -> 0 | E27: =IFERROR(C27/D27-1,"-") -> - | F27: =IFERROR(SUMIFS(Realizado!59:59,Realizado!$2:$2,">="&'P&L Acumulado'!$G$1,Realizado!$2:$2,"<="&'P&L Acumulado'!$I$1),0) -> -14897133 | G27: =IFERROR(SUMIFS('Orçado '!64:64,'Orçado '!$2:$2,">="&'P&L Acumulado'!$G$1,Realizado!$2:$2,"<="&'P&L Acumulado'!$I$1),0) -> -14593480 | H27: =IFERROR(F27/G27-1,"-") -> 0.020807455 | I27: =IFERROR(SUMIFS(Realizado!103:103,Realizado!$2:$2,">="&'P&L Acumulado'!$G$1,Realizado!$2:$2,"<="&'P&L Acumulado'!$I$1),0) -> -35637698 | J27: =IFERROR(SUMIFS('Orçado '!108:108,'Orçado '!$2:$2,">="&'P&L Acumulado'!$G$1,Realizado!$2:$2,"<="&'P&L Acumulado'!$I$1),0) -> -34558300 | K27: =IFERROR(I27/J27-1,"-") -> 0.031234138 | L27: =C27+F27+I27 -> -50534831 | M27: =D27+G27+J27 -> -49151779 | N27: =IFERROR(L27/M27-1,"-") -> 0.028138388 | O27: =ABS(L27)-ABS(M27) -> 1383051.9
B28: Receita Financeira + Outros | C28: =+IFERROR(SUMIFS(Realizado!22:22,Realizado!$2:$2,">="&'P&L Acumulado'!$G$1,Realizado!$2:$2,"<="&'P&L Acumulado'!$I$1),0) -> 0 | D28: =+IFERROR(SUMIFS('Orçado '!24:24,'Orçado '!$2:$2,">="&'P&L Acumulado'!$G$1,Realizado!$2:$2,"<="&'P&L Acumulado'!$I$1),0) -> 0 | E28: =IFERROR(C28/D28-1,"-") -> - | F28: =+IFERROR(SUMIFS(Realizado!60:60,Realizado!$2:$2,">="&'P&L Acumulado'!$G$1,Realizado!$2:$2,"<="&'P&L Acumulado'!$I$1),0) -> 1639266.2 | G28: =+IFERROR(SUMIFS('Orçado '!65:65,'Orçado '!$2:$2,">="&'P&L Acumulado'!$G$1,Realizado!$2:$2,"<="&'P&L Acumulado'!$I$1),0) -> 1621140.1 | H28: =IFERROR(F28/G28-1,"-") -> 0.011181073 | I28: =+IFERROR(SUMIFS(Realizado!104:104,Realizado!$2:$2,">="&'P&L Acumulado'!$G$1,Realizado!$2:$2,"<="&'P&L Acumulado'!$I$1),0) -> 6003650.7 | J28: =+IFERROR(SUMIFS('Orçado '!109:109,'Orçado '!$2:$2,">="&'P&L Acumulado'!$G$1,Realizado!$2:$2,"<="&'P&L Acumulado'!$I$1),0) -> 5938223.2 | K28: =IFERROR(I28/J28-1,"-") -> 0.011018042 | L28: =C28+F28+I28 -> 7642916.9 | M28: =D28+G28+J28 -> 7559363.2 | N28: =IFERROR(L28/M28-1,"-") -> 0.011053005 | O28: =ABS(L28)-ABS(M28) -> 83553.68
B29: Swap | C29: =+IFERROR(SUMIFS(Realizado!23:23,Realizado!$2:$2,">="&'P&L Acumulado'!$G$1,Realizado!$2:$2,"<="&'P&L Acumulado'!$I$1),0) -> 0 | D29: =+IFERROR(SUMIFS('Orçado '!25:25,'Orçado '!$2:$2,">="&'P&L Acumulado'!$G$1,Realizado!$2:$2,"<="&'P&L Acumulado'!$I$1),0) -> 0 | E29: =IFERROR(C29/D29-1,"-") -> - | F29: =+IFERROR(SUMIFS(Realizado!61:61,Realizado!$2:$2,">="&'P&L Acumulado'!$G$1,Realizado!$2:$2,"<="&'P&L Acumulado'!$I$1),0) -> 880105.19 | G29: =+IFERROR(SUMIFS('Orçado '!66:66,'Orçado '!$2:$2,">="&'P&L Acumulado'!$G$1,Realizado!$2:$2,"<="&'P&L Acumulado'!$I$1),0) -> 1019821.9 | H29: =IFERROR(F29/G29-1,"-") -> -0.13700107 | I29: =+IFERROR(SUMIFS(Realizado!105:105,Realizado!$2:$2,">="&'P&L Acumulado'!$G$1,Realizado!$2:$2,"<="&'P&L Acumulado'!$I$1),0) -> 550404.39 | J29: =+IFERROR(SUMIFS('Orçado '!110:110,'Orçado '!$2:$2,">="&'P&L Acumulado'!$G$1,Realizado!$2:$2,"<="&'P&L Acumulado'!$I$1),0) -> 845770.05 | K29: =IFERROR(I29/J29-1,"-") -> -0.34922691 | L29: =C29+F29+I29 -> 1430509.6 | M29: =D29+G29+J29 -> 1865591.9 | N29: =IFERROR(L29/M29-1,"-") -> -0.2332141 | O29: =ABS(L29)-ABS(M29) -> -435082.35
B30: Impostos Diretos | C30: =IFERROR(SUMIFS(Realizado!24:24,Realizado!$2:$2,">="&'P&L Acumulado'!$G$1,Realizado!$2:$2,"<="&'P&L Acumulado'!$I$1),0) -> 0 | D30: =IFERROR(SUMIFS('Orçado '!26:26,'Orçado '!$2:$2,">="&'P&L Acumulado'!$G$1,Realizado!$2:$2,"<="&'P&L Acumulado'!$I$1),0) -> 0 | E30: =IFERROR(C30/D30-1,"-") -> - | F30: =IFERROR(SUMIFS(Realizado!62:62,Realizado!$2:$2,">="&'P&L Acumulado'!$G$1,Realizado!$2:$2,"<="&'P&L Acumulado'!$I$1),0) -> -577965.52 | G30: =IFERROR(SUMIFS('Orçado '!67:67,'Orçado '!$2:$2,">="&'P&L Acumulado'!$G$1,Realizado!$2:$2,"<="&'P&L Acumulado'!$I$1),0) -> -442314.17 | H30: =IFERROR(F30/G30-1,"-") -> 0.30668551 | I30: =IFERROR(SUMIFS(Realizado!106:106,Realizado!$2:$2,">="&'P&L Acumulado'!$G$1,Realizado!$2:$2,"<="&'P&L Acumulado'!$I$1),0) -> -1960115.4 | J30: =IFERROR(SUMIFS('Orçado '!111:111,'Orçado '!$2:$2,">="&'P&L Acumulado'!$G$1,Realizado!$2:$2,"<="&'P&L Acumulado'!$I$1),0) -> -1568205.9 | K30: =IFERROR(I30/J30-1,"-") -> 0.24990949 | L30: =C30+F30+I30 -> -2538080.9 | M30: =D30+G30+J30 -> -2010520.1 | N30: =IFERROR(L30/M30-1,"-") -> 0.26240021 | O30: =ABS(L30)-ABS(M30) -> 527560.88
B31: MARGEM INTERMEDIAÇÃO | C31: =C5+C24+C30 -> 0 | D31: =D5+D24+D30 -> 0 | E31: =IFERROR(C31/D31-1,"-") -> - | F31: =F5+F24+F30 -> 9822377.8 | G31: =G5+G24+G30 -> 10057791 | H31: =IFERROR(F31/G31-1,"-") -> -0.02340608 | I31: =I5+I24+I30 -> 36498078 | J31: =J5+J24+J30 -> 33944855 | K31: =IFERROR(I31/J31-1,"-") -> 0.075216817 | L31: =L5+L24+L30 -> 46320456 | M31: =M5+M24+M30 -> 44002646 | N31: =IFERROR(L31/M31-1,"-") -> 0.052674343 | O31: =ABS(L31)-ABS(M31) -> 2317810.5
B32: Provisões | C32: =IFERROR(SUMIFS(Realizado!26:26,Realizado!$2:$2,">="&'P&L Acumulado'!$G$1,Realizado!$2:$2,"<="&'P&L Acumulado'!$I$1),0) -> 0 | D32: =IFERROR(SUMIFS('Orçado '!28:28,'Orçado '!$2:$2,">="&'P&L Acumulado'!$G$1,Realizado!$2:$2,"<="&'P&L Acumulado'!$I$1),0) -> 0 | E32: =IFERROR(C32/D32-1,"-") -> - | F32: =SUM(F33:F34) -> -1740127.7 | G32: =IFERROR(SUMIFS('Orçado '!69:69,'Orçado '!$2:$2,">="&'P&L Acumulado'!$G$1,Realizado!$2:$2,"<="&'P&L Acumulado'!$I$1),0) -> -1857717.6 | H32: =IFERROR(F32/G32-1,"-") -> -0.063298085 | I32: =SUM(I33:I34) -> -3731809 | J32: =IFERROR(SUMIFS('Orçado '!113:113,'Orçado '!$2:$2,">="&'P&L Acumulado'!$G$1,Realizado!$2:$2,"<="&'P&L Acumulado'!$I$1),0) -> -3737182.1 | K32: =IFERROR(I32/J32-1,"-") -> -0.0014377466 | L32: =SUM(L33:L34) -> -5471936.7 | M32: =D32+G32+J32 -> -5594899.7 | N32: =IFERROR(L32/M32-1,"-") -> -0.021977711 | O32: =ABS(L32)-ABS(M32) -> -122963.09
B33: Provisões | F33: =IFERROR(SUMIFS(Realizado!65:65,Realizado!$2:$2,">="&'P&L Acumulado'!$G$1,Realizado!$2:$2,"<="&'P&L Acumulado'!$I$1),0) -> -1740127.7 | G33: =IFERROR(SUMIFS('Orçado '!69:69,'Orçado '!$2:$2,">="&'P&L Acumulado'!$G$1,Realizado!$2:$2,"<="&'P&L Acumulado'!$I$1),0) -> -1857717.6 | H33: =IFERROR(F33/G33-1,"-") -> -0.063298085 | I33: =IFERROR(SUMIFS(Realizado!109:109,Realizado!$2:$2,">="&'P&L Acumulado'!$G$1,Realizado!$2:$2,"<="&'P&L Acumulado'!$I$1),0) -> -3731809 | J33: =IFERROR(SUMIFS('Orçado '!113:113,'Orçado '!$2:$2,">="&'P&L Acumulado'!$G$1,Realizado!$2:$2,"<="&'P&L Acumulado'!$I$1),0) -> -3737182.1 | K33: =IFERROR(I33/J33-1,"-") -> -0.0014377466 | L33: =I33+F33 -> -5471936.7 | M33: =J33+G33 -> -5594899.7 | N33: =IFERROR(L33/M33-1,"-") -> -0.021977711 | O33: =ABS(L33)-ABS(M33) -> -122963.09
B34: Desvalorização de BNDU | C34: =IFERROR(SUMIFS(Realizado!28:28,Realizado!$2:$2,">="&'P&L Acumulado'!$G$1,Realizado!$2:$2,"<="&'P&L Acumulado'!$I$1),0) -> 0 | D34: 0 | E34: =IFERROR(C34/D34-1,"-") -> - | F34: =IFERROR(SUMIFS(Realizado!66:66,Realizado!$2:$2,">="&'P&L Acumulado'!$G$1,Realizado!$2:$2,"<="&'P&L Acumulado'!$I$1),0) -> 0 | G34: 0 | H34: =IFERROR(F34/G34-1,"-") -> - | I34: =IFERROR(SUMIFS(Realizado!110:110,Realizado!$2:$2,">="&'P&L Acumulado'!$G$1,Realizado!$2:$2,"<="&'P&L Acumulado'!$I$1),0) -> 0 | J34: 0 | K34: =IFERROR(I34/J34-1,"-") -> - | L34: =C34+F34+I34 -> 0 | M34: =D34+G34+J34 -> 0 | N34: =IFERROR(L34/M34-1,"-") -> - | O34: =ABS(L34)-ABS(M34) -> 0
B35: MG INTERMEDIAÇÃO LIQ | C35: =C31+C32 -> 0 | D35: =D31+D32 -> 0 | E35: =IFERROR(C35/D35-1,"-") -> - | F35: =F31+F32 -> 8082250.1 | G35: =G31+G32 -> 8200073.6 | H35: =IFERROR(F35/G35-1,"-") -> -0.01436859 | I35: =I31+I32 -> 32766269 | J35: =J31+J32 -> 30207672 | K35: =IFERROR(I35/J35-1,"-") -> 0.084700238 | L35: =L31+L32 -> 40848520 | M35: =M31+M32 -> 38407746 | N35: =IFERROR(L35/M35-1,"-") -> 0.063548992 | O35: =ABS(L35)-ABS(M35) -> 2440773.5
B36: Despesas Administrativas Diretas | C36: =IFERROR(SUMIFS(Realizado!30:30,Realizado!$2:$2,">="&'P&L Acumulado'!$G$1,Realizado!$2:$2,"<="&'P&L Acumulado'!$I$1),0) -> 0 | D36: =IFERROR(SUMIFS('Orçado '!30:30,'Orçado '!$2:$2,">="&'P&L Acumulado'!$G$1,Realizado!$2:$2,"<="&'P&L Acumulado'!$I$1),0) -> 0 | E36: =IFERROR(C36/D36-1,"-") -> - | F36: =IFERROR(SUMIFS(Realizado!68:68,Realizado!$2:$2,">="&'P&L Acumulado'!$G$1,Realizado!$2:$2,"<="&'P&L Acumulado'!$I$1),0) -> -1351895 | G36: =IFERROR(SUMIFS('Orçado '!71:71,'Orçado '!$2:$2,">="&'P&L Acumulado'!$G$1,Realizado!$2:$2,"<="&'P&L Acumulado'!$I$1),0) -> -1385981.9 | H36: =IFERROR(F36/G36-1,"-") -> -0.024594049 | I36: =IFERROR(SUMIFS(Realizado!112:112,Realizado!$2:$2,">="&'P&L Acumulado'!$G$1,Realizado!$2:$2,"<="&'P&L Acumulado'!$I$1),0) -> -5682614 | J36: =IFERROR(SUMIFS('Orçado '!115:115,'Orçado '!$2:$2,">="&'P&L Acumulado'!$G$1,Realizado!$2:$2,"<="&'P&L Acumulado'!$I$1),0) -> -6306934 | K36: =IFERROR(I36/J36-1,"-") -> -0.098989462 | L36: =C36+F36+I36 -> -7034509 | M36: =D36+G36+J36 -> -7692915.9 | N36: =IFERROR(L36/M36-1,"-") -> -0.085586131 | O36: =ABS(L36)-ABS(M36) -> -658406.91
B37: Comissão (Apoio - Comercial - Mídia Paga) | C37: =IFERROR(SUMIFS(Realizado!31:31,Realizado!$2:$2,">="&'P&L Acumulado'!$G$1,Realizado!$2:$2,"<="&'P&L Acumulado'!$I$1),0) -> 0 | D37: =IFERROR(SUMIFS('Orçado '!31:31,'Orçado '!$2:$2,">="&'P&L Acumulado'!$G$1,Realizado!$2:$2,"<="&'P&L Acumulado'!$I$1),0) -> 0 | E37: =IFERROR(C37/D37-1,"-") -> - | F37: =IFERROR(SUMIFS(Realizado!70:70,Realizado!$2:$2,">="&'P&L Acumulado'!$G$1,Realizado!$2:$2,"<="&'P&L Acumulado'!$I$1),0) -> -302002.27 | G37: =IFERROR(SUMIFS('Orçado '!72:72,'Orçado '!$2:$2,">="&'P&L Acumulado'!$G$1,Realizado!$2:$2,"<="&'P&L Acumulado'!$I$1),0) -> 0 | H37: =IFERROR(F37/G37-1,"-") -> - | I37: =IFERROR(SUMIFS(Realizado!114:114,Realizado!$2:$2,">="&'P&L Acumulado'!$G$1,Realizado!$2:$2,"<="&'P&L Acumulado'!$I$1),0) -> -1070735 | J37: =IFERROR(SUMIFS('Orçado '!116:116,'Orçado '!$2:$2,">="&'P&L Acumulado'!$G$1,Realizado!$2:$2,"<="&'P&L Acumulado'!$I$1),0) -> -606623.38 | K37: =IFERROR(I37/J37-1,"-") -> 0.76507379 | L37: =C37+F37+I37 -> -1372737.3 | M37: =D37+G37+J37 -> -606623.38 | N37: =IFERROR(L37/M37-1,"-") -> 1.2629153 | O37: =ABS(L37)-ABS(M37) -> 766113.91
B38: MG CONTRIBUIÇÃO DIRETA | C38: =C35+C36+C37 -> 0 | D38: =D35+D36+D37 -> 0 | E38: =IFERROR(C38/D38-1,"-") -> - | F38: =F35+F36+F37 -> 6428352.9 | G38: =G35+G36+G37 -> 6814091.7 | H38: =IFERROR(F38/G38-1,"-") -> -0.056608991 | I38: =I35+I36+I37 -> 26012920 | J38: =J35+J36+J37 -> 23294115 | K38: =IFERROR(I38/J38-1,"-") -> 0.11671641 | L38: =L35+L36+L37 -> 32441273 | M38: =M35+M36+M37 -> 30108207 | N38: =IFERROR(L38/M38-1,"-") -> 0.077489389 | O38: =ABS(L38)-ABS(M38) -> 2333066.5
B39: Desp. Administrativas Indiretas | C39: =IFERROR(SUMIFS(Realizado!33:33,Realizado!$2:$2,">="&'P&L Acumulado'!$G$1,Realizado!$2:$2,"<="&'P&L Acumulado'!$I$1),0) -> 0 | D39: =IFERROR(SUMIFS('Orçado '!33:33,'Orçado '!$2:$2,">="&'P&L Acumulado'!$G$1,Realizado!$2:$2,"<="&'P&L Acumulado'!$I$1),0) -> 0 | E39: =IFERROR(C39/D39-1,"-") -> - | F39: =IFERROR(SUMIFS(Realizado!72:72,Realizado!$2:$2,">="&'P&L Acumulado'!$G$1,Realizado!$2:$2,"<="&'P&L Acumulado'!$I$1),0) -> -1843131.1 | G39: =IFERROR(SUMIFS('Orçado '!74:74,'Orçado '!$2:$2,">="&'P&L Acumulado'!$G$1,Realizado!$2:$2,"<="&'P&L Acumulado'!$I$1),0) -> -1780512.1 | H39: =IFERROR(F39/G39-1,"-") -> 0.035169075 | I39: =IFERROR(SUMIFS(Realizado!116:116,Realizado!$2:$2,">="&'P&L Acumulado'!$G$1,Realizado!$2:$2,"<="&'P&L Acumulado'!$I$1),0) -> -5790453.2 | J39: =IFERROR(SUMIFS('Orçado '!118:118,'Orçado '!$2:$2,">="&'P&L Acumulado'!$G$1,Realizado!$2:$2,"<="&'P&L Acumulado'!$I$1),0) -> -6168799.2 | K39: =IFERROR(I39/J39-1,"-") -> -0.061332195 | L39: =F39+I39 -> -7633584.3 | M39: =G39+J39 -> -7949311.4 | N39: =IFERROR(L39/M39-1,"-") -> -0.039717533 | O39: =ABS(L39)-ABS(M39) -> -315727.03
B40: Amortização | F40: =IFERROR(SUMIFS(Realizado!$69:$69,Realizado!$2:$2,">="&'P&L Acumulado'!$G$1,Realizado!$2:$2,"<="&'P&L Acumulado'!$I$1),0) -> -286940.9 | G40: =IFERROR(SUMIFS('Orçado '!75:75,'Orçado '!$2:$2,">="&'P&L Acumulado'!$G$1,Realizado!$2:$2,"<="&'P&L Acumulado'!$I$1),0) -> -292777.96 | H40: =IFERROR(F40/G40-1,"-") -> -0.019936811 | I40: =IFERROR(SUMIFS(Realizado!$113:$113,Realizado!$2:$2,">="&'P&L Acumulado'!$G$1,Realizado!$2:$2,"<="&'P&L Acumulado'!$I$1),0) -> -1019094.3 | J40: =IFERROR(SUMIFS('Orçado '!119:119,'Orçado '!$2:$2,">="&'P&L Acumulado'!$G$1,Realizado!$2:$2,"<="&'P&L Acumulado'!$I$1),0) -> -1038031 | K40: =IFERROR(I40/J40-1,"-") -> -0.018242844 | L40: =F40+I40 -> -1306035.2 | M40: =G40+J40 -> -1330808.9 | N40: =IFERROR(L40/M40-1,"-") -> -0.018615516 | O40: =ABS(L40)-ABS(M40) -> -24773.695
B41: RESULTADO ANTES IMPOSTO | C41: =C38+C39 -> 0 | D41: =D38+D39 -> 0 | E41: =IFERROR(C41/D41-1,"-") -> - | F41: =F38+F39+F40 -> 4298280.9 | G41: =G38+G39+G40 -> 4740801.7 | H41: =IFERROR(F41/G41-1,"-") -> -0.093343024 | I41: =I38+I39+I40 -> 19203373 | J41: =J38+J39+J40 -> 16087285 | K41: =IFERROR(I41/J41-1,"-") -> 0.19369882 | L41: =L38+L39+L40 -> 23501654 | M41: =M38+M39+M40 -> 20828086 | N41: =IFERROR(L41/M41-1,"-") -> 0.12836356 | O41: =ABS(L41)-ABS(M41) -> 2673567.3
B42: Impostos (IR/CSLL) | C42: =IFERROR(SUMIFS(Realizado!35:35,Realizado!$2:$2,">="&'P&L Acumulado'!$G$1,Realizado!$2:$2,"<="&'P&L Acumulado'!$I$1),0) -> 0 | D42: =IFERROR(SUMIFS('Orçado '!35:35,'Orçado '!$2:$2,">="&'P&L Acumulado'!$G$1,Realizado!$2:$2,"<="&'P&L Acumulado'!$I$1),0) -> 0 | E42: =IFERROR(C42/D42-1,"-") -> - | F42: =IFERROR(SUMIFS(Realizado!74:74,Realizado!$2:$2,">="&'P&L Acumulado'!$G$1,Realizado!$2:$2,"<="&'P&L Acumulado'!$I$1),0) -> -1034735.7 | G42: =IFERROR(SUMIFS('Orçado '!77:77,'Orçado '!$2:$2,">="&'P&L Acumulado'!$G$1,Realizado!$2:$2,"<="&'P&L Acumulado'!$I$1),0) -> -1191100.8 | H42: =IFERROR(F42/G42-1,"-") -> -0.13127785 | I42: =IFERROR(SUMIFS(Realizado!118:118,Realizado!$2:$2,">="&'P&L Acumulado'!$G$1,Realizado!$2:$2,"<="&'P&L Acumulado'!$I$1),0) -> -6617628.8 | J42: =IFERROR(SUMIFS('Orçado '!121:121,'Orçado '!$2:$2,">="&'P&L Acumulado'!$G$1,Realizado!$2:$2,"<="&'P&L Acumulado'!$I$1),0) -> -4227633.7 | K42: =IFERROR(I42/J42-1,"-") -> 0.56532693 | L42: =C42+F42+I42 -> -7652364.5 | M42: =D42+G42+J42 -> -5418734.5 | N42: =IFERROR(L42/M42-1,"-") -> 0.4122051 | O42: =L42-M42 -> -2233630
B43: RESULTADO CONTÁBIL | C43: =#REF!+C23+#REF!+#REF! -> #REF! | D43: =#REF!+D23+#REF!+#REF! -> #REF! | E43: =IFERROR(C43/D43-1,"-") -> - | F43: =F41+F42 -> 3263545.2 | G43: =G41+G42 -> 3549700.8 | H43: =IFERROR(F43/G43-1,"-") -> -0.080614007 | I43: =I41+I42 -> 12585744 | J43: =J41+J42 -> 11859651 | K43: =IFERROR(I43/J43-1,"-") -> 0.061223799 | L43: =L41+L42 -> 15849289 | M43: =M41+M42 -> 15409352 | N43: =IFERROR(L43/M43-1,"-") -> 0.028550019 | O43: =ABS(L43)-ABS(M43) -> 439937.29
B44: Margem Bruta | C44: =IFERROR(((C31/C49)*N1),0) -> 0 | D44: =IFERROR(((D31/D49)*#REF!),0) -> 0 | E44: =IFERROR(C44/D44-1,"-") -> - | F44: =((F31/F49)*N1) -> 0.09577287 | G44: =((G31/G49)*N1) -> 0.097618504 | H44: =IFERROR(F44-G44,"-") -> -0.0018456344 | I44: =((I31/I49)*N1) -> 0.093272028 | J44: =((J31/J49)*N1) -> 0.088770703 | K44: =IFERROR(I44-J44,"-") -> 0.0045013252 | L44: =((L31/L49)*N1) -> 0.093791367 | M44: =((M31/M49)*N1) -> #DIV/0! | N44: =IFERROR(L44-M44,"-") -> -
B45: Margem Liquida | C45: =IFERROR(((C35/C49)*N1),0) -> 0 | D45: =IFERROR(((D35/D49)*#REF!),0) -> 0 | E45: =IFERROR(C45/D45-1,"-") -> - | F45: =((F35/F49)*N1) -> 0.078805795 | G45: =((G35/G49)*N1) -> 0.079587943 | H45: =IFERROR(F45-G45,"-") -> -0.00078214861 | I45: =((I35/I49)*N1) -> 0.083735269 | J45: =((J35/J49)*N1) -> 0.078997432 | K45: =IFERROR(I45-J45,"-") -> 0.0047378374 | L45: =((L35/L49)*N1) -> 0.082711588 | M45: =((M35/M49)*N1) -> #DIV/0! | N45: =IFERROR(L45-M45,"-") -> -
B46: Rácio de Eficiência | C46: =IFERROR((C36+C39)/C31,0) -> 0 | D46: =IFERROR((D36+D39)/D31,0) -> 0 | E46: =IFERROR(C46/D46-1,"-") -> - | F46: =(F36+F39)/F31 -> -0.32528031 | G46: =(G36+G39)/G31 -> -0.31482996 | H46: =IFERROR(F46-G46,"-") -> -0.010450348 | I46: =(I36+I39)/I31 -> -0.31434716 | J46: =(J36+J39)/J31 -> -0.36752944 | K46: =IFERROR(I46-J46,"-") -> 0.053182278 | L46: =(L36+L39)/L31 -> -0.31666556 | M46: =(M36+M39)/M31 -> -0.35548379 | N46: =IFERROR(L46-M46,"-") -> 0.038818227
B47: Rácio de Eficiência Recorrente | C47: =IFERROR((C36+C39+#REF!)/C31,0) -> 0 | D47: =IFERROR((D36+D39+#REF!)/D31,0) -> 0 | E47: =IFERROR(C47/D47-1,"-") -> - | F47: =(F36+F39+F40)/F31 -> -0.35449328 | G47: =(G36+G39+#REF!)/G31 -> #REF! | H47: =IFERROR(F47-G47,"-") -> - | I47: =(I36+I39+#REF!)/I31 -> #REF! | J47: =(J36+J39+#REF!)/J31 -> #REF! | K47: =IFERROR(I47-J47,"-") -> - | L47: =(L36+L39+#REF!)/L31 -> #REF! | M47: =(M36+M39+#REF!)/M31 -> #REF! | N47: =IFERROR(L47-M47,"-") -> -
B48: RPL - RES. CONTÁBIL | C48: =IFERROR(((C43/#REF!)*N1),0) -> 0 | D48: =IFERROR(((D43/#REF!)*#REF!),0) -> 0 | E48: =IFERROR(C48/D48-1,"-") -> - | F48: =((F43/F57)*N1) -> #DIV/0! | G48: =((G43/#REF!)*N1) -> #REF! | H48: =IFERROR(F48-G48,"-") -> - | I48: =((I43/#REF!)*N1) -> #REF! | J48: =((J43/#REF!)*N1) -> #REF! | K48: =IFERROR(I48-J48,"-") -> - | L48: =((L43/#REF!)*N1) -> #REF! | M48: =((M43/#REF!)*N1) -> #REF! | N48: =IFERROR(L48-M48,"-") -> -
B49: Carteira de Crédito Bruta Média | C49: =AVERAGE(INDEX(Realizado!$127:$127,MATCH($G$1,Realizado!$2:$2,0)),INDEX(Realizado!$127:$127,MATCH($I$1,Realizado!$2:$2,0))) -> #DIV/0! | D49: =AVERAGE(INDEX('Orçado '!127:127,MATCH($G$1,'Orçado '!$2:$2,0)),INDEX('Orçado '!127:127,MATCH($I$1,'Orçado '!$2:$2,0))) -> #DIV/0! | E49: =IFERROR(C49/D49-1,"-") -> - | F49: =AVERAGE(INDEX(Realizado!$128:$128,MATCH($G$1,Realizado!$2:$2,0)),INDEX(Realizado!$128:$128,MATCH($I$1,Realizado!$2:$2,0))) -> 4.1023634e+08 | G49: =AVERAGE(INDEX('Orçado '!128:128,MATCH($I$1,'Orçado '!$2:$2,0)),INDEX('Orçado '!128:128,MATCH($G$1,'Orçado '!$2:$2,0))) -> 4.1212642e+08 | H49: =IFERROR(F49/G49-1,"-") -> -0.0045861844 | I49: =AVERAGE(INDEX(Realizado!$129:$129,MATCH($G$1,Realizado!$2:$2,0)),INDEX(Realizado!$129:$129,MATCH($I$1,Realizado!$2:$2,0))) -> 1.5652315e+09 | J49: =AVERAGE(INDEX('Orçado '!129:129,MATCH($I$1,'Orçado '!$2:$2,0)),INDEX('Orçado '!129:129,MATCH($G$1,'Orçado '!$2:$2,0))) -> 1.5295521e+09 | K49: =IFERROR(I49/J49-1,"-") -> 0.023326657 | L49: =IFERROR(C49,0)+F49+I49 -> 1.9754678e+09 | M49: =D49+G49+J49 -> #DIV/0! | N49: =IFERROR(L49/M49-1,"-") -> - | O49: =M49-L49 -> #DIV/0!
B50: Carteira de Crédito SD Cliente Média | F50: =AVERAGE(INDEX(Realizado!$132:$132,MATCH($G$1,Realizado!$2:$2,0)),INDEX(Realizado!$128:$128,MATCH($I$1,Realizado!$2:$2,0))) -> 4.09081e+08 | G50: =AVERAGE(INDEX('Orçado '!134:134,MATCH($I$1,'Orçado '!$2:$2,0)),INDEX('Orçado '!134:134,MATCH($G$1,'Orçado '!$2:$2,0))) -> 4.1052279e+08 | H50: =IFERROR(F50/G50-1,"-") -> -0.0035120796 | I50: =AVERAGE(INDEX(Realizado!$133:$133,MATCH($G$1,Realizado!$2:$2,0)),INDEX(Realizado!$133:$133,MATCH($I$1,Realizado!$2:$2,0))) -> 1.5407948e+09 | J50: =AVERAGE(INDEX('Orçado '!135:135,MATCH($I$1,'Orçado '!$2:$2,0)),INDEX('Orçado '!135:135,MATCH($G$1,'Orçado '!$2:$2,0))) -> 1.5020227e+09 | K50: =IFERROR(I50/J50-1,"-") -> 0.025813233 | L50: =IFERROR(C50,0)+F50+I50 -> 1.9498758e+09 | M50: =D50+G50+J50 -> 1.9125455e+09 | N50: =IFERROR(L50/M50-1,"-") -> 0.019518633 | O50: =M50-L50 -> -37330273
B52: Taxa Média Carteira Bruta Média | C52: 0.019026332 | D52: 0.01872293 | E52: 0.016204825
B53: Taxa Média Carteira SD Cliente Média | C53: 0.019134686 | D53: 0.01878539 | E53: 0.018594041
B55: Rateio Carteira | C55: 0.21616784 | D55: 0.21770121 | E55: -0.0070434626
B56: Alocação de Capital | C56: 42965667 | D56: 43078625 | E56: -0.0026221344
B58: PL Médio (Banco + Hipo)
B59: PL Médio (Prudencial + BRCards)
B60: Margem Bruta | C60: =((C47/C65)*$N$1) -> 0 | D60: =((D47/D65)*$N$1) -> #DIV/0! | E60: =IFERROR(C60-D60,"-")*100 -> #VALUE! | F60: =(F31/F65)*$N$1 -> 0.095784008 | G60: =(G31/G65)*$N$1 -> 0.097645562 | H60: =IFERROR(F60-G60,"-")*100 -> -0.1861554 | I60: =(I31/I65)*$N$1 -> 0.093472594 | J60: =(J31/J65)*$N$1 -> 0.08891135 | K60: =IFERROR(I60-J60,"-")*100 -> 0.45612444 | L60: =(L31/L65)*$N$1 -> 0.093953368 | M60: =(M31/M65)*$N$1 -> 0.090767117 | N60: =IFERROR(L60-M60,"-")*100 -> 0.31862506
B61: Margem Liquida | C61: =((C51/C65)*$N$1) -> 0 | D61: =((D51/D65)*$N$1) -> #DIV/0! | E61: =IFERROR(C61-D61,"-")*100 -> #VALUE! | F61: =(F35/F65)*$N$1 -> 0.078814959 | G61: =(G35/G65)*$N$1 -> 0.079610003 | H61: =IFERROR(F61-G61,"-")*100 -> -0.079504369 | I61: =(I35/I65)*$N$1 -> 0.083915327 | J61: =(J35/J65)*$N$1 -> 0.079122594 | K61: =IFERROR(I61-J61,"-")*100 -> 0.4792734 | L61: =(L35/L65)*$N$1 -> 0.082854451 | M61: =(M35/M65)*$N$1 -> 0.079226154 | N61: =IFERROR(L61-M61,"-")*100 -> 0.36282974
B62: Rácio de Eficiência | C62: =(C52+C55)/(C47) -> #DIV/0! | D62: =(D52+D55)/(D47) -> #DIV/0! | E62: =IFERROR(C62-D62,"-")*100 -> #VALUE! | F62: =(F36+F39)/F31 -> -0.32528031 | G62: =(G36+G39)/G31 -> -0.31482996 | H62: =IFERROR(F62-G62,"-")*100 -> -1.0450348 | I62: =(I36+I39)/I31 -> -0.31434716 | J62: =(J36+J39)/J31 -> -0.36752944 | K62: =IFERROR(I62-J62,"-")*100 -> 5.3182278 | L62: =(L36+L39)/L31 -> -0.31666556 | M62: =(M36+M39)/M31 -> -0.35548379 | N62: =IFERROR(L62-M62,"-")*100 -> 3.8818227
B63: Rácio de Eficiência Recorrente | C63: =(C52+C55+C56)/C47 -> #DIV/0! | D63: =(D52+D55+D56)/D47 -> #DIV/0! | E63: =IFERROR(C63-D63,"-")*100 -> #VALUE! | F63: =(F36+F39+F40)/(F31) -> -0.35449328 | G63: =(G36+G39+G40)/(G31) -> -0.34393953 | H63: =IFERROR(F63-G63,"-")*100 -> -1.0553758 | I63: =(I36+I39+I40)/(I31) -> -0.34226902 | J63: =(J36+J39+J40)/(J31) -> -0.39810936 | K63: =IFERROR(I63-J63,"-")*100 -> 5.5840336 | L63: =(L36+L39+L40)/(L31) -> -0.34486121 | M63: =(M36+M39+M40)/(M31) -> -0.38572763 | N63: =IFERROR(L63-M63,"-")*100 -> 4.0866419
B64: RPL - RES. CONTÁBIL | C64: =((C59/C78)*$N$1) -> #DIV/0! | D64: =((D59/D78)*$N$1) -> #DIV/0! | E64: =IFERROR(C64-D64,"-")*100 -> #VALUE! | F64: =(F43/F68)*$N$1 -> 0.29542983 | G64: =(G43/G68)*$N$1 -> 0.3078745 | H64: =IFERROR(F64-G64,"-")*100 -> -1.2444677 | I64: =(I43/I68)*$N$1 -> 0.29921373 | J64: =(J43/J68)*$N$1 -> 0.28149478 | K64: =IFERROR(I64-J64,"-")*100 -> 1.771895 | L64: =(L43/L68)*$N$1 -> 0.29842668 | M64: =(M43/M68)*$N$1 -> 0.28716281 | N64: =IFERROR(L64-M64,"-")*100 -> 1.1263869
B65: Carteira de Crédito Bruta Média | C65: =AVERAGEIFS(Realizado!$128:$128,Realizado!$2:$2,">="&$G$1,Realizado!$2:$2,"<="&$I$1) -> 4.1018863e+08 | D65: =AVERAGEIFS('Orçado '!$144:$144,'Orçado '!$2:$2,">="&$G$1,'Orçado '!$2:$2,"<="&$I$1) -> #DIV/0! | E65: =IFERROR(C65/D65-1,"-") -> - | F65: =AVERAGEIFS(Realizado!$128:$128,Realizado!$2:$2,">="&$G$1,Realizado!$2:$2,"<="&$I$1) -> 4.1018863e+08 | G65: =AVERAGEIFS('Orçado '!$128:$128,'Orçado '!$2:$2,">="&$G$1,'Orçado '!$2:$2,"<="&$I$1) -> 4.1201222e+08 | H65: =IFERROR(F65/G65-1,"-") -> -0.0044260606 | I65: =AVERAGEIFS(Realizado!$129:$129,Realizado!$2:$2,">="&$G$1,Realizado!$2:$2,"<="&$I$1) -> 1.5618729e+09 | J65: =AVERAGEIFS('Orçado '!$129:$129,'Orçado '!$2:$2,">="&$G$1,'Orçado '!$2:$2,"<="&$I$1) -> 1.5271326e+09 | K65: =IFERROR(I65/J65-1,"-") -> 0.022748747 | L65: =F65+I65 -> 1.9720616e+09 | M65: =G65+J65 -> 1.9391448e+09 | N65: =IFERROR(L65/M65-1,"-") -> 0.016974886
B66: Carteira de Crédito SD Cliente Média | C66: =AVERAGEIFS(Realizado!$132:$132,Realizado!$2:$2,">="&$G$1,Realizado!$2:$2,"<="&$I$1) -> 4.0767667e+08 | D66: =AVERAGEIFS('Orçado '!$150:$150,'Orçado '!$2:$2,">="&$G$1,'Orçado '!$2:$2,"<="&$I$1) -> #DIV/0! | E66: =IFERROR(C66/D66-1,"-") -> - | F66: =AVERAGEIFS(Realizado!$132:$132,Realizado!$2:$2,">="&$G$1,Realizado!$2:$2,"<="&$I$1) -> 4.0767667e+08 | G66: =AVERAGEIFS('Orçado '!$134:$134,'Orçado '!$2:$2,">="&$G$1,'Orçado '!$2:$2,"<="&$I$1) -> 4.1040852e+08 | H66: =IFERROR(F66/G66-1,"-") -> -0.0066564089 | I66: =AVERAGEIFS(Realizado!$133:$133,Realizado!$2:$2,">="&$G$1,Realizado!$2:$2,"<="&$I$1) -> 1.5398897e+09 | J66: =AVERAGEIFS('Orçado '!$135:$135,'Orçado '!$2:$2,">="&$G$1,'Orçado '!$2:$2,"<="&$I$1) -> 1.4996845e+09 | K66: =IFERROR(I66/J66-1,"-") -> 0.026809139 | L66: =F66+I66 -> 1.9475664e+09 | M66: =G66+J66 -> 1.910093e+09 | N66: =IFERROR(L66/M66-1,"-") -> 0.019618628
B67: Rateio da Carteira | F67: =F65/$L$65 -> 0.20799991 | G67: =G66/$M$66 -> 0.21486311 | I67: =I65/$L$65 -> 0.79200009 | J67: =J66/$M$66 -> 0.78513689
B68: Alocação de Capital | F68: =F67*L69 -> 44187078 | G68: =G67*M69 -> 46118802 | I68: =I67*L69 -> 1.6825089e+08 | J68: =J67*M69 -> 1.6852392e+08 | L68: =F68+I68 -> 2.1243797e+08 | M68: =G68+J68 -> 2.1464272e+08
B69: PL Médio | L69: =AVERAGEIFS(Realizado!$136:$136,Realizado!$2:$2,">="&$G$1,Realizado!$2:$2,"<="&$I$1) -> 2.1243797e+08 | M69: =AVERAGEIFS('Orçado '!$137:$137,'Orçado '!$2:$2,">="&$G$1,'Orçado '!$2:$2,"<="&$I$1) -> 2.1464272e+08
L72: Realizado | M72: Orçado | N72: ∆
J73: Despesas Administrativas | L73: =L36+L39 -> -14668093 | M73: =M36+M39 -> -15642227 | N73: =(L73/M73)-1 -> -0.06227591

Sheet Orçado 
C1: Atualizado com novo orçado, aprovado em Nov/22. | D1: Atualizado com novo orçado, aprovado em Jan/23. | H1: Atualizado com novo orçado, prévia | L1: 0.45 | M1: 0.45 | N1: 0.45 | O1: 0.45 | P1: Orçamento aprovado em mar/24. | V1: Orçamento aprovado em mar/24, ajustando rateio (sem banco digital) e amortização. | AB1: Novo Orçamento (ainda não aprovado) | AN1: Novo Orçamento
A2: Banco Digital | B2: 44895 | C2: 44926 | D2: 44957 | E2: 44985 | F2: 45016 | G2: 45046 | H2: 45077 | I2: 45107 | J2: 45138 | K2: 45169 | L2: 45199 | M2: 45230 | N2: 45260 | O2: 45291 | P2: 45322 | Q2: 45351 | R2: 45382 | S2: 45412 | T2: 45443 | U2: 45473 | V2: 45504 | W2: 45535 | X2: 45565 | Y2: 45596 | Z2: 45626 | AA2: 45657 | AB2: 45688 | AC2: 45716 | AD2: 45747 | AE2: 45777 | AF2: 45808 | AG2: 45838 | AH2: 45869 | AI2: 45900 | AJ2: 45930 | AK2: 45961 | AL2: 45991 | AM2: 46022 | AN2: 46053 | AO2: 46081 | AP2: 46112 | AQ2: 46142 | AR2: 46173 | AS2: 46203 | AT2: 46234 | AU2: 46265 | AV2: 46295 | AW2: 46326 | AX2: 46356 | AY2: 46387
A3: RECEITAS | C3: 1010456.5 | D3: 1007654.3 | E3: 986848.21 | F3: 987136.31 | G3: 810641.77 | H3: 434765.62 | I3: 378126.73 | J3: 345117.14 | K3: 318971.5 | L3: 299833.98 | M3: 280534.75 | N3: 261365.79 | O3: 242103.5 | P3: 191159.27 | Q3: 183904.13 | R3: 177827.48 | S3: 173415.38 | T3: 168452.28 | U3: 167099.9
A4: Operações de Crédito | C4: 738266.48 | D4: 737161.34 | E4: 718069.74 | F4: 718728.65 | G4: 635364.06 | H4: 333080.3 | I4: 293659.13 | J4: 260661.37 | K4: 234209.86 | L4: 214704.55 | M4: 195199.25 | N4: 175693.95 | O4: 156188.64 | P4: 93834.041 | Q4: 85689.392 | R4: 78658.064 | S4: 73271.627 | T4: 67291.762 | U4: 64837.794
A5: Receita Juros | H5: 0 | I5: 0 | J5: 0 | K5: 0 | L5: 0 | M5: 0 | N5: 0 | O5: 0 | P5: 0 | Q5: 0 | R5: 0 | S5: 0 | T5: 0 | U5: 0
A6: Receita CM - Crédito Imobiliário | H6: 0 | I6: 0 | J6: 0 | K6: 0 | L6: 0 | M6: 0 | N6: 0 | O6: 0 | P6: 0 | Q6: 0 | R6: 0 | S6: 0 | T6: 0 | U6: 0
A7: Multa + Mora - Crédito Imobiliário | H7: 0 | I7: 0 | J7: 0 | K7: 0 | L7: 0 | M7: 0 | N7: 0 | O7: 0 | P7: 0 | Q7: 0 | R7: 0 | S7: 0 | T7: 0 | U7: 0
A8: Receita Juros - Cartão
A9: Receita Serviços | C9: 272190.03 | D9: 270492.95 | E9: 268778.47 | F9: 268407.66 | G9: 175277.71 | H9: 101685.32 | I9: 84467.599 | J9: 84455.771 | K9: 84761.64 | L9: 85129.43 | M9: 85335.498 | N9: 85671.841 | O9: 85914.863
A10: Receita Serviços | C10: 272190.03 | D10: 270492.95 | E10: 268778.47 | F10: 268407.66 | G10: 175277.71 | H10: 101685.32 | I10: 84467.599 | J10: 84455.771 | K10: 84761.64 | L10: 85129.43 | M10: 85335.498 | N10: 85671.841 | O10: 85914.863
A11: Receita de outras taxas e serviços
A12: Receita Interchange | P12: 97325.231 | Q12: 98214.738 | R12: 99169.415 | S12: 100143.76 | T12: 101160.51 | U12: 102262.11
A13: Receita Comissão CRI | C13: 0 | D13: 0 | E13: 0 | F13: 0 | G13: 0 | H13: 0 | I13: 0 | J13: 0 | K13: 0 | L13: 0 | M13: 0 | N13: 0 | O13: 0
A14: Receita Cobrança Ext. Cebraco | C14: 0 | D14: 0 | E14: 0 | F14: 0 | G14: 0 | H14: 0 | I14: 0 | J14: 0 | K14: 0 | L14: 0 | M14: 0 | N14: 0 | O14: 0
A15: Barigui Veículos
A16: Honorários
A17: Securitizadora (Patrimônio Separado)
A18: Resultado de Seguros | C18: 0 | D18: 0 | E18: 0 | F18: 0 | G18: 0 | H18: 0 | I18: 0 | J18: 0 | K18: 0 | L18: 0 | M18: 0 | N18: 0 | O18: 0
A19: Resultado Brasil Cards | C19: 0 | D19: 0 | E19: 0 | F19: 0 | G19: 0 | H19: 0 | I19: 0 | J19: 0 | K19: 0 | L19: 0 | M19: 0 | N19: 0 | O19: 0
A20: DESPESAS DE ORIGINAÇÃO | C20: 135676.79 | D20: 135891.08 | E20: 111260.33 | F20: 142447.36 | G20: 106849.08 | H20: 61989.289 | I20: 28977.939 | J20: 41283.297 | K20: 78193.713 | L20: 44488.392 | M20: 71511.921 | N20: 56967.043 | O20: 64016.82 | P20: 121582.33 | Q20: 91905.012 | R20: 115374.66 | S20: 131458.29 | T20: 126861.25 | U20: 119375.08
A21: Despesa de Captação | C21: 135676.79 | D21: 135891.08 | E21: 111260.33 | F21: 142447.36 | G21: 106849.08 | H21: 61989.289 | I21: 28977.939 | J21: 41283.297 | K21: 78193.713 | L21: 44488.392 | M21: 71511.921 | N21: 56967.043 | O21: 64016.82 | P21: 121582.33 | Q21: 91905.012 | R21: 115374.66 | S21: 131458.29 | T21: 126861.25 | U21: 119375.08
A22: Inflação | H22: 0 | I22: 0 | J22: 0 | K22: 0 | L22: 0 | M22: 0 | N22: 0 | O22: 0 | P22: 0 | Q22: 0 | R22: 0 | S22: 0 | T22: 0 | U22: 0
A23: DI/Pré | C23: 135676.79 | D23: 135891.08 | E23: 111260.33 | F23: 142447.36 | G23: 106849.08 | H23: 61989.289 | I23: 28977.939 | J23: 41283.297 | K23: 78193.713 | L23: 44488.392 | M23: 71511.921 | N23: 56967.043 | O23: 64016.82 | P23: 121582.33 | Q23: 91905.012 | R23: 115374.66 | S23: 131458.29 | T23: 126861.25 | U23: 119375.08
A24: Outros | H24: 0 | I24: 0 | J24: 0 | K24: 0 | L24: 0 | M24: 0 | N24: 0 | O24: 0 | P24: 0 | Q24: 0 | R24: 0 | S24: 0 | T24: 0 | U24: 0
A25: Swap | P25: 0 | Q25: 0 | R25: 0 | S25: 0 | T25: 0 | U25: 0
A26: Impostos Diretos | C26: -31813.383 | D26: -31745.519 | E26: -31307.673 | F26: -30733.818 | G26: -27883.411 | H26: -10382.268 | I26: -8700.8068 | J26: -7753.5409 | K26: -7683.4262 | L26: -6222.0649 | M26: -6403.6546 | N26: -5226.13 | O26: -4765.5102 | P26: -822.32686 | Q26: -586.44274 | R26: -981.66533 | S26: -868.82069 | T26: -985.3055 | U26: -989.1421
A27: MARGEM INTERMEDIAÇÃO | C27: 1114319.9 | D27: 1111799.9 | E27: 1066800.9 | F27: 1098849.8 | G27: 889607.44 | H27: 486372.64 | I27: 398403.86 | J27: 378646.89 | K27: 389481.79 | L27: 338100.31 | M27: 345643.01 | N27: 313106.7 | O27: 301354.81 | P27: 311919.27 | Q27: 275222.7 | R27: 292220.47 | S27: 304004.86 | T27: 294328.22 | U27: 285485.84
A28: Provisões | C28: -738266.48 | D28: -737161.34 | E28: -718069.74 | F28: -718728.65 | G28: -635364.06 | H28: -847247.93 | I28: -702857.61 | J28: -491417.24 | K28: -276009.31 | L28: -47683.363 | M28: -43712.23 | N28: -39741.097 | O28: -35769.964 | P28: -107207.94 | Q28: -55604.424 | R28: -31946.553 | S28: -3548.7094 | T28: -3548.7094 | U28: -3548.7094
A29: MG INTERMEDIAÇÃO LIQ | C29: 376053.43 | D29: 374638.51 | E29: 348731.13 | F29: 380121.2 | G29: 254243.38 | H29: -360875.29 | I29: -304453.76 | J29: -112770.34 | K29: 113472.48 | L29: 290416.95 | M29: 301930.78 | N29: 273365.6 | O29: 265584.85 | P29: 204711.34 | Q29: 219618.27 | R29: 260273.92 | S29: 300456.15 | T29: 290779.51 | U29: 281937.13
A30: Despesas Administrativas Diretas | C30: -1835680.9 | D30: -1872903.9 | E30: -1973448.1 | F30: -1675131.6 | G30: -1515173.2 | H30: -1656297.2 | I30: -1636925.4 | J30: -1643365.5 | K30: -1647355.6 | L30: -1608891.6 | M30: -1612692.6 | N30: -1599845.2 | O30: -1562792.5 | P30: -1397067.6 | Q30: -1386066.1 | R30: -1383861 | S30: -1384592.3 | T30: -1380231.7 | U30: -1391303.2
A31: Comissão Correspondentes | C31: 0 | D31: 0 | E31: 0 | F31: 0 | G31: 0 | H31: 0 | I31: 0 | J31: 0 | K31: 0 | L31: 0 | M31: 0 | N31: 0 | O31: 0 | P31: 0 | Q31: 0 | R31: 0 | S31: 0 | T31: 0 | U31: 0
A32: MG CONTRIBUIÇÃO DIRETA | C32: -1459627.5 | D32: -1498265.4 | E32: -1624717 | F32: -1295010.4 | G32: -1260929.9 | H32: -2017172.5 | I32: -1941379.2 | J32: -1756135.9 | K32: -1533883.1 | L32: -1318474.7 | M32: -1310761.8 | N32: -1326479.6 | O32: -1297207.7 | P32: -1192356.3 | Q32: -1166447.9 | R32: -1123587.1 | S32: -1084136.2 | T32: -1089452.1 | U32: -1109366.1
A33: Desp. Administrativas Indiretas | C33: -429597.2 | D33: -437997.2 | E33: -439327.61 | F33: -421436.57 | G33: -417625.25 | H33: -429779.03 | I33: -438613.88 | J33: -438613.88 | K33: -438613.88 | L33: -431988.88 | M33: -431988.88 | N33: -431988.88 | O33: -431988.88 | P33: -465132.67 | Q33: -467824.98 | R33: -469806.8 | S33: -469806.8 | T33: -469806.8 | U33: -482605.71
A34: RESULTADO ANTES IMPOSTO | C34: -1889224.7 | D34: -1936262.6 | E34: -2064044.6 | F34: -1716446.9 | G34: -1678555.1 | H34: -2446951.5 | I34: -2379993 | J34: -2194749.7 | K34: -1972497 | L34: -1750463.5 | M34: -1742750.7 | N34: -1758468.5 | O34: -1729196.5 | P34: -1657489 | Q34: -1634272.8 | R34: -1593393.9 | S34: -1553943 | T34: -1559258.9 | U34: -1591971.8
A35: Impostos (IR/CSLL) | C35: 850151.12 | D35: 871318.16 | E35: 928820.05 | F35: 772401.13 | G35: 755349.8 | H35: 978780.61 | I35: 951997.21 | J35: 877899.89 | K35: 788998.79 | L35: 787708.59 | M35: 784237.82 | N35: 791310.81 | O35: 778138.44 | P35: 662995.59 | Q35: 653709.13 | R35: 637357.54 | S35: 621577.18 | T35: 623703.58 | U35: 636788.73
A36: RESULTADO ANTES PARTICIPAÇÃO | C36: -1039073.6 | D36: -1064944.4 | E36: -1135224.5 | F36: -944045.82 | G36: -923205.31 | H36: -1468170.9 | I36: -1427995.8 | J36: -1316849.8 | K36: -1183498.2 | L36: -962754.95 | M36: -958512.89 | N36: -967157.66 | O36: -951058.09 | P36: -994493.39 | Q36: -980563.7 | R36: -956036.32 | S36: -932365.78 | T36: -935555.36 | U36: -955183.1
A37: PART. CONTROLADAS (GESTAO + SEC) | C37: 0 | D37: 0 | E37: 0 | F37: 0 | G37: 0 | H37: 0 | I37: 0 | J37: 0 | K37: 0 | L37: 0 | M37: 0 | N37: 0 | O37: 0 | P37: 0 | Q37: 0 | R37: 0 | S37: 0 | T37: 0 | U37: 0
A38: RESULTADO CONTÁBIL | C38: -1039073.6 | D38: -1064944.4 | E38: -1135224.5 | F38: -944045.82 | G38: -923205.31 | H38: -1468170.9 | I38: -1427995.8 | J38: -1316849.8 | K38: -1183498.2 | L38: -962754.95 | M38: -958512.89 | N38: -967157.66 | O38: -951058.09 | P38: -994493.39 | Q38: -980563.7 | R38: -956036.32 | S38: -932365.78 | T38: -935555.36 | U38: -955183.1
A40: Consignado | AK40: 45961 | AL40: 45991 | AM40: 46022 | AN40: 46053 | AO40: 46081 | AP40: 46112 | AQ40: 46142 | AR40: 46173 | AS40: 46203 | AT40: 46234 | AU40: 46265 | AV40: 46295 | AW40: 46326 | AX40: 46356 | AY40: 46387
A41: RECEITAS | AK41: 7566322.8 | AL41: 7624696.9 | AM41: 8567872.1 | AN41: 7701714.3 | AO41: 6991516.2 | AP41: 7759392.7 | AQ41: 7551512 | AR41: 7837760.5 | AS41: 7626952.8 | AT41: 7915101.7 | AU41: 7957281.7 | AV41: 7742730.8 | AW41: 8034591.5 | AX41: 7819668.9 | AY41: 8113540.7
A42: Operações de Crédito | AK42: 7553856.2 | AL42: 7612230.3 | AM42: 8555405.6 | AN42: 7701714.3 | AO42: 6991516.2 | AP42: 7759392.7 | AQ42: 7551512 | AR42: 7837760.5 | AS42: 7626952.8 | AT42: 7915101.7 | AU42: 7957281.7 | AV42: 7742730.8 | AW42: 8034591.5 | AX42: 7819668.9 | AY42: 8113540.7
A43: Receita Juros | AK43: 5801472.1 | AL43: 5921701.6 | AM43: 6819812.3 | AN43: 5963467 | AO43: 5428491 | AP43: 6046154.6 | AQ43: 5903016.4 | AR43: 6147095.5 | AS43: 6000520.8 | AT43: 6247547 | AU43: 6300778.4 | AV43: 6149762.5 | AW43: 6401948.2 | AX43: 6249989.7 | AY43: 6505271
A44: Receita de Juros PMT | AK44: 5816589.1 | AL44: 6051310.5 | AM44: 6375548.9 | AN44: 6005125.1 | AO44: 5480059.1 | AP44: 6098549.7 | AQ44: 5955334.9 | AR44: 6200782.7 | AS44: 6054725 | AT44: 6303928.1 | AU44: 6358917 | AV44: 6208780.2 | AW44: 6463987.1 | AX44: 6313056.2 | AY44: 6571734.5
A45: Custo de originação diferido TJEO | AK45: -15117 | AL45: -129608.94 | AM45: 444263.42 | AN45: -41658.085 | AO45: -51568.066 | AP45: -52395.037 | AQ45: -52318.467 | AR45: -53687.161 | AS45: -54204.24 | AT45: -56381.087 | AU45: -58138.621 | AV45: -59017.745 | AW45: -62038.887 | AX45: -63066.492 | AY45: -66463.501
A46: Receita CM - Crédito Imobiliário | AK46: 0 | AL46: 0 | AM46: 0 | AN46: 0 | AO46: 0 | AP46: 0 | AQ46: 0 | AR46: 0 | AS46: 0 | AT46: 0 | AU46: 0 | AV46: 0 | AW46: 0 | AX46: 0 | AY46: 0
A47: Multa + Mora - Crédito Imobiliário | AK47: 0 | AL47: 0 | AM47: 0 | AN47: 0 | AO47: 0 | AP47: 0 | AQ47: 0 | AR47: 0 | AS47: 0 | AT47: 0 | AU47: 0 | AV47: 0 | AW47: 0 | AX47: 0 | AY47: 0
A48: Receita Juros - Cartão | AK48: 1752384.1 | AL48: 1690528.7 | AM48: 1735593.3 | AN48: 1725780.8 | AO48: 1550558.7 | AP48: 1700771.4 | AQ48: 1636029 | AR48: 1678198.5 | AS48: 1613965.5 | AT48: 1655088.1 | AU48: 1644036.8 | AV48: 1580501.8 | AW48: 1620176.8 | AX48: 1557212.6 | AY48: 1595803.2
A49: Receita Serviços | AK49: 0 | AL49: 0 | AM49: 0 | AN49: 0 | AO49: 0 | AP49: 0 | AQ49: 0 | AR49: 0 | AS49: 0 | AT49: 0 | AU49: 0 | AV49: 0 | AW49: 0 | AX49: 0 | AY49: 0
A50: Receita Serviços
A51: Receita de outras taxas e serviços
A52: Receita Interchange | AK52: 12466.562 | AL52: 12466.562 | AM52: 12466.562 | AN52: 12466.562 | AO52: 12466.562 | AP52: 12466.562 | AQ52: 12466.562 | AR52: 12466.562 | AS52: 12466.562 | AT52: 12466.562 | AU52: 12466.562 | AV52: 12466.562 | AW52: 12466.562 | AX52: 12466.562 | AY52: 12466.562
A53: Receita Comissão CRI | AK53: 0 | AL53: 0 | AM53: 0 | AN53: 0 | AO53: 0 | AP53: 0 | AQ53: 0 | AR53: 0 | AS53: 0 | AT53: 0 | AU53: 0 | AV53: 0 | AW53: 0 | AX53: 0 | AY53: 0
A54: Receita Cobrança Ext. Cebraco | AK54: 0 | AL54: 0 | AM54: 0 | AN54: 0 | AO54: 0 | AP54: 0 | AQ54: 0 | AR54: 0 | AS54: 0 | AT54: 0 | AU54: 0 | AV54: 0 | AW54: 0 | AX54: 0 | AY54: 0
A55: Barigui Veículos
A56: Honorários
A57: Securitizadora (Patrimônio Separado)
A58: Resultado de Seguros | AK58: 0 | AL58: 0 | AM58: 0 | AN58: 0 | AO58: 0 | AP58: 0 | AQ58: 0 | AR58: 0 | AS58: 0 | AT58: 0 | AU58: 0 | AV58: 0 | AW58: 0 | AX58: 0 | AY58: 0
A59: Resultado Brasil Cards | AK59: 0 | AL59: 0 | AM59: 0 | AN59: 0 | AO59: 0 | AP59: 0 | AQ59: 0 | AR59: 0 | AS59: 0 | AT59: 0 | AU59: 0 | AV59: 0 | AW59: 0 | AX59: 0 | AY59: 0
A60: Resultado Bari Capital | AK60: 0 | AL60: 0 | AM60: 0 | AN60: 0 | AO60: 0 | AP60: 0 | AQ60: 0 | AR60: 0 | AS60: 0 | AT60: 0 | AU60: 0 | AV60: 0 | AW60: 0 | AX60: 0 | AY60: 0
A61: DESPESAS DE ORIGINAÇÃO | AK61: -5004748.2 | AL61: -3848863.7 | AM61: -4693765.5 | AN61: -4007372 | AO61: -3324628.9 | AP61: -4620516.9 | AQ61: -4409897.3 | AR61: -4475939 | AS61: -4848789.1 | AT61: -5185752.6 | AU61: -4722997.6 | AV61: -4748321.1 | AW61: -4771630 | AX61: -4296891.1 | AY61: -4597062.6
A62: Despesa de Captação | AK62: -5004748.2 | AL62: -3848863.7 | AM62: -4693765.5 | AN62: -4007372 | AO62: -3324628.9 | AP62: -4620516.9 | AQ62: -4409897.3 | AR62: -4475939 | AS62: -4848789.1 | AT62: -5185752.6 | AU62: -4722997.6 | AV62: -4748321.1 | AW62: -4771630 | AX62: -4296891.1 | AY62: -4597062.6
A63: Inflação | AN63: 0 | AO63: 0 | AP63: 0 | AQ63: 0 | AR63: 0 | AS63: 0 | AT63: 0 | AU63: 0 | AV63: 0 | AW63: 0 | AX63: 0 | AY63: 0
A64: DI/Pré | AK64: -6291263.3 | AL64: -4686038.1 | AM64: -5712593.2 | AN64: -4887881.8 | AO64: -4008310.8 | AP64: -5697287.1 | AQ64: -5117668.8 | AR64: -5078309.7 | AS64: -5501427.3 | AT64: -5895987.6 | AU64: -5299733.4 | AV64: -5291278.2 | AW64: -5285602.5 | AX64: -4704113.6 | AY64: -5079850.4
A65: Outros | AK65: 564208.54 | AL65: 381029.16 | AM65: 571832.55 | AN65: 531727.93 | AO65: 403487.21 | AP65: 685924.94 | AQ65: 463465.43 | AR65: 442543.5 | AS65: 459367.83 | AT65: 500253.85 | AU65: 449216.63 | AV65: 446681.13 | AW65: 445031.52 | AX65: 395412.58 | AY65: 464056.32
A66: Swap | AK66: 722306.48 | AL66: 456145.16 | AM66: 446995.07 | AN66: 348781.91 | AO66: 280194.71 | AP66: 390845.25 | AQ66: 244306.13 | AR66: 159827.25 | AS66: 193270.37 | AT66: 209981.1 | AU66: 127519.2 | AV66: 96276.005 | AW66: 68940.965 | AX66: 11809.937 | AY66: 18731.459
A67: Impostos Diretos | AK67: -120040.28 | AL67: -162159.63 | AM67: -148120.86 | AN67: -135078 | AO67: -138230.37 | AP67: -169005.8 | AQ67: -168402.62 | AR67: -156646.84 | AS67: -170010.17 | AT67: -154750.92 | AU67: -174347.38 | AV67: -175986.98 | AW67: -182452.02 | AX67: -200340.97 | AY67: -183383
A68: MARGEM INTERMEDIAÇÃO | AK68: 2441534.2 | AL68: 3613673.5 | AM68: 3725985.7 | AN68: 3559264.4 | AO68: 3528656.9 | AP68: 2969870 | AQ68: 2973212.1 | AR68: 3205174.7 | AS68: 2608153.5 | AT68: 2574598.1 | AU68: 3059936.8 | AV68: 2818422.8 | AW68: 3080509.5 | AX68: 3322436.8 | AY68: 3333095
A69: Provisões | AK69: -552974.41 | AL69: -664269.35 | AM69: -408609.67 | AN69: -724707 | AO69: -555191.52 | AP69: -577819.12 | AQ69: -572342.1 | AR69: -579408.77 | AS69: -569041.42 | AT69: -640107.42 | AU69: -637930.47 | AV69: -627338.16 | AW69: -639328.32 | AX69: -628332.24 | AY69: -634500.91
A70: MG INTERMEDIAÇÃO LIQ | AK70: 1888559.8 | AL70: 2949404.1 | AM70: 3317376.1 | AN70: 2834557.4 | AO70: 2973465.4 | AP70: 2392050.8 | AQ70: 2400870 | AR70: 2625765.9 | AS70: 2039112.1 | AT70: 1934490.7 | AU70: 2422006.3 | AV70: 2191084.6 | AW70: 2441181.2 | AX70: 2694104.6 | AY70: 2698594.1
A71: Despesas Administrativas Diretas | AK71: -383570.09 | AL71: -383570.09 | AM71: -383570.09 | AN71: -423570.09 | AO71: -475521.66 | AP71: -486890.14 | AQ71: -486890.14 | AR71: -486890.14 | AS71: -497979.28 | AT71: -498703.08 | AU71: -498703.08 | AV71: -498703.08 | AW71: -498703.08 | AX71: -498703.08 | AY71: -502907.92 | AZ71: -1
A72: Comissão Correspondentes | AK72: 0 | AL72: 0 | AM72: 0 | AN72: 0 | AO72: 0 | AP72: 0 | AQ72: 0 | AR72: 0 | AS72: 0 | AT72: 0 | AU72: 0 | AV72: 0 | AW72: 0 | AX72: 0 | AY72: 0
A73: MG CONTRIBUIÇÃO DIRETA | AK73: 1371444 | AL73: 2441219.4 | AM73: 2816867.5 | AN73: 2303808.5 | AO73: 2400426.7 | AP73: 1817078.5 | AQ73: 1834329.2 | AR73: 2063263.9 | AS73: 1468027.1 | AT73: 1367294.8 | AU73: 1859502.3 | AV73: 1633237.9 | AW73: 1887643.2 | AX73: 2145161.2 | AY73: 2145656.6
A74: Desp. Administrativas Indiretas | AK74: -719698.61 | AL74: -718832.31 | AM74: -718832.31 | AN74: -728263.17 | AO74: -476449.99 | AP74: -575798.96 | AQ74: -487798.96 | AR74: -487798.96 | AS74: -500863.85 | AT74: -501808.3 | AU74: -501808.3 | AV74: -501808.3 | AW74: -501808.3 | AX74: -514568.3 | AY74: -501808.3 | AZ74: -1
A75: Amortização (estoque - projeto banco) | AK75: -133545.7 | AL75: -124614.67 | AM75: -116938.44 | AN75: -107178.79 | AO75: -97517.009 | AP75: -88082.166 | AQ75: -79650.623 | AR75: -75611.866 | AS75: -73105.71 | AT75: -68492.853 | AU75: -63800.946 | AV75: -59143.644 | AW75: -54834.896 | AX75: -50240.337 | AY75: -50029.604
A76: RESULTADO ANTES IMPOSTO | AK76: 651745.44 | AL76: 1722387.1 | AM76: 2098035.2 | AN76: 1575545.3 | AO76: 1923976.7 | AP76: 1241279.6 | AQ76: 1346530.3 | AR76: 1575464.9 | AS76: 967163.22 | AT76: 865486.48 | AU76: 1357694 | AV76: 1131429.6 | AW76: 1385834.9 | AX76: 1630592.9 | AY76: 1643848.3
A77: Impostos (IR/CSLL) | AK77: -161960.92 | AL77: -454291.81 | AM77: -505766.29 | AN77: -325141 | AO77: -377989.9 | AP77: -487969.93 | AQ77: -520162.59 | AR77: -454841.62 | AS77: -485727.28 | AT77: -383710.56 | AU77: -489045.22 | AV77: -489902.56 | AW77: -523423.36 | AX77: -618638.97 | AY77: -519254.41
A78: RESULTADO ANTES PARTICIPAÇÃO | AK78: 489784.52 | AL78: 1268095.3 | AM78: 1592268.9 | AN78: 1250404.3 | AO78: 1545986.8 | AP78: 753309.65 | AQ78: 826367.67 | AR78: 1120623.3 | AS78: 481435.94 | AT78: 481775.92 | AU78: 868648.76 | AV78: 641527.03 | AW78: 862411.57 | AX78: 1011953.9 | AY78: 1124593.9
A79: RESULTADO CONTÁBIL | AK79: 489784.52 | AL79: 1268095.3 | AM79: 1592268.9 | AN79: 1250404.3 | AO79: 1545986.8 | AP79: 753309.65 | AQ79: 826367.67 | AR79: 1120623.3 | AS79: 481435.94 | AT79: 481775.92 | AU79: 868648.76 | AV79: 641527.03 | AW79: 862411.57 | AX79: 1011953.9 | AY79: 1124593.9
AP80: 0 | AQ80: 0 | AR80: 0 | AS80: 0 | AT80: 0 | AU80: 0 | AV80: 0 | AW80: 0 | AX80: 0 | AY80: 0
A81: Imobiliário | AK81: 45961 | AL81: 45991 | AM81: 46022 | AN81: 46053 | AO81: 46081 | AP81: 46112 | AQ81: 46142 | AR81: 46173 | AS81: 46203 | AT81: 46234 | AU81: 46265 | AV81: 46295 | AW81: 46326 | AX81: 46356 | AY81: 46387
A82: RECEITAS | AK82: 21022834 | AL82: 22572876 | AM82: 24527586 | AN82: 24532548 | AO82: 23417973 | AP82: 29464374 | AQ82: 27827307 | AR82: 26639239 | AS82: 29052906 | AT82: 29113454 | AU82: 29754492 | AV82: 30381983 | AW82: 30970768 | AX82: 31571676 | AY82: 32307158
A83: Operações de Crédito | AK83: 17619345 | AL83: 19687163 | AM83: 20853867 | AN83: 21210590 | AO83: 20364605 | AP83: 26280606 | AQ83: 24677939 | AR83: 23584471 | AS83: 25869138 | AT83: 25706086 | AU83: 26433124 | AV83: 27129415 | AW83: 27683800 | AX83: 28258908 | AY83: 28959990
A84: Receita Juros | AK84: 14619852 | AL84: 15730290 | AM84: 18885599 | AN84: 18019560 | AO84: 16315715 | AP84: 20556772 | AQ84: 19154707 | AR84: 18901932 | AS84: 20741537 | AT84: 20594778 | AU84: 21164553 | AV84: 21710799 | AW84: 22256363 | AX84: 22820026 | AY84: 23382874
A85: Receita de Juros PMT | AK85: 17267126 | AL85: 16480465 | AM85: 19315753 | AN85: 18518811 | AO85: 16836460 | AP85: 21135581 | AQ85: 19776969 | AR85: 19567952 | AS85: 21447286 | AT85: 21350470 | AU85: 21966657 | AV85: 22554206 | AW85: 23151597 | AX85: 23755840 | AY85: 24372586
A86: Custo de originação diferido TJEO | AK86: -2647274.8 | AL86: -750175.41 | AM86: -430154.11 | AN86: -499251.62 | AO86: -520744.98 | AP86: -578809.46 | AQ86: -622261.99 | AR86: -666020.17 | AS86: -705748.92 | AT86: -755691.46 | AU86: -802103.38 | AV86: -843407.59 | AW86: -895233.57 | AX86: -935814.11 | AY86: -989712.2
A87: Receita CM - Crédito Imobiliário | AK87: 2609404.7 | AL87: 3558565 | AM87: 1574779.4 | AN87: 2790874.1 | AO87: 3641713.1 | AP87: 5309468.9 | AQ87: 5098166.9 | AR87: 4248792.5 | AS87: 4701365 | AT87: 4675672.4 | AU87: 4821979.5 | AV87: 4961576.9 | AW87: 4960526.3 | AX87: 4961217.9 | AY87: 5107987.8
A88: Multa + Mora - Crédito Imobiliário | AK88: 348636.07 | AL88: 356855.51 | AM88: 352035.47 | AN88: 358704.27 | AO88: 365724.09 | AP88: 372913.43 | AQ88: 383612.66 | AR88: 392294.41 | AS88: 384783.72 | AT88: 394182.82 | AU88: 405139.32 | AV88: 415586.86 | AW88: 425457.75 | AX88: 436211.53 | AY88: 427676
A89: Receita Juros - Cartão | AK89: 41452.468 | AL89: 41452.468 | AM89: 41452.468 | AN89: 41452.468 | AO89: 41452.468 | AP89: 41452.468 | AQ89: 41452.468 | AR89: 41452.468 | AS89: 41452.468 | AT89: 41452.468 | AU89: 41452.468 | AV89: 41452.468 | AW89: 41452.468 | AX89: 41452.468 | AY89: 41452.468
A90: Receita Serviços | AK90: 1970000 | AL90: 1970000 | AM90: 1970000 | AN90: 1642600 | AO90: 1591000 | AP90: 1754400 | AQ90: 1720000 | AR90: 1625400 | AS90: 1754400 | AT90: 1978000 | AU90: 1892000 | AV90: 1823200 | AW90: 1857600 | AX90: 1883400 | AY90: 1917800
A91: Receita Serviços
A92: Receita de outras taxas e serviços
A93: Receita Interchange | AK93: 16829.858 | AL93: 16829.858 | AM93: 16829.858 | AN93: 16829.858 | AO93: 16829.858 | AP93: 16829.858 | AQ93: 16829.858 | AR93: 16829.858 | AS93: 16829.858 | AT93: 16829.858 | AU93: 16829.858 | AV93: 16829.858 | AW93: 16829.858 | AX93: 16829.858 | AY93: 16829.858
A94: Receita Comissão CRI | AK94: 0 | AL94: 0 | AM94: 0 | AN94: 0 | AO94: 0 | AP94: 0 | AQ94: 0 | AR94: 0 | AS94: 0 | AT94: 0 | AU94: 0 | AV94: 0 | AW94: 0 | AX94: 0 | AY94: 0
A95: Receita Cobrança Ext. Cebraco | AK95: 220437.96 | AL95: 251558 | AM95: 294718 | AN95: 364301.13 | AO95: 282753.77 | AP95: 282753.77 | AQ95: 282753.77 | AR95: 282753.77 | AS95: 282753.77 | AT95: 282753.77 | AU95: 282753.77 | AV95: 282753.77 | AW95: 282753.77 | AX95: 282753.77 | AY95: 282753.77
A96: Barigui Veículos
A97: Honorários
A98: Securitizadora (Patrimônio Separado)
A99: Resultado de Seguros | AK99: 1080237.8 | AL99: 791082.68 | AM99: 885803.25 | AN99: 976784.38 | AO99: 900000 | AP99: 900000 | AQ99: 900000 | AR99: 900000 | AS99: 900000 | AT99: 900000 | AU99: 900000 | AV99: 900000 | AW99: 900000 | AX99: 900000 | AY99: 900000
A100: Resultado Brasil Cards | AK100: 115983.11 | AL100: -143757.6 | AM100: -38583.43 | AN100: 65704.18 | AO100: -163.435 | AP100: -163.435 | AQ100: -163.435 | AR100: -163.435 | AS100: -163.435 | AT100: -163.435 | AU100: -163.435 | AV100: -163.435 | AW100: -163.435 | AX100: -163.435 | AY100: -163.435
A101: Resultado Bari Capital | AK101: 0 | AL101: 0 | AM101: 544951.51 | AN101: 168678.17 | AO101: 52800 | AP101: 19800 | AQ101: 19800 | AR101: 19800 | AS101: 19800 | AT101: 19800 | AU101: 19800 | AV101: 19800 | AW101: 19800 | AX101: 19800 | AY101: 19800
...

Sheet Destaques
B2: Principais Variações: Orçado X Realizado
B4: 46054
B5: Resultado Contábil | C5: O Resultado Contábil encerrou Fevereiro 11,9% abaixo do orçado, uma variação negativa de R$ 580 mil.
B6: Despesa de PDD | C6: No mês de Fevereiro tivemos a manutenção da PDD em patamares elevados. A aba "Evolução acima de 10 k - Imob", apresenta os casos que mais impactaram as despesas de PDD.
B7: Despesa de Originação | C7: As despesas de Captação finalizaram 7,1% abaixo do orçado, ou seja, 1,3 milhões a menor. Do mesmo modo que a inflação inferior ao orçado, contribuiu para a redução da receita de correção monetária da carteira do imobiliário, o mesmo efeito foi observado nessa linha no que concerne ao desvio para baixo na linha de captações indexadas ao IPCA.
B8: Despesa de Comissão | C8: Nesta rúbrica, vale destacar a elevação nos gastos com Google e Facebook, que juntos somaram 821 mil em Fevereiro. Entram também nessa conta as Comissões diferidas, ou seja, as Comissões que ultrapassam os 6%, e, dessa forma, são alocadas diretamente como despesas.
B9: Despesas com IR e CSLL | C9: Na linha de IR e CSLL, fechamos também com 430 k acima do orçado, com uma alíquota de 33,3%, contra os 26% orçados.

Sheet Evolução acima de 10 k - Imob
A1: Contrato | B1: Nome | C1: Saldo Atual | D1: Saldo M-1 | E1: Atraso | F1: Atraso M-1 | G1: PDD | H1: PDD M-1 | I1: Evolução
A2: 504026-4 | B2: FERRAGEM THONY LTDA | C2: 4259515.1 | D2: 4256781.6 | E2: 192 | F2: 164 | G2: 1000986 | H2: 808788.51 | I2: 192197.53
A3: 502813-2 | B3: JOSE GERALDO DE BARROS COSCELLI | C3: 2819790.9 | D3: 2816683.8 | E3: 565 | F3: 537 | G3: 2185338 | H3: 2056179.2 | I3: 129158.8
A4: 503527-9 | B4: MARCELO THYSE DE AZEVEDO STEIN | C4: 2670121.6 | D4: 2667527.8 | E4: 534 | F4: 506 | G4: 1949188.8 | H4: 1827256.6 | I4: 121932.2
A5: 010583-A | B5: SOPETRA ROLAMENTOS E PECAS LTDA. | C5: 4875679 | D5: 4814667.8 | E5: 16 | F5: 0 | G5: 170648.77 | H5: 67405.35 | I5: 103243.42
A6: 011423-5 | B6: JORGE VACITE NETO | C6: 3154438.5 | D6: 3105494.8 | E6: 41 | F6: 13 | G6: 141949.73 | H6: 43476.927 | I6: 98472.805
A7: 010775-1 | B7: ROBERTO PROVASI DE CAROLICE BARBOSA | C7: 2129902.9 | D7: 2128317.6 | E7: 131 | F7: 103 | G7: 308835.93 | H7: 212831.76 | I7: 96004.165
A8: 500299-0 | B8: JORGE ASSAD | C8: 2097902.4 | D8: 2096203 | E8: 131 | F8: 103 | G8: 304195.85 | H8: 209620.3 | I8: 94575.556
A9: 507878-4 | B9: LILIANE MARIA COUTINHO BARBOSA | C9: 5468916.2 | E9: 0 | G9: 76564.827 | I9: 76564.827
A10: 506303-5 | B10: JACSON MOREIRA NIZA | C10: 2412774.2 | D10: 2372634.9 | E10: 39 | F10: 11 | G10: 108574.84 | H10: 33216.889 | I10: 75357.952
A11: 505674-8 | B11: MARCELO CHIBA PROENÇA | C11: 1432232.4 | D11: 1419105.3 | E11: 102 | F11: 74 | G11: 143223.24 | H11: 70955.266 | I11: 72267.972
A12: 013637-9 | B12: ELLY JOSE CORREIA | C12: 4297704.6 | E12: 0 | G12: 60167.864 | I12: 60167.864
A13: 504766-8 | B13: PEDRO PAULO MOLLO NETO | C13: 1313879 | D13: 1312807.1 | E13: 192 | F13: 164 | G13: 308761.57 | H13: 249433.35 | I13: 59328.216
A14: 507892-A | B14: FABIO FABRICIO MANIGLIA | C14: 3511979.4 | E14: 0 | G14: 49167.712 | I14: 49167.712
A15: 505037-5 | B15: AFRANIO AFFONSO FERREIRA NETO | C15: 2215527 | D15: 2183950.3 | E15: 23 | F15: 0 | G15: 77543.445 | H15: 30575.304 | I15: 46968.141
A16: 011303-4 | B16: MARCOS TULIO SILVEIRA FREITAS | C16: 1366225.4 | D16: 1345543.1 | E16: 39 | F16: 11 | G16: 61480.143 | H16: 18837.603 | I16: 42642.54
A17: 502993-7 | B17: JOSE MAURICIO ZULINI | C17: 937173.22 | D17: 936079.7 | E17: 284 | F17: 256 | G17: 346754.09 | H17: 304225.9 | I17: 42528.189
A18: 504325-5 | B18: ERICA MARCIANA SOUSA | C18: 1278338.8 | D18: 1256620.1 | E18: 39 | F18: 11 | G18: 57525.244 | H18: 17592.681 | I18: 39932.563
A19: 505728-0 | B19: FABIO KENJI SERRA FUGIWARA | C19: 815083.84 | D19: 814562.31 | E19: 139 | F19: 111 | G19: 118187.16 | H19: 81456.231 | I19: 36730.926
A20: 010159-1 | B20: MURILO ESTEVES DE CARVALHO | C20: 781738.62 | D20: 780916.4 | E20: 618 | F20: 590 | G20: 676203.91 | H20: 640351.45 | I20: 35852.458
A21: 011120-1 | B21: CLAUDIA BARBOSA DE BRITO | C21: 788050.41 | D21: 787343.79 | E21: 381 | F21: 353 | G21: 397965.46 | H21: 362178.14 | I21: 35787.314
A22: 507893-8 | B22: EUGENIO PACELLI ROMA FERNANDES | C22: 2380063.9 | E22: 0 | G22: 33320.895 | I22: 33320.895
A23: 011204-6 | B23: ZAQUEO ALVES DA LUZ | C23: 1489695.7 | D23: 1466942.1 | E23: 16 | F23: 0 | G23: 52139.351 | H23: 20537.189 | I23: 31602.162
A24: 013643-3 | B24: CICERO AUGUSTO GOULART | C24: 2249987.5 | E24: 0 | G24: 31499.824 | I24: 31499.824
A25: 012488-5 | B25: RICARDO ANTONIO PORTELLA BARROSO | C25: 319704.17 | D25: 323682.05 | E25: 10 | F25: 13 | G25: 31970.417 | H25: 4531.5487 | I25: 27438.868
A26: 506418-A | B26: ELIAS ROBERTO DE PAIVA | C26: 813549.79 | D26: 802253.53 | E26: 41 | F26: 13 | G26: 36609.741 | H26: 11231.549 | I26: 25378.191
A27: 011192-9 | B27: ALEX RAPHAEL MESCHINI | C27: 811053.45 | D27: 800408.53 | E27: 39 | F27: 11 | G27: 36497.405 | H27: 11205.719 | I27: 25291.686
A28: 503836-7 | B28: EDIR KESTRING PERIN | C28: 776964.21 | D28: 765068.06 | E28: 39 | F28: 11 | G28: 34963.389 | H28: 10710.953 | I28: 24252.437
A29: 013704-9 | B29: RAFAEL DA SILVA DA LUZ | C29: 1730264.2 | E29: 0 | G29: 24223.699 | I29: 24223.699
A30: 504924-5 | B30: DEBORA MONTEIRO FERNANDES | C30: 5166693.1 | D30: 3598029.6 | E30: 0 | F30: 0 | G30: 72333.703 | H30: 50372.415 | I30: 21961.289
A31: 012383-8 | B31: FLAVIA VINOCUR WAHBA | C31: 1027839.1 | D31: 1008076.5 | E31: 16 | F31: 0 | G31: 35974.37 | H31: 14113.071 | I31: 21861.298
A32: 504758-7 | B32: MAX DE OLIVEIRA YOSHIZAKI | C32: 663982.16 | D32: 653983.62 | E32: 41 | F32: 13 | G32: 29879.197 | H32: 9155.7707 | I32: 20723.427
A33: 012585-7 | B33: SIMONE PAES | C33: 625258.61 | D33: 614963.83 | E33: 41 | F33: 13 | G33: 28136.637 | H33: 8609.4936 | I33: 19527.144
A34: 013651-4 | B34: JOSEANE BITTENCOURT ALTHOFF | C34: 1335669.7 | E34: 0 | G34: 18699.376 | I34: 18699.376
A35: 503279-2 | B35: ROSELI DE LIMA RAMOS XAVIER | C35: 593337.82 | D35: 571820.56 | E35: 39 | F35: 11 | G35: 26700.202 | H35: 8005.4878 | I35: 18694.714
A36: 011426-A | B36: TIAGO OLIVEIRA DE SOUSA | C36: 352146.74 | D36: 332022.63 | E36: 102 | F36: 74 | G36: 35214.674 | H36: 16601.131 | I36: 18613.542
A37: 500885-9 | B37: ANDERSON SANTOS DA SILVA | C37: 876995.68 | D37: 864885.64 | E37: 16 | F37: 0 | G37: 30694.849 | H37: 12108.399 | I37: 18586.45
A38: 507857-1 | B38: THIAGO BUENO DE OLIVEIRA | C38: 1283165 | E38: 0 | G38: 17964.311 | I38: 17964.311
A39: 505417-6 | B39: FRANKLIN GRAY ELVAS PEREIRA | C39: 396136.72 | D39: 395899.92 | E39: 139 | F39: 111 | G39: 57439.824 | H39: 39589.992 | I39: 17849.832
A40: 009136-7 | B40: ROGER RODRIGUES DA SILVA | C40: 1243964.6 | E40: 0 | G40: 17415.505 | I40: 17415.505
A41: 500474-8 | B41: JOSE MIGUEL SAKER NETO | C41: 818132.94 | D41: 809609.49 | E41: 16 | F41: 0 | G41: 28634.653 | H41: 11334.533 | I41: 17300.12
A42: 506461-9 | B42: MAURO DE PAULA RAMOS | C42: 381542.77 | D42: 381070.55 | E42: 194 | F42: 166 | G42: 89662.551 | H42: 72403.404 | I42: 17259.146
A43: 010589-9 | B43: EDUARDO DAMAZO CAMARGO SILVA | C43: 549773.01 | D43: 541116.62 | E43: 41 | F43: 13 | G43: 24739.785 | H43: 7575.6327 | I43: 17164.153
A44: 504741-2 | B44: MAURICIO PERPETUO PEREIRA MANZANO | C44: 375359.24 | D44: 374911.02 | E44: 139 | F44: 111 | G44: 54427.09 | H44: 37491.102 | I44: 16935.988
A45: 502611-3 | B45: ALICE GEORGES ELIAS | C45: 538042 | D45: 531901.77 | E45: 39 | F45: 11 | G45: 24211.89 | H45: 7446.6248 | I45: 16765.265
A46: 013664-6 | B46: CELIO ROBERTO LOPES | C46: 1161669.4 | E46: 0 | G46: 16263.372 | I46: 16263.372
A47: 503979-7 | B47: RENATO TRABULSI ASHCAR | C47: 336113.96 | D47: 335807.46 | E47: 131 | F47: 103 | G47: 48736.524 | H47: 33580.746 | I47: 15155.778
A48: 507845-8 | B48: CARLOS ROBERTO DENANI | C48: 1051314 | E48: 0 | G48: 14718.397 | I48: 14718.397
A49: 505831-7 | B49: THIAGO JACINTO RIBEIRO | C49: 321568.41 | D49: 321403.15 | E49: 231 | F49: 203 | G49: 90039.155 | H49: 75529.74 | I49: 14509.415
A50: 013698-0 | B50: VICENTE ALVES CABRAL JUNIOR | C50: 1025462.9 | E50: 0 | G50: 14356.48 | I50: 14356.48
A51: 012891-0 | B51: FABIO PRADO BACHA | C51: 456389.2 | D51: 447710.57 | E51: 41 | F51: 13 | G51: 20537.514 | H51: 6267.948 | I51: 14269.566
A52: 011855-9 | B52: JORASA INCORPORACOES E EMPREEND. LTDA | C52: 321597.8 | D52: 323856.22 | E52: 192 | F52: 164 | G52: 75575.483 | H52: 61532.682 | I52: 14042.801
A53: 505032-4 | B53: JOSE CARLOS TORRES | C53: 298672.57 | D53: 298259.22 | E53: 200 | F53: 172 | G53: 70188.054 | H53: 56669.252 | I53: 13518.802
A54: 504937-7 | B54: LUIZ ALBERTO NACCARI | C54: 432355.22 | D54: 425189.91 | E54: 41 | F54: 13 | G54: 19455.985 | H54: 5952.6587 | I54: 13503.326
A55: 507043-0 | B55: WILDEM CLAY SOUSA VIEIRA | C55: 261319.6 | D55: 258553.2 | E55: 102 | F55: 74 | G55: 26131.96 | H55: 12927.66 | I55: 13204.3
A56: 011543-6 | B56: ADALBERTO FIORE | C56: 420631.2 | D56: 413775.07 | E56: 41 | F56: 13 | G56: 18928.404 | H56: 5792.851 | I56: 13135.553
A57: 507847-4 | B57: CESAR BENIGNO CLAUDINO | C57: 910585.68 | E57: 0 | G57: 12748.2 | I57: 12748.2
A58: 503783-2 | B58: JOAO JOSE CASCAES DIAS | C58: 1199765 | D58: 1181701.1 | E58: 54 | F58: 26 | G58: 53989.425 | H58: 41359.54 | I58: 12629.885
A59: 500378-4 | B59: ELANIA CAMILO DE SOUSA AMARAL | C59: 278826.27 | D59: 278724.59 | E59: 169 | F59: 141 | G59: 52976.991 | H59: 40415.066 | I59: 12561.926
A60: 013662-A | B60: MARIA C DA SILVEIRA MACHADO CORNETTI | C60: 886559.64 | E60: 0 | G60: 12411.835 | I60: 12411.835
A61: 012970-4 | B61: DANILO SILVEIRA RODRIGUES | C61: 395244.01 | D61: 387747.04 | E61: 41 | F61: 13 | G61: 17785.98 | H61: 5428.4586 | I61: 12357.522
A62: 012844-9 | B62: RUBIA MUNHOZ ARISA | C62: 269312.31 | D62: 269091.76 | E62: 163 | F62: 135 | G62: 51169.339 | H62: 39018.305 | I62: 12151.034
A63: 009884-1 | B63: PAULO MARCOS DE OLIVEIRA | C63: 365990.76 | D63: 361877.99 | E63: 39 | F63: 11 | G63: 16469.584 | H63: 5066.2919 | I63: 11403.292
A64: 504275-5 | B64: ADRIANE FERNANDES NOVO | C64: 360648.99 | D64: 355361.79 | E64: 39 | F64: 11 | G64: 16229.205 | H64: 4975.0651 | I64: 11254.139
A65: 011328-A | B65: ADRIANO REIS DE PAULA | C65: 358734.23 | D65: 352402.09 | E65: 39 | F65: 11 | G65: 16143.04 | H65: 4933.6293 | I65: 11209.411
A66: 013699-9 | B66: PAULA ROBERTA CECCON ORO | C66: 787487.43 | E66: 0 | G66: 11024.824 | I66: 11024.824
A67: 007790-9 | B67: ASBOR ADM DE BENS LTDA | C67: 780737.12 | E67: 0 | G67: 10930.32 | I67: 10930.32
A68: 013143-1 | B68: LILIAN ZO | C68: 346321 | D68: 340602.23 | E68: 41 | F68: 13 | G68: 15584.445 | H68: 4768.4312 | I68: 10816.014
A69: 012510-5 | B69: ANDRESSA STEFANELLO RIGHI | C69: 237845.01 | D69: 237651.71 | E69: 255 | F69: 227 | G69: 77299.628 | H69: 66542.479 | I69: 10757.149
A70: 012580-6 | B70: OSEAS BANDEIRA DA SILVA JUNIOR | C70: 220370.48 | D70: 230896.32 | E70: 23 | F70: 87 | G70: 22037.048 | H70: 11544.816 | I70: 10492.232
A71: 011703-A | B71: CLEONICE BARBOZA CASSEMIRO | C71: 117140.65 | D71: 115120.64 | E71: 0 | F71: 0 | G71: 11714.065 | H71: 1611.689 | I71: 10102.376
A72: 503172-9 | B72: DEBORA JACQUELINI PEREIRA | C72: 222885.64 | D72: 222682.69 | E72: 192 | F72: 164 | G72: 52378.125 | H72: 42309.711 | I72: 10068.414

Sheet Base comparativo - Desp Admin
B1: Até 2025 | C1: A partir de 2026
A2: Desp. Administrativas Realizadas | B2: ='P&L Mensal'!#REF! -> #REF! | C2: ='[2]Base Despesas'!$BA$3*-1 -> -5107034.8 | D2: =B2/C2-1 -> #REF!
A3: IR e CSLL das coligadas | B3: -520649.65 | D3: >> Entra como IR e CSLL | I3: =B3+B4 -> -788489.15 | J3: =I3*12 -> -9461869.8
A4: Mídia Paga | B4: =-161350.61-106488.89 -> -267839.5 | D4: >>> Entra na linha de Comissões
A5: Folha Apoio | B5: -865066.43 | D5: >>> Entra na linha de Comissões
A6: Total | B6: =B2+B3+B4+B5 -> #REF!
B8: 45658 | C8: 45689 | D8: 45717 | E8: 45748 | F8: 45778 | G8: 45809 | H8: 45839 | I8: 45870 | J8: 45901 | K8: 45931 | L8: 45962 | M8: 45992 | N8: 46023
A10: Contingências Trabalhistas/Civeis e Outros
A12: É Orçado, mas não está no Dash
A13: Recuperação de Despesas | B13: >>> Sazonal
A14: Receitas Financeiras das periféricas | B14: >>> Não é sazonal
A15: ISS - Service, Tec, Cebraco e Apoio | B15: >>> Não é sazonal
A16: PIS e COFINS - Service, Tec, Cebraco e Apoio | B16: >>> Não é sazonal

Sheet Organização P&L
A1: RECEITAS | B1: Empresas Financeiras | C1: Empresas Não Financerias | D1: Participação das Não Financeiras | E1: Fonte dos Dados
A2: Operações de Crédito | B2: Banco + Hipo | C2: - | E2: Relatório Gerencial da Contabilidade | G2: Na planilha do mês anterior há um "de-para", recomenda-se consultar a planilha a fim de verificar a coerência nas classificações
A3: Receita Serviços | B3: Banco + Hipo | C3: DI | D3: Receita (sem deduções) até 2023, após com dedução de 20%
A4: Receita Comissão CRI | B4: Banco + Hipo | C4: -
A5: Receita Cobrança Ext. Cebraco | B5: - | C5: Cebraco | D5: Receita de Terceiros (sem deduções) até 2023, após com dedução de 20%
A6: Resultado de Seguros | B6: - | C6: BarigSeg | D6: Lucro Líquido
A7: Resultado Brasil Cards | B7: - | C7: BR Cards | D7: Lucro Líquido
A8: DESPESAS DE ORIGINAÇÃO
A9: Despesa de Captação | B9: Banco + Hipo | C9: - | E9: Relatório Gerencial da Contabilidade
A10: Impostos Diretos | B10: Banco + Hipo | C10: DI | D10: Pis / Cofins | E10: Check Contábil
A11: MARGEM INTERMEDIAÇÃO
A12: Provisões | B12: Banco + Hipo | C12: -
A13: MG INTERMEDIAÇÃO LIQ
A14: Despesas Administrativas Diretas | B14: Banco + Hipo | C14: Service, Cebraco (Interno), Tec e DI. | D14: SG&A / Pis / Cofins / ISS / IR
B15: - | C15: Marumbi | D15: Lucro Líquido
A16: Comissão Correspondentes | B16: Banco + Hipo | C16: Apoio
A17: MG CONTRIBUIÇÃO DIRETA
A18: Desp. Administrativas Indiretas | B18: Banco + Hipo | C18: Service, Cebraco, Tec e DI | D18: SG&A / Receita Financeira
A19: RESULTADO ANTES IMPOSTO
A20: Impostos (IR/CSLL) | B20: Banco + Hipo | D20: IR/CSLL
A21: RESULTADO ANTES PARTICIPAÇÃO
A22: PART. CONTROLADAS (GESTAO + SEC) | C22: Gestão e Sec | D22: Lucro Líquido | G22: Na planilha do mês anterior há um "de-para", recomenda-se consultar a planilha a fim de verificar a coerência nas classificações
A23: RESULTADO CONTÁBIL

Sheet DRE Simplificado
C1: Slide 1
B2: Data ---> | C2: 45658
C3: =EOMONTH(C2,5) -> 45838
B4: Quantidade mês | C4: =MONTH(C3)-MONTH(C2)+1 -> 6
C6: Realizado
C7: 2024
B8: RECEITAS | C8: =C9+C13 -> 0
B9: Operações de Crédito | C9: =C10+C11+C12 -> 0
B10: Banco Digital | C10: =SUMIFS(Realizado!4:4,Realizado!2:2,"<="&C$3,Realizado!2:2,">="&C$2) -> 0
B11: Consignado | C11: =+SUMIFS(Realizado!40:40,Realizado!2:2,"<="&C$3,Realizado!2:2,">="&C$2) -> 0
B12: Imobiliário | C12: =+SUMIFS(Realizado!82:82,Realizado!2:2,"<="&C$3,Realizado!2:2,">="&C$2) -> 0
B13: Receita Serviços | C13: =+SUMIFS(Realizado!88:88,Realizado!2:2,"<="&C$3,Realizado!2:2,">="&C$2)+SUMIFS(Realizado!90:90,Realizado!2:2,"<="&C$3,Realizado!2:2,">="&C$2)+SUMIFS(Realizado!91:91,Realizado!2:2,"<="&C$3,Realizado!2:2,">="&C$2)+SUMIFS(Realizado!95:95,Realizado!2:2,"<="&C$3,Realizado!2:2,">="&C$2)+SUMIFS(Realizado!96:96,Realizado!2:2,"<="&C$3,Realizado!2:2,">="&C$2)+SUMIFS(Realizado!9:9,Realizado!2:2,"<="&C$3,Realizado!2:2,">="&C$2)+SUMIFS(Realizado!47:47,Realizado!2:2,"<="&C$3,Realizado!2:2,">="&C$2)+SUMIFS(Realizado!89:89,Realizado!2:2,"<="&C$3,Realizado!2:2,">="&C$2)+SUMIFS(Realizado!10:10,Realizado!2:2,"<="&C$3,Realizado!2:2,">="&C$2)+SUMIFS(Realizado!46:46,Realizado!2:2,"<="&C$3,Realizado!2:2,">="&C$2) -> 0
B14: Juros Pagos | C14: =+SUMIFS(Realizado!19:19,Realizado!2:2,"<="&C$3,Realizado!2:2,">="&C$2)+SUMIFS(Realizado!24:24,Realizado!2:2,"<="&C$3,Realizado!2:2,">="&C$2)+SUMIFS(Realizado!57:57,Realizado!2:2,"<="&C$3,Realizado!2:2,">="&C$2)+SUMIFS(Realizado!62:62,Realizado!2:2,"<="&C$3,Realizado!2:2,">="&C$2)+SUMIFS(Realizado!99:99,Realizado!2:2,"<="&C$3,Realizado!2:2,">="&C$2)+SUMIFS(Realizado!106:106,Realizado!2:2,"<="&C$3,Realizado!2:2,">="&C$2) -> 0
B15: Provisão | C15: =+SUMIFS(Realizado!26:26,Realizado!2:2,"<="&C$3,Realizado!2:2,">="&C$2)+SUMIFS(Realizado!64:64,Realizado!2:2,"<="&C$3,Realizado!2:2,">="&C$2)+SUMIFS(Realizado!108:108,Realizado!2:2,"<="&C$3,Realizado!2:2,">="&C$2) -> 0
B16: Despesas | C16: =+SUMIFS(Realizado!30:30,Realizado!2:2,"<="&C$3,Realizado!2:2,">="&C$2)+SUMIFS(Realizado!33:33,Realizado!2:2,"<="&C$3,Realizado!2:2,">="&C$2)+SUMIFS(Realizado!68:68,Realizado!2:2,"<="&C$3,Realizado!2:2,">="&C$2)+SUMIFS(Realizado!70:70,Realizado!2:2,"<="&C$3,Realizado!2:2,">="&C$2)+SUMIFS(Realizado!72:72,Realizado!2:2,"<="&C$3,Realizado!2:2,">="&C$2)+SUMIFS(Realizado!112:112,Realizado!2:2,"<="&C$3,Realizado!2:2,">="&C$2)+SUMIFS(Realizado!114:114,Realizado!2:2,"<="&C$3,Realizado!2:2,">="&C$2)+SUMIFS(Realizado!116:116,Realizado!2:2,"<="&C$3,Realizado!2:2,">="&C$2)+SUMIFS(Realizado!#REF!,Realizado!2:2,"<="&C$3,Realizado!2:2,">="&C$2) -> #REF!
B17: RESULTADO ANTES IMPOSTO | C17: =C8+C14+C15+C16 -> #REF!
B18: Imposto | C18: =+SUMIFS(Realizado!35:35,Realizado!2:2,"<="&C$3,Realizado!2:2,">="&C$2)+SUMIFS(Realizado!74:74,Realizado!2:2,"<="&C$3,Realizado!2:2,">="&C$2)+SUMIFS(Realizado!118:118,Realizado!2:2,"<="&C$3,Realizado!2:2,">="&C$2) -> 0
B19: Part. Coligadas | C19: =+SUMIFS(Realizado!37:37,Realizado!2:2,"<="&C$3,Realizado!2:2,">="&C$2)+SUMIFS(Realizado!76:76,Realizado!2:2,"<="&C$3,Realizado!2:2,">="&C$2)+SUMIFS(Realizado!120:120,Realizado!2:2,"<="&C$3,Realizado!2:2,">="&C$2)+SUMIFS(Realizado!#REF!,Realizado!2:2,"<="&C$3,Realizado!2:2,">="&C$2)+SUMIFS(Realizado!#REF!,Realizado!2:2,"<="&C$3,Realizado!2:2,">="&C$2)-SUMIFS(Realizado!#REF!,Realizado!2:2,"<="&C$3,Realizado!2:2,">="&C$2) -> #REF!
B20: RESULTADO CONTÁBIL | C20: =C17+C18+C19 -> #REF!
B21: RESULTADO ANTES IMPOSTO RECORRENTE * | C21: ='P&L Acumulado'!#REF! -> #REF!
B22: RESULTADO CONTÁBIL RECORRENTE | C22: ='P&L Acumulado'!#REF! -> #REF!
B23: *Ajuste intangível + Resultado Securitizadora.
B25: Margem Bruta | C25: ='P&L Acumulado'!L44 -> 0.093791367
B26: Margem Liquida | C26: ='P&L Acumulado'!L45 -> 0.082711588
B27: Rácio de Eficiência | C27: ='P&L Acumulado'!L46 -> -0.31666556
B28: Rácio de Eficiência Recorrente | C28: -0.46637549
B29: RPL - RES. CONTÁBIL | C29: ='P&L Acumulado'!L48 -> #REF!
B30: RPL - RES. CONTÁBIL RECORRENTE | C30: 0.28838421

Sheet Evolução PDD Imobiliário

Sheet Despesas
A1: 46054
A2: Fornecedor | B2: Realizado | C2: Orçado | D2: Diferença | E2: Observações
A3: Comissão | B3: 866571 | C3: 799342 | D3: 67229 | E3: Comissão de correspondentes paga para a Apoio
A4: Marketing | B4: 884755 | C4: 370602 | D4: 514153
A5: GOOGLE | B5: 544992 | C5: 132032 | D5: 412960 | E5: Pagamentos retroativos e valor alinhado com o Ugo e Willian dentro do percentual gasto de aquisição.
A6: FACEBOOK | B6: 276147 | C6: 198049 | D6: 78098 | E6: Pagamentos retroativos e valor alinhado com o Ugo e Willian dentro do percentual gasto de aquisição.
A7: TOPVIEW BRANDING | B7: 30000 | C7: 0 | D7: 30000 | E7: Posicionamneto da marca em canais digitais + aquisição de Leads
A8: Pessoal | B8: 3353423 | C8: 3125180 | D8: 228243 | E8: Em linhas gerais, veio bem próximo do orçado.
A9: PROVISÃO PARA PLR | B9: 248275 | C9: 0 | D9: 248275
A10: Outros | B10: 262766 | C10: 320870 | D10: -58104
A11: BANCO BRADESCO | B11: 36606 | C11: 47585 | D11: -10979 | E11: Cartão Corporativo
A12: BANCO BARI DE INVESTIMENTOS | B12: 17836 | C12: 25333 | D12: -7497 | E12: Cartão Corporativo
A13: TRIBUNAL DE JUSTIÇA DE SC | B13: 0 | C13: 24000 | D13: -24000 | E13: Não tivemos taxas ou custas judiciais
A14: CAIXA ECONOMICA FEDERAL | B14: 0 | C14: 16662 | D14: -16662 | E14: Não tivemos depósitos judiciais ou condenações
A15: Terceiros | B15: 789255 | C15: 985199 | D15: -195944
A16: GABARDO E TERRA ADVOGADOS ASSOCIADOS | B16: 23250 | C16: 53602 | D16: -30352 | E16: Pagamentos de honorários advocatícios abaixo do orçado
A17: OPERADOR NACIONAL DO SISTEMA DE REGISTRO | B17: 49637 | C17: 77504 | D17: -27867 | E17: Menos serviços prestados em relação à média
A18: OUTROS REPASSES A ÓRGÃOS PÚBLICOS | B18: 34826 | C18: 123188 | D18: -88362 | E18: Repasses abaixo do orçado
A19: KPMG AUDITORES INDEPENDENTES | B19: 0 | C19: 45636 | D19: -45636 | E19: Contrato com o fornecedor ainda não renovado, apenas valor provisionado com base no realizado do ano anterior
A20: Sistemas | B20: 1028966 | C20: 1007667 | D20: 21299
A21: RTM | B21: 48644 | C21: 26472 | D21: 22172 | E21: Custo de manutenção de servidores
A22: Realizado x Orçado (total) | B22: 7185736 | C22: 6608860 | D22: 576876
A24: Realizado x Orçado (sem comissão) | B24: 6319165 | C24: 5809518 | D24: 509647

Sheet Margem Financeira
B1: Dias juros apropriados (receita)
B2: =SUM(D2:K2) -> 240 | D2: 30 | E2: 27 | F2: 33 | G2: 29 | H2: 31 | I2: 29 | J2: 31 | K2: 30
B3: Realizado | D3: ='Orçado '!AB2 -> 45688 | E3: ='Orçado '!AC2 -> 45716 | F3: ='Orçado '!AD2 -> 45747 | G3: ='Orçado '!AE2 -> 45777 | H3: ='Orçado '!AF2 -> 45808 | I3: ='Orçado '!AG2 -> 45838 | J3: ='Orçado '!AH2 -> 45869 | K3: ='Orçado '!AI2 -> 45900
B4: Operações de Crédito | D4: =SUM(D5:D8) -> 0 | E4: =SUM(E5:E8) -> 0 | F4: =SUM(F5:F8) -> 0 | G4: =SUM(G5:G8) -> 0 | H4: =SUM(H5:H8) -> 0 | I4: =SUM(I5:I8) -> 0 | J4: =SUM(J5:J8) -> 0 | K4: =SUM(K5:K8) -> 0 | N4: =D4 -> 0 | O4: =E4+D4 -> 0 | P4: =O4+F4 -> 0 | Q4: =P4+G4 -> 0 | R4: =Q4+H4 -> 0 | S4: =R4+I4 -> 0
B5: Receita Juros | D5: =Realizado!AB41+Realizado!AB83 -> 0 | E5: =Realizado!AC41+Realizado!AC83 -> 0 | F5: =Realizado!AD41+Realizado!AD83 -> 0 | G5: =Realizado!AE41+Realizado!AE83 -> 0 | H5: =Realizado!AF41+Realizado!AF83 -> 0 | I5: =Realizado!AG41+Realizado!AG83 -> 0 | J5: =Realizado!AH41+Realizado!AH83 -> 0 | K5: =Realizado!AI41+Realizado!AI83 -> 0 | N5: =D5 -> 0 | O5: =E5+D5 -> 0 | P5: =O5+F5 -> 0 | Q5: =P5+G5 -> 0 | R5: =Q5+H5 -> 0 | S5: =R5+I5 -> 0
B6: Receita CM - Crédito Imobiliário | D6: =Realizado!AB43+Realizado!AB85 -> 0 | E6: =Realizado!AC43+Realizado!AC85 -> 0 | F6: =Realizado!AD43+Realizado!AD85 -> 0 | G6: =Realizado!AE43+Realizado!AE85 -> 0 | H6: =Realizado!AF43+Realizado!AF85 -> 0 | I6: =Realizado!AG43+Realizado!AG85 -> 0 | J6: =Realizado!AH43+Realizado!AH85 -> 0 | K6: =Realizado!AI43+Realizado!AI85 -> 0 | N6: =D6 -> 0 | O6: =E6+D6 -> 0 | P6: =O6+F6 -> 0 | Q6: =P6+G6 -> 0 | R6: =Q6+H6 -> 0 | S6: =R6+I6 -> 0
B7: Multa + Mora - Crédito Imobiliário | D7: =Realizado!AB44+Realizado!AB86 -> 0 | E7: =Realizado!AC44+Realizado!AC86 -> 0 | F7: =Realizado!AD44+Realizado!AD86 -> 0 | G7: =Realizado!AE44+Realizado!AE86 -> 0 | H7: =Realizado!AF44+Realizado!AF86 -> 0 | I7: =Realizado!AG44+Realizado!AG86 -> 0 | J7: =Realizado!AH44+Realizado!AH86 -> 0 | K7: =Realizado!AI44+Realizado!AI86 -> 0 | N7: =D7 -> 0 | O7: =E7+D7 -> 0 | P7: =O7+F7 -> 0 | Q7: =P7+G7 -> 0 | R7: =Q7+H7 -> 0 | S7: =R7+I7 -> 0
B8: Receita Juros - Cartão | D8: =Realizado!AB45+Realizado!AB87 -> 0 | E8: =Realizado!AC45+Realizado!AC87 -> 0 | F8: =Realizado!AD45+Realizado!AD87 -> 0 | G8: =Realizado!AE45+Realizado!AE87 -> 0 | H8: =Realizado!AF45+Realizado!AF87 -> 0 | I8: =Realizado!AG45+Realizado!AG87 -> 0 | J8: =Realizado!AH45+Realizado!AH87 -> 0 | K8: =Realizado!AI45+Realizado!AI87 -> 0 | N8: =D8 -> 0 | O8: =E8+D8 -> 0 | P8: =O8+F8 -> 0 | Q8: =P8+G8 -> 0 | R8: =Q8+H8 -> 0 | S8: =R8+I8 -> 0
B9: Despesa de Captação | D9: =SUM(D10:D14) -> #REF! | E9: =SUM(E10:E14) -> #REF! | F9: =SUM(F10:F14) -> #REF! | G9: =SUM(G10:G14) -> #REF! | H9: =SUM(H10:H14) -> #REF! | I9: =SUM(I10:I14) -> #REF! | J9: =SUM(J10:J14) -> #REF! | K9: =SUM(K10:K14) -> #REF! | N9: =D9 -> #REF! | O9: =E9+D9 -> #REF! | P9: =O9+F9 -> #REF! | Q9: =P9+G9 -> #REF! | R9: =Q9+H9 -> #REF! | S9: =R9+I9 -> #REF!
B10: Despesa de Juros | D10: =Realizado!AB142 -> 0 | E10: =Realizado!AC142 -> 0 | F10: =Realizado!AD142 -> 0 | G10: =Realizado!AE142 -> 0 | H10: =Realizado!AF142 -> 0 | I10: =Realizado!AG142 -> 0 | J10: =Realizado!AH142 -> 0 | K10: =Realizado!AI142 -> 0 | N10: =D10 -> 0 | O10: =E10+D10 -> 0 | P10: =O10+F10 -> 0 | Q10: =P10+G10 -> 0 | R10: =Q10+H10 -> 0 | S10: =R10+I10 -> 0
B11: Despesa de CM | D11: =Realizado!AB143 -> 0 | E11: =Realizado!AC143 -> 0 | F11: =Realizado!AD143 -> 0 | G11: =Realizado!AE143 -> 0 | H11: =Realizado!AF143 -> 0 | I11: =Realizado!AG143 -> 0 | J11: =Realizado!AH143 -> 0 | K11: =Realizado!AI143 -> 0 | N11: =D11 -> 0 | O11: =E11+D11 -> 0 | P11: =O11+F11 -> 0 | Q11: =P11+G11 -> 0 | R11: =Q11+H11 -> 0 | S11: =R11+I11 -> 0
B12: Despesa FGC + Outros | D12: =Realizado!#REF! -> #REF! | E12: =Realizado!#REF! -> #REF! | F12: =Realizado!#REF! -> #REF! | G12: =Realizado!#REF! -> #REF! | H12: =Realizado!#REF! -> #REF! | I12: =Realizado!#REF! -> #REF! | J12: =Realizado!#REF! -> #REF! | K12: =Realizado!#REF! -> #REF! | N12: =D12 -> #REF! | O12: =E12+D12 -> #REF! | P12: =O12+F12 -> #REF! | Q12: =P12+G12 -> #REF! | R12: =Q12+H12 -> #REF! | S12: =R12+I12 -> #REF!
B13: Receitas De Aplicações Financeiras | D13: =Realizado!#REF! -> #REF! | E13: =Realizado!#REF! -> #REF! | F13: =Realizado!#REF! -> #REF! | G13: =Realizado!#REF! -> #REF! | H13: =Realizado!#REF! -> #REF! | I13: =Realizado!#REF! -> #REF! | J13: =Realizado!#REF! -> #REF! | K13: =Realizado!#REF! -> #REF! | N13: =D13 -> #REF! | O13: =E13+D13 -> #REF! | P13: =O13+F13 -> #REF! | Q13: =P13+G13 -> #REF! | R13: =Q13+H13 -> #REF! | S13: =R13+I13 -> #REF!
B14: Swaps | D14: =Realizado!#REF! -> #REF! | E14: =Realizado!#REF! -> #REF! | F14: =Realizado!#REF! -> #REF! | G14: =Realizado!#REF! -> #REF! | H14: =Realizado!#REF! -> #REF! | I14: =Realizado!#REF! -> #REF! | J14: =Realizado!#REF! -> #REF! | K14: =Realizado!#REF! -> #REF! | N14: =D14 -> #REF! | O14: =E14+D14 -> #REF! | P14: =O14+F14 -> #REF! | Q14: =P14+G14 -> #REF! | R14: =Q14+H14 -> #REF! | S14: =R14+I14 -> #REF!
B15: Margem Intermediação | D15: =D4+D9 -> #REF! | E15: =E4+E9 -> #REF! | F15: =F4+F9 -> #REF! | G15: =G4+G9 -> #REF! | H15: =H4+H9 -> #REF! | I15: =I4+I9 -> #REF! | J15: =J4+J9 -> #REF! | K15: =K4+K9 -> #REF! | N15: =D15 -> #REF! | O15: =E15+D15 -> #REF! | P15: =O15+F15 -> #REF! | Q15: =P15+G15 -> #REF! | R15: =Q15+H15 -> #REF! | S15: =R15+I15 -> #REF!
B17: Carteira Captação Indexada | C17: =Realizado!AA141 -> 0 | D17: =Realizado!AB141 -> 0 | E17: =Realizado!AC141 -> 0 | F17: =Realizado!AD141 -> 0 | G17: =Realizado!AE141 -> 0 | H17: =Realizado!AF141 -> 0 | I17: =Realizado!AG141 -> 0 | J17: =Realizado!AH141 -> 0 | K17: =Realizado!AI141 -> 0
D18: =D11/AVERAGE(C17:D17) -> #DIV/0! | E18: =E11/AVERAGE(D17:E17) -> #DIV/0! | F18: =F11/AVERAGE(E17:F17) -> #DIV/0! | G18: =G11/AVERAGE(F17:G17) -> #DIV/0! | H18: =H11/AVERAGE(G17:H17) -> #DIV/0! | I18: =I11/AVERAGE(H17:I17) -> #DIV/0! | J18: =J11/AVERAGE(I17:J17) -> #DIV/0! | K18: =K11/AVERAGE(J17:K17) -> #DIV/0!
B20: Carteira Cred (TJEO) | D20: =Realizado!AB129 -> 0 | E20: =Realizado!AC129 -> 0 | F20: =Realizado!AD129 -> 0 | G20: =Realizado!AE129 -> 0 | H20: =Realizado!AF129 -> 0 | I20: =Realizado!AG129 -> 0 | J20: =Realizado!AH129 -> 0 | K20: =Realizado!AI129 -> 0
B21: Carteira Captação Indexada | C21: =Realizado!AA141 -> 0 | D21: =Realizado!AB141 -> 0 | E21: =Realizado!AC141 -> 0 | F21: =Realizado!AD141 -> 0 | G21: =Realizado!AE141 -> 0 | H21: =Realizado!AF141 -> 0 | I21: =Realizado!AG141 -> 0 | J21: =Realizado!AH141 -> 0 | K21: =Realizado!AI141 -> 0
D22: =D11/AVERAGE(C21:D21) -> #DIV/0! | E22: =E11/AVERAGE(D21:E21) -> #DIV/0! | F22: =F11/AVERAGE(E21:F21) -> #DIV/0! | G22: =G11/AVERAGE(F21:G21) -> #DIV/0! | H22: =H11/AVERAGE(G21:H21) -> #DIV/0! | I22: =I11/AVERAGE(H21:I21) -> #DIV/0! | J22: =J11/AVERAGE(I21:J21) -> #DIV/0! | K22: =K11/AVERAGE(J21:K21) -> #DIV/0!
B23: Dias juros apropriados (receita)
B24: =SUM(D24:K24) -> 243 | D24: 31 | E24: 28 | F24: 31 | G24: 30 | H24: 31 | I24: 30 | J24: 31 | K24: 31
B25: Orçado | D25: =D3 -> 45688 | E25: =E3 -> 45716 | F25: =F3 -> 45747 | G25: =G3 -> 45777 | H25: =H3 -> 45808 | I25: =I3 -> 45838 | J25: =J3 -> 45869 | K25: =K3 -> 45900
B26: Operações de Crédito | D26: =SUM(D27:D30) -> 0 | E26: =SUM(E27:E30) -> 0 | F26: =SUM(F27:F30) -> 0 | G26: =SUM(G27:G30) -> 0 | H26: =SUM(H27:H30) -> 0 | I26: =SUM(I27:I30) -> 0 | J26: =SUM(J27:J30) -> 0 | K26: =SUM(K27:K30) -> 0 | N26: =D26 -> 0 | O26: =E26+D26 -> 0 | P26: =O26+F26 -> 0 | Q26: =P26+G26 -> 0 | R26: =Q26+H26 -> 0 | S26: =R26+I26 -> 0
B27: Receita Juros | D27: ='Orçado '!AB153 -> 0 | E27: ='Orçado '!AC153 -> 0 | F27: ='Orçado '!AD153 -> 0 | G27: ='Orçado '!AE153 -> 0 | H27: ='Orçado '!AF153 -> 0 | I27: ='Orçado '!AG153 -> 0 | J27: ='Orçado '!AH153 -> 0 | K27: ='Orçado '!AI153 -> 0 | N27: =D27 -> 0 | O27: =E27+D27 -> 0 | P27: =O27+F27 -> 0 | Q27: =P27+G27 -> 0 | R27: =Q27+H27 -> 0 | S27: =R27+I27 -> 0
B28: Receita CM - Crédito Imobiliário | D28: ='Orçado '!AB154 -> 0 | E28: ='Orçado '!AC154 -> 0 | F28: ='Orçado '!AD154 -> 0 | G28: ='Orçado '!AE154 -> 0 | H28: ='Orçado '!AF154 -> 0 | I28: ='Orçado '!AG154 -> 0 | J28: ='Orçado '!AH154 -> 0 | K28: ='Orçado '!AI154 -> 0 | N28: =D28 -> 0 | O28: =E28+D28 -> 0 | P28: =O28+F28 -> 0 | Q28: =P28+G28 -> 0 | R28: =Q28+H28 -> 0 | S28: =R28+I28 -> 0
B29: Multa + Mora - Crédito Imobiliário | D29: ='Orçado '!AB155 -> 0 | E29: ='Orçado '!AC155 -> 0 | F29: ='Orçado '!AD155 -> 0 | G29: ='Orçado '!AE155 -> 0 | H29: ='Orçado '!AF155 -> 0 | I29: ='Orçado '!AG155 -> 0 | J29: ='Orçado '!AH155 -> 0 | K29: ='Orçado '!AI155 -> 0 | N29: =D29 -> 0 | O29: =E29+D29 -> 0 | P29: =O29+F29 -> 0 | Q29: =P29+G29 -> 0 | R29: =Q29+H29 -> 0 | S29: =R29+I29 -> 0
B30: Receita Juros - Cartão | D30: ='Orçado '!AB156 -> 0 | E30: ='Orçado '!AC156 -> 0 | F30: ='Orçado '!AD156 -> 0 | G30: ='Orçado '!AE156 -> 0 | H30: ='Orçado '!AF156 -> 0 | I30: ='Orçado '!AG156 -> 0 | J30: ='Orçado '!AH156 -> 0 | K30: ='Orçado '!AI156 -> 0 | N30: =D30 -> 0 | O30: =E30+D30 -> 0 | P30: =O30+F30 -> 0 | Q30: =P30+G30 -> 0 | R30: =Q30+H30 -> 0 | S30: =R30+I30 -> 0
B31: Despesa de Captação | D31: =SUM(D32:D36) -> 0 | E31: =SUM(E32:E36) -> 0 | F31: =SUM(F32:F36) -> 0 | G31: =SUM(G32:G36) -> 0 | H31: =SUM(H32:H36) -> 0 | I31: =SUM(I32:I36) -> 0 | J31: =SUM(J32:J36) -> 0 | K31: =SUM(K32:K36) -> 0 | N31: =D31 -> 0 | O31: =E31+D31 -> 0 | P31: =O31+F31 -> 0 | Q31: =P31+G31 -> 0 | R31: =Q31+H31 -> 0 | S31: =R31+I31 -> 0
B32: Despesa de Juros | D32: ='Orçado '!AB144 -> 0 | E32: ='Orçado '!AC144 -> 0 | F32: ='Orçado '!AD144 -> 0 | G32: ='Orçado '!AE144 -> 0 | H32: ='Orçado '!AF144 -> 0 | I32: ='Orçado '!AG144 -> 0 | J32: ='Orçado '!AH144 -> 0 | K32: ='Orçado '!AI144 -> 0 | N32: =D32 -> 0 | O32: =E32+D32 -> 0 | P32: =O32+F32 -> 0 | Q32: =P32+G32 -> 0 | R32: =Q32+H32 -> 0 | S32: =R32+I32 -> 0
B33: Despesa de CM | D33: ='Orçado '!AB145 -> 0 | E33: ='Orçado '!AC145 -> 0 | F33: ='Orçado '!AD145 -> 0 | G33: ='Orçado '!AE145 -> 0 | H33: ='Orçado '!AF145 -> 0 | I33: ='Orçado '!AG145 -> 0 | J33: ='Orçado '!AH145 -> 0 | K33: ='Orçado '!AI145 -> 0 | N33: =D33 -> 0 | O33: =E33+D33 -> 0 | P33: =O33+F33 -> 0 | Q33: =P33+G33 -> 0 | R33: =Q33+H33 -> 0 | S33: =R33+I33 -> 0
B34: Despesa FGC + Outros | D34: ='Orçado '!AB146 -> 0 | E34: ='Orçado '!AC146 -> 0 | F34: ='Orçado '!AD146 -> 0 | G34: ='Orçado '!AE146 -> 0 | H34: ='Orçado '!AF146 -> 0 | I34: ='Orçado '!AG146 -> 0 | J34: ='Orçado '!AH146 -> 0 | K34: ='Orçado '!AI146 -> 0 | N34: =D34 -> 0 | O34: =E34+D34 -> 0 | P34: =O34+F34 -> 0 | Q34: =P34+G34 -> 0 | R34: =Q34+H34 -> 0 | S34: =R34+I34 -> 0
B35: Receitas De Aplicações Financeiras | D35: ='Orçado '!AB147 -> 0 | E35: ='Orçado '!AC147 -> 0 | F35: ='Orçado '!AD147 -> 0 | G35: ='Orçado '!AE147 -> 0 | H35: ='Orçado '!AF147 -> 0 | I35: ='Orçado '!AG147 -> 0 | J35: ='Orçado '!AH147 -> 0 | K35: ='Orçado '!AI147 -> 0 | N35: =D35 -> 0 | O35: =E35+D35 -> 0 | P35: =O35+F35 -> 0 | Q35: =P35+G35 -> 0 | R35: =Q35+H35 -> 0 | S35: =R35+I35 -> 0
B36: Swaps | D36: ='Orçado '!AB173 -> 0 | E36: ='Orçado '!AC173 -> 0 | F36: ='Orçado '!AD173 -> 0 | G36: ='Orçado '!AE173 -> 0 | H36: ='Orçado '!AF173 -> 0 | I36: ='Orçado '!AG173 -> 0 | J36: ='Orçado '!AH173 -> 0 | K36: ='Orçado '!AI173 -> 0 | N36: =D36 -> 0 | O36: =E36+D36 -> 0 | P36: =O36+F36 -> 0 | Q36: =P36+G36 -> 0 | R36: =Q36+H36 -> 0 | S36: =R36+I36 -> 0
B37: Margem Intermediação | D37: =D26+D31 -> 0 | E37: =E26+E31 -> 0 | F37: =F26+F31 -> 0 | G37: =G26+G31 -> 0 | H37: =H26+H31 -> 0 | I37: =I26+I31 -> 0 | J37: =J26+J31 -> 0 | K37: =K26+K31 -> 0 | N37: =D37 -> 0 | O37: =E37+D37 -> 0 | P37: =O37+F37 -> 0 | Q37: =P37+G37 -> 0 | R37: =Q37+H37 -> 0 | S37: =R37+I37 -> 0
B39: Descasamento de margem | D39: =D15-D37 -> #REF! | E39: =E15-E37 -> #REF! | F39: =F15-F37 -> #REF! | G39: =G15-G37 -> #REF! | H39: =H15-H37 -> #REF! | I39: =I15-I37 -> #REF! | J39: =J15-J37 -> #REF! | K39: =K15-K37 -> #REF! | M39: CM Receita | N39: =N6-N28 -> 0 | O39: =O6-O28 -> 0 | P39: =P6-P28 -> 0 | Q39: =Q6-Q28 -> 0 | R39: =R6-R28 -> 0 | S39: =S6-S28 -> 0 | T39: Receita orçada a maior
M40: CM Despesa | N40: =N11-N33 -> 0 | O40: =O11-O33 -> 0 | P40: =P11-P33 -> 0 | Q40: =Q11-Q33 -> 0 | R40: =R11-R33 -> 0 | S40: =S11-S33 -> 0 | T40: Despesa orçada a maior
B41: Carteira Captação Indexada | C41: ='Orçado '!AA143 -> 0 | D41: ='Orçado '!AB143 -> 0 | E41: ='Orçado '!AC143 -> 0 | F41: ='Orçado '!AD143 -> 0 | G41: ='Orçado '!AE143 -> 0 | H41: ='Orçado '!AF143 -> 0 | I41: ='Orçado '!AG143 -> 0 | J41: ='Orçado '!AH143 -> 0 | K41: ='Orçado '!AI143 -> 0 | M41: Net | N41: =N39+N40 -> 0 | O41: =O39+O40 -> 0 | P41: =P39+P40 -> 0 | Q41: =Q39+Q40 -> 0 | R41: =R39+R40 -> 0 | S41: =S39+S40 -> 0
D42: =D33/AVERAGE(C41:D41) -> #DIV/0! | E42: =E33/AVERAGE(D41:E41) -> #DIV/0! | F42: =F33/AVERAGE(E41:F41) -> #DIV/0! | G42: =G33/AVERAGE(F41:G41) -> #DIV/0! | H42: =H33/AVERAGE(G41:H41) -> #DIV/0! | I42: =I33/AVERAGE(H41:I41) -> #DIV/0! | J42: =J33/AVERAGE(I41:J41) -> #DIV/0! | K42: =K33/AVERAGE(J41:K41) -> #DIV/0!
B43: Carteira Cred (TJEO) | D43: ='Orçado '!AB129 -> 0 | E43: ='Orçado '!AC129 -> 0 | F43: ='Orçado '!AD129 -> 0 | G43: ='Orçado '!AE129 -> 0 | H43: ='Orçado '!AF129 -> 0 | I43: ='Orçado '!AG129 -> 0 | J43: ='Orçado '!AH129 -> 0 | K43: ='Orçado '!AI129 -> 0
B44: Carteira Captação Indexada | C44: ='Orçado '!AA143 -> 0 | D44: ='Orçado '!AB143 -> 0 | E44: ='Orçado '!AC143 -> 0 | F44: ='Orçado '!AD143 -> 0 | G44: ='Orçado '!AE143 -> 0 | H44: ='Orçado '!AF143 -> 0 | I44: ='Orçado '!AG143 -> 0 | J44: ='Orçado '!AH143 -> 0 | K44: ='Orçado '!AI143 -> 0
D45: =D33/AVERAGE(C44:D44) -> #DIV/0! | E45: =E33/AVERAGE(D44:E44) -> #DIV/0! | F45: =F33/AVERAGE(E44:F44) -> #DIV/0! | G45: =G33/AVERAGE(F44:G44) -> #DIV/0! | H45: =H33/AVERAGE(G44:H44) -> #DIV/0! | I45: =I33/AVERAGE(H44:I44) -> #DIV/0! | J45: =J33/AVERAGE(I44:J44) -> #DIV/0! | K45: =K33/AVERAGE(J44:K44) -> #DIV/0!
B48: CM média
B49: Realizado | D49: =D18 -> #DIV/0! | E49: =E18 -> #DIV/0! | F49: =F18 -> #DIV/0! | G49: =G18 -> #DIV/0! | H49: =H18 -> #DIV/0! | I49: =I18 -> #DIV/0! | J49: =J18 -> #DIV/0! | K49: =K18 -> #DIV/0!
B50: Orçado | D50: =D42 -> #DIV/0! | E50: =E42 -> #DIV/0! | F50: =F42 -> #DIV/0! | G50: =G42 -> #DIV/0! | H50: =H42 -> #DIV/0! | I50: =I42 -> #DIV/0! | J50: =J42 -> #DIV/0! | K50: =K42 -> #DIV/0!
B51: Dif. | D51: =D49-D50 -> #DIV/0! | E51: =E49-E50 -> #DIV/0! | F51: =F49-F50 -> #DIV/0! | G51: =G49-G50 -> #DIV/0! | H51: =H49-H50 -> #DIV/0! | I51: =I49-I50 -> #DIV/0! | J51: =J49-J50 -> #DIV/0! | K51: =K49-K50 -> #DIV/0!
D54: 22 | E54: 20 | F54: 19 | G54: 20 | H54: 21 | I54: 20 | J54: 20 | K54: 21
B55: Juros diários | D55: =D32/D54 -> 0 | E55: =E32/E54 -> 0 | F55: =F32/F54 -> 0 | G55: =G32/G54 -> 0 | H55: =H32/H54 -> 0 | I55: =I32/I54 -> 0 | J55: =J32/J54 -> 0 | K55: =K32/K54 -> 0
B65: Fatores que podem afetar:
B66: -Desconto de taxa bonificada está impactando a CM, mas ainda não temos relatórios gerenciais validar o montante do desconto.
B67: -Correção monetária a maior no orçado, que no realizado

Sheet Lista de data para filtro
A1: Data
A2: =LARGE(Realizado!2:2,1) -> 46387
A3: =EOMONTH(A2,-1) -> 46356
A4: =EOMONTH(A3,-1) -> 46326
A5: =EOMONTH(A4,-1) -> 46295
A6: =EOMONTH(A5,-1) -> 46265
A7: =EOMONTH(A6,-1) -> 46234
A8: =EOMONTH(A7,-1) -> 46203
A9: =EOMONTH(A8,-1) -> 46173
A10: =EOMONTH(A9,-1) -> 46142
A11: =EOMONTH(A10,-1) -> 46112
A12: =EOMONTH(A11,-1) -> 46081
A13: =EOMONTH(A12,-1) -> 46053
A14: =EOMONTH(A13,-1) -> 46022
... A25: =EOMONTH(A24,-1) -> 45688

Sheet BASE_DASH
A1: Visao | B1: Data_Inicio | C1: Data_Fim | D1: Data_Base | E1: Periodo | F1: Linha_PnL | G1: Produto | H1: Metrica | I1: Valor | J1: Aba_Origem | K1: Celula_Origem | L1: Linha_Origem | N1: Observação
A2: Mensal | B2: =DATE(YEAR('P&L Mensal'!$F$1),MONTH('P&L Mensal'!$F$1),1) -> 46082 | C2: ='P&L Mensal'!$F$1 -> 46112 | D2: ='P&L Mensal'!$F$1 -> 46112 | E2: =TEXT('P&L Mensal'!$F$1,"mmm/yyyy") -> mar/yyyy | F2: RECEITAS | G2: Consignado | H2: Realizado | I2: ='P&L Mensal'!C5 -> 7877352.9 | J2: P&L Mensal | K2: C5 | L2: 5 | N2: A BASE_DASH usa fórmulas que referenciam P&L Mensal e P&L Acumulado. Atualize as abas originais no Excel, salve o arquivo e importe esta aba no Power BI/web.
A3: Mensal | B3: =DATE(YEAR('P&L Mensal'!$F$1),MONTH('P&L Mensal'!$F$1),1) -> 46082 | C3: ='P&L Mensal'!$F$1 -> 46112 | D3: ='P&L Mensal'!$F$1 -> 46112 | E3: =TEXT('P&L Mensal'!$F$1,"mmm/yyyy") -> mar/yyyy | F3: RECEITAS | G3: Consignado | H3: Orçado | I3: ='P&L Mensal'!D5 -> 7759392.7 | J3: P&L Mensal | K3: D5 | L3: 5
A4: Mensal | B4: =DATE(YEAR('P&L Mensal'!$F$1),MONTH('P&L Mensal'!$F$1),1) -> 46082 | C4: ='P&L Mensal'!$F$1 -> 46112 | D4: ='P&L Mensal'!$F$1 -> 46112 | E4: =TEXT('P&L Mensal'!$F$1,"mmm/yyyy") -> mar/yyyy | F4: RECEITAS | G4: Consignado | H4: Variação % | I4: ='P&L Mensal'!E5 -> 0.015202255 | J4: P&L Mensal | K4: E5 | L4: 5
A5: Mensal | B5: =DATE(YEAR('P&L Mensal'!$F$1),MONTH('P&L Mensal'!$F$1),1) -> 46082 | C5: ='P&L Mensal'!$F$1 -> 46112 | D5: ='P&L Mensal'!$F$1 -> 46112 | E5: =TEXT('P&L Mensal'!$F$1,"mmm/yyyy") -> mar/yyyy | F5: RECEITAS | G5: Imobiliário | H5: Realizado | I5: ='P&L Mensal'!F5 -> 33774613 | J5: P&L Mensal | K5: F5 | L5: 5
A6: Mensal | B6: =DATE(YEAR('P&L Mensal'!$F$1),MONTH('P&L Mensal'!$F$1),1) -> 46082 | C6: ='P&L Mensal'!$F$1 -> 46112 | D6: ='P&L Mensal'!$F$1 -> 46112 | E6: =TEXT('P&L Mensal'!$F$1,"mmm/yyyy") -> mar/yyyy | F6: RECEITAS | G6: Imobiliário | H6: Orçado | I6: ='P&L Mensal'!G5 -> 29464374 | J6: P&L Mensal | K6: G5 | L6: 5
A7: Mensal | B7: =DATE(YEAR('P&L Mensal'!$F$1),MONTH('P&L Mensal'!$F$1),1) -> 46082 | C7: ='P&L Mensal'!$F$1 -> 46112 | D7: ='P&L Mensal'!$F$1 -> 46112 | E7: =TEXT('P&L Mensal'!$F$1,"mmm/yyyy") -> mar/yyyy | F7: RECEITAS | G7: Imobiliário | H7: Variação % | I7: ='P&L Mensal'!H5 -> 0.14628643 | J7: P&L Mensal | K7: H5 | L7: 5
A8: Mensal | B8: =DATE(YEAR('P&L Mensal'!$F$1),MONTH('P&L Mensal'!$F$1),1) -> 46082 | C8: ='P&L Mensal'!$F$1 -> 46112 | D8: ='P&L Mensal'!$F$1 -> 46112 | E8: =TEXT('P&L Mensal'!$F$1,"mmm/yyyy") -> mar/yyyy | F8: RECEITAS | G8: Total | H8: Realizado | I8: ='P&L Mensal'!I5 -> 41651965 | J8: P&L Mensal | K8: I5 | L8: 5
A9: Mensal | B9: =DATE(YEAR('P&L Mensal'!$F$1),MONTH('P&L Mensal'!$F$1),1) -> 46082 | C9: ='P&L Mensal'!$F$1 -> 46112 | D9: ='P&L Mensal'!$F$1 -> 46112 | E9: =TEXT('P&L Mensal'!$F$1,"mmm/yyyy") -> mar/yyyy | F9: RECEITAS | G9: Total | H9: Orçado | I9: ='P&L Mensal'!J5 -> 37223767 | J9: P&L Mensal | K9: J5 | L9: 5
A10: Mensal | B10: =DATE(YEAR('P&L Mensal'!$F$1),MONTH('P&L Mensal'!$F$1),1) -> 46082 | C10: ='P&L Mensal'!$F$1 -> 46112 | D10: ='P&L Mensal'!$F$1 -> 46112 | E10: =TEXT('P&L Mensal'!$F$1,"mmm/yyyy") -> mar/yyyy | F10: RECEITAS | G10: Total | H10: Variação % | I10: ='P&L Mensal'!K5 -> 0.11896159 | J10: P&L Mensal | K10: K5 | L10: 5
A11: Mensal | B11: =DATE(YEAR('P&L Mensal'!$F$1),MONTH('P&L Mensal'!$F$1),1) -> 46082 | C11: ='P&L Mensal'!$F$1 -> 46112 | D11: ='P&L Mensal'!$F$1 -> 46112 | E11: =TEXT('P&L Mensal'!$F$1,"mmm/yyyy") -> mar/yyyy | F11: RECEITAS | G11: Total | H11: Variação R$ | I11: ='P&L Mensal'!L5 -> 4428198.4 | J11: P&L Mensal | K11: L5 | L11: 5
A12: Mensal | B12: =DATE(YEAR('P&L Mensal'!$F$1),MONTH('P&L Mensal'!$F$1),1) -> 46082 | C12: ='P&L Mensal'!$F$1 -> 46112 | D12: ='P&L Mensal'!$F$1 -> 46112 | E12: =TEXT('P&L Mensal'!$F$1,"mmm/yyyy") -> mar/yyyy | F12: Operações de Crédito | G12: Consignado | H12: Realizado | I12: ='P&L Mensal'!C6 -> 7868473.4 | J12: P&L Mensal | K12: C6 | L12: 6
A13: Mensal | B13: =DATE(YEAR('P&L Mensal'!$F$1),MONTH('P&L Mensal'!$F$1),1) -> 46082 | C13: ='P&L Mensal'!$F$1 -> 46112 | D13: ='P&L Mensal'!$F$1 -> 46112 | E13: =TEXT('P&L Mensal'!$F$1,"mmm/yyyy") -> mar/yyyy | F13: Operações de Crédito | G13: Consignado | H13: Orçado | I13: ='P&L Mensal'!D6 -> 7746926.1 | J13: P&L Mensal | K13: D6 | L13: 6
A14: Mensal | B14: =DATE(YEAR('P&L Mensal'!$F$1),MONTH('P&L Mensal'!$F$1),1) -> 46082 | C14: ='P&L Mensal'!$F$1 -> 46112 | D14: ='P&L Mensal'!$F$1 -> 46112 | E14: =TEXT('P&L Mensal'!$F$1,"mmm/yyyy") -> mar/yyyy | F14: Operações de Crédito | G14: Consignado | H14: Variação % | I14: ='P&L Mensal'!E6 -> 0.015689749 | J14: P&L Mensal | K14: E6 | L14: 6
A15: Mensal | B15: =DATE(YEAR('P&L Mensal'!$F$1),MONTH('P&L Mensal'!$F$1),1) -> 46082 | C15: ='P&L Mensal'!$F$1 -> 46112 | D15: ='P&L Mensal'!$F$1 -> 46112 | E15: =TEXT('P&L Mensal'!$F$1,"mmm/yyyy") -> mar/yyyy | F15: Operações de Crédito | G15: Imobiliário | H15: Realizado | I15: ='P&L Mensal'!F6 -> 29656161 | J15: P&L Mensal | K15: F6 | L15: 6
A16: Mensal | B16: =DATE(YEAR('P&L Mensal'!$F$1),MONTH('P&L Mensal'!$F$1),1) -> 46082 | C16: ='P&L Mensal'!$F$1 -> 46112 | D16: ='P&L Mensal'!$F$1 -> 46112 | E16: =TEXT('P&L Mensal'!$F$1,"mmm/yyyy") -> mar/yyyy | F16: Operações de Crédito | G16: Imobiliário | H16: Orçado | I16: ='P&L Mensal'!G6 -> 26280606 | J16: P&L Mensal | K16: G6 | L16: 6
A17: Mensal | B17: =DATE(YEAR('P&L Mensal'!$F$1),MONTH('P&L Mensal'!$F$1),1) -> 46082 | C17: ='P&L Mensal'!$F$1 -> 46112 | D17: ='P&L Mensal'!$F$1 -> 46112 | E17: =TEXT('P&L Mensal'!$F$1,"mmm/yyyy") -> mar/yyyy | F17: Operações de Crédito | G17: Imobiliário | H17: Variação % | I17: ='P&L Mensal'!H6 -> 0.12844279 | J17: P&L Mensal | K17: H6 | L17: 6
A18: Mensal | B18: =DATE(YEAR('P&L Mensal'!$F$1),MONTH('P&L Mensal'!$F$1),1) -> 46082 | C18: ='P&L Mensal'!$F$1 -> 46112 | D18: ='P&L Mensal'!$F$1 -> 46112 | E18: =TEXT('P&L Mensal'!$F$1,"mmm/yyyy") -> mar/yyyy | F18: Operações de Crédito | G18: Total | H18: Realizado | I18: ='P&L Mensal'!I6 -> 37524634 | J18: P&L Mensal | K18: I6 | L18: 6
A19: Mensal | B19: =DATE(YEAR('P&L Mensal'!$F$1),MONTH('P&L Mensal'!$F$1),1) -> 46082 | C19: ='P&L Mensal'!$F$1 -> 46112 | D19: ='P&L Mensal'!$F$1 -> 46112 | E19: =TEXT('P&L Mensal'!$F$1,"mmm/yyyy") -> mar/yyyy | F19: Operações de Crédito | G19: Total | H19: Orçado | I19: ='P&L Mensal'!J6 -> 34027532 | J19: P&L Mensal | K19: J6 | L19: 6
A20: Mensal | B20: =DATE(YEAR('P&L Mensal'!$F$1),MONTH('P&L Mensal'!$F$1),1) -> 46082 | C20: ='P&L Mensal'!$F$1 -> 46112 | D20: ='P&L Mensal'!$F$1 -> 46112 | E20: =TEXT('P&L Mensal'!$F$1,"mmm/yyyy") -> mar/yyyy | F20: Operações de Crédito | G20: Total | H20: Variação % | I20: ='P&L Mensal'!K6 -> 0.10277271 | J20: P&L Mensal | K20: K6 | L20: 6
A21: Mensal | B21: =DATE(YEAR('P&L Mensal'!$F$1),MONTH('P&L Mensal'!$F$1),1) -> 46082 | C21: ='P&L Mensal'!$F$1 -> 46112 | D21: ='P&L Mensal'!$F$1 -> 46112 | E21: =TEXT('P&L Mensal'!$F$1,"mmm/yyyy") -> mar/yyyy | F21: Operações de Crédito | G21: Total | H21: Variação R$ | I21: ='P&L Mensal'!L6 -> 3497101.8 | J21: P&L Mensal | K21: L6 | L21: 6
A22: Mensal | B22: =DATE(YEAR('P&L Mensal'!$F$1),MONTH('P&L Mensal'!$F$1),1) -> 46082 | C22: ='P&L Mensal'!$F$1 -> 46112 | D22: ='P&L Mensal'!$F$1 -> 46112 | E22: =TEXT('P&L Mensal'!$F$1,"mmm/yyyy") -> mar/yyyy | F22: Receita Juros | G22: Consignado | H22: Realizado | I22: ='P&L Mensal'!C7 -> 6041460.8 | J22: P&L Mensal | K22: C7 | L22: 7
A23: Mensal | B23: =DATE(YEAR('P&L Mensal'!$F$1),MONTH('P&L Mensal'!$F$1),1) -> 46082 | C23: ='P&L Mensal'!$F$1 -> 46112 | D23: ='P&L Mensal'!$F$1 -> 46112 | E23: =TEXT('P&L Mensal'!$F$1,"mmm/yyyy") -> mar/yyyy | F23: Receita Juros | G23: Consignado | H23: Orçado | I23: ='P&L Mensal'!D7 -> 6046154.6 | J23: P&L Mensal | K23: D7 | L23: 7
A24: Mensal | B24: =DATE(YEAR('P&L Mensal'!$F$1),MONTH('P&L Mensal'!$F$1),1) -> 46082 | C24: ='P&L Mensal'!$F$1 -> 46112 | D24: ='P&L Mensal'!$F$1 -> 46112 | E24: =TEXT('P&L Mensal'!$F$1,"mmm/yyyy") -> mar/yyyy | F24: Receita Juros | G24: Consignado | H24: Variação % | I24: ='P&L Mensal'!E7 -> -0.00077634449 | J24: P&L Mensal | K24: E7 | L24: 7
A25: Mensal | B25: =DATE(YEAR('P&L Mensal'!$F$1),MONTH('P&L Mensal'!$F$1),1) -> 46082 | C25: ='P&L Mensal'!$F$1 -> 46112 | D25: ='P&L Mensal'!$F$1 -> 46112 | E25: =TEXT('P&L Mensal'!$F$1,"mmm/yyyy") -> mar/yyyy | F25: Receita Juros | G25: Imobiliário | H25: Realizado | I25: ='P&L Mensal'!F7 -> 21983325 | J25: P&L Mensal | K25: F7 | L25: 7
A26: Mensal | B26: =DATE(YEAR('P&L Mensal'!$F$1),MONTH('P&L Mensal'!$F$1),1) -> 46082 | C26: ='P&L Mensal'!$F$1 -> 46112 | D26: ='P&L Mensal'!$F$1 -> 46112 | E26: =TEXT('P&L Mensal'!$F$1,"mmm/yyyy") -> mar/yyyy | F26: Receita Juros | G26: Imobiliário | H26: Orçado | I26: ='P&L Mensal'!G7 -> 20556772 | J26: P&L Mensal | K26: G7 | L26: 7
A27: Mensal | B27: =DATE(YEAR('P&L Mensal'!$F$1),MONTH('P&L Mensal'!$F$1),1) -> 46082 | C27: ='P&L Mensal'!$F$1 -> 46112 | D27: ='P&L Mensal'!$F$1 -> 46112 | E27: =TEXT('P&L Mensal'!$F$1,"mmm/yyyy") -> mar/yyyy | F27: Receita Juros | G27: Imobiliário | H27: Variação % | I27: ='P&L Mensal'!H7 -> 0.0693958 | J27: P&L Mensal | K27: H7 | L27: 7
A28: Mensal | B28: =DATE(YEAR('P&L Mensal'!$F$1),MONTH('P&L Mensal'!$F$1),1) -> 46082 | C28: ='P&L Mensal'!$F$1 -> 46112 | D28: ='P&L Mensal'!$F$1 -> 46112 | E28: =TEXT('P&L Mensal'!$F$1,"mmm/yyyy") -> mar/yyyy | F28: Receita Juros | G28: Total | H28: Realizado | I28: ='P&L Mensal'!I7 -> 28024786 | J28: P&L Mensal | K28: I7 | L28: 7
A29: Mensal | B29: =DATE(YEAR('P&L Mensal'!$F$1),MONTH('P&L Mensal'!$F$1),1) -> 46082 | C29: ='P&L Mensal'!$F$1 -> 46112 | D29: ='P&L Mensal'!$F$1 -> 46112 | E29: =TEXT('P&L Mensal'!$F$1,"mmm/yyyy") -> mar/yyyy | F29: Receita Juros | G29: Total | H29: Orçado | I29: ='P&L Mensal'!J7 -> 26602926 | J29: P&L Mensal | K29: J7 | L29: 7
A30: Mensal | B30: =DATE(YEAR('P&L Mensal'!$F$1),MONTH('P&L Mensal'!$F$1),1) -> 46082 | C30: ='P&L Mensal'!$F$1 -> 46112 | D30: ='P&L Mensal'!$F$1 -> 46112 | E30: =TEXT('P&L Mensal'!$F$1,"mmm/yyyy") -> mar/yyyy | F30: Receita Juros | G30: Total | H30: Variação % | I30: ='P&L Mensal'!K7 -> 0.053447493 | J30: P&L Mensal | K30: K7 | L30: 7
A31: Mensal | B31: =DATE(YEAR('P&L Mensal'!$F$1),MONTH('P&L Mensal'!$F$1),1) -> 46082 | C31: ='P&L Mensal'!$F$1 -> 46112 | D31: ='P&L Mensal'!$F$1 -> 46112 | E31: =TEXT('P&L Mensal'!$F$1,"mmm/yyyy") -> mar/yyyy | F31: Receita Juros | G31: Total | H31: Variação R$ | I31: ='P&L Mensal'!L7 -> 1421859.7 | J31: P&L Mensal | K31: L7 | L31: 7
A32: Mensal | B32: =DATE(YEAR('P&L Mensal'!$F$1),MONTH('P&L Mensal'!$F$1),1) -> 46082 | C32: ='P&L Mensal'!$F$1 -> 46112 | D32: ='P&L Mensal'!$F$1 -> 46112 | E32: =TEXT('P&L Mensal'!$F$1,"mmm/yyyy") -> mar/yyyy | F32: Receita CM - Crédito Imobiliário | G32: Consignado | H32: Realizado | I32: ='P&L Mensal'!C10 -> 0 | J32: P&L Mensal | K32: C10 | L32: 10
A33: Mensal | B33: =DATE(YEAR('P&L Mensal'!$F$1),MONTH('P&L Mensal'!$F$1),1) -> 46082 | C33: ='P&L Mensal'!$F$1 -> 46112 | D33: ='P&L Mensal'!$F$1 -> 46112 | E33: =TEXT('P&L Mensal'!$F$1,"mmm/yyyy") -> mar/yyyy | F33: Receita CM - Crédito Imobiliário | G33: Consignado | H33: Orçado | I33: ='P&L Mensal'!D10 -> 0 | J33: P&L Mensal | K33: D10 | L33: 10
A34: Mensal | B34: =DATE(YEAR('P&L Mensal'!$F$1),MONTH('P&L Mensal'!$F$1),1) -> 46082 | C34: ='P&L Mensal'!$F$1 -> 46112 | D34: ='P&L Mensal'!$F$1 -> 46112 | E34: =TEXT('P&L Mensal'!$F$1,"mmm/yyyy") -> mar/yyyy | F34: Receita CM - Crédito Imobiliário | G34: Consignado | H34: Variação % | I34: ='P&L Mensal'!E10 -> - | J34: P&L Mensal | K34: E10 | L34: 10
A35: Mensal | B35: =DATE(YEAR('P&L Mensal'!$F$1),MONTH('P&L Mensal'!$F$1),1) -> 46082 | C35: ='P&L Mensal'!$F$1 -> 46112 | D35: ='P&L Mensal'!$F$1 -> 46112 | E35: =TEXT('P&L Mensal'!$F$1,"mmm/yyyy") -> mar/yyyy | F35: Receita CM - Crédito Imobiliário | G35: Imobiliário | H35: Realizado | I35: ='P&L Mensal'!F10 -> 7200722.4 | J35: P&L Mensal | K35: F10 | L35: 10
A36: Mensal | B36: =DATE(YEAR('P&L Mensal'!$F$1),MONTH('P&L Mensal'!$F$1),1) -> 46082 | C36: ='P&L Mensal'!$F$1 -> 46112 | D36: ='P&L Mensal'!$F$1 -> 46112 | E36: =TEXT('P&L Mensal'!$F$1,"mmm/yyyy") -> mar/yyyy | F36: Receita CM - Crédito Imobiliário | G36: Imobiliário | H36: Orçado | I36: ='P&L Mensal'!G10 -> 5309468.9 | J36: P&L Mensal | K36: G10 | L36: 10
A37: Mensal | B37: =DATE(YEAR('P&L Mensal'!$F$1),MONTH('P&L Mensal'!$F$1),1) -> 46082 | C37: ='P&L Mensal'!$F$1 -> 46112 | D37: ='P&L Mensal'!$F$1 -> 46112 | E37: =TEXT('P&L Mensal'!$F$1,"mmm/yyyy") -> mar/yyyy | F37: Receita CM - Crédito Imobiliário | G37: Imobiliário | H37: Variação % | I37: ='P&L Mensal'!H10 -> 0.35620388 | J37: P&L Mensal | K37: H10 | L37: 10
A38: Mensal | B38: =DATE(YEAR('P&L Mensal'!$F$1),MONTH('P&L Mensal'!$F$1),1) -> 46082 | C38: ='P&L Mensal'!$F$1 -> 46112 | D38: ='P&L Mensal'!$F$1 -> 46112 | E38: =TEXT('P&L Mensal'!$F$1,"mmm/yyyy") -> mar/yyyy | F38: Receita CM - Crédito Imobiliário | G38: Total | H38: Realizado | I38: ='P&L Mensal'!I10 -> 7200722.4 | J38: P&L Mensal | K38: I10 | L38: 10
A39: Mensal | B39: =DATE(YEAR('P&L Mensal'!$F$1),MONTH('P&L Mensal'!$F$1),1) -> 46082 | C39: ='P&L Mensal'!$F$1 -> 46112 | D39: ='P&L Mensal'!$F$1 -> 46112 | E39: =TEXT('P&L Mensal'!$F$1,"mmm/yyyy") -> mar/yyyy | F39: Receita CM - Crédito Imobiliário | G39: Total | H39: Orçado | I39: ='P&L Mensal'!J10 -> 5309468.9 | J39: P&L Mensal | K39: J10 | L39: 10
A40: Mensal | B40: =DATE(YEAR('P&L Mensal'!$F$1),MONTH('P&L Mensal'!$F$1),1) -> 46082 | C40: ='P&L Mensal'!$F$1 -> 46112 | D40: ='P&L Mensal'!$F$1 -> 46112 | E40: =TEXT('P&L Mensal'!$F$1,"mmm/yyyy") -> mar/yyyy | F40: Receita CM - Crédito Imobiliário | G40: Total | H40: Variação % | I40: ='P&L Mensal'!K10 -> 0.35620388 | J40: P&L Mensal | K40: K10 | L40: 10
A41: Mensal | B41: =DATE(YEAR('P&L Mensal'!$F$1),MONTH('P&L Mensal'!$F$1),1) -> 46082 | C41: ='P&L Mensal'!$F$1 -> 46112 | D41: ='P&L Mensal'!$F$1 -> 46112 | E41: =TEXT('P&L Mensal'!$F$1,"mmm/yyyy") -> mar/yyyy | F41: Receita CM - Crédito Imobiliário | G41: Total | H41: Variação R$ | I41: ='P&L Mensal'!L10 -> 1891253.4 | J41: P&L Mensal | K41: L10 | L41: 10
A42: Mensal | B42: =DATE(YEAR('P&L Mensal'!$F$1),MONTH('P&L Mensal'!$F$1),1) -> 46082 | C42: ='P&L Mensal'!$F$1 -> 46112 | D42: ='P&L Mensal'!$F$1 -> 46112 | E42: =TEXT('P&L Mensal'!$F$1,"mmm/yyyy") -> mar/yyyy | F42: Multa + Mora - Crédito Imobiliário | G42: Consignado | H42: Realizado | I42: ='P&L Mensal'!C11 -> 0 | J42: P&L Mensal | K42: C11 | L42: 11
A43: Mensal | B43: =DATE(YEAR('P&L Mensal'!$F$1),MONTH('P&L Mensal'!$F$1),1) -> 46082 | C43: ='P&L Mensal'!$F$1 -> 46112 | D43: ='P&L Mensal'!$F$1 -> 46112 | E43: =TEXT('P&L Mensal'!$F$1,"mmm/yyyy") -> mar/yyyy | F43: Multa + Mora - Crédito Imobiliário | G43: Consignado | H43: Orçado | I43: ='P&L Mensal'!D11 -> 0 | J43: P&L Mensal | K43: D11 | L43: 11
A44: Mensal | B44: =DATE(YEAR('P&L Mensal'!$F$1),MONTH('P&L Mensal'!$F$1),1) -> 46082 | C44: ='P&L Mensal'!$F$1 -> 46112 | D44: ='P&L Mensal'!$F$1 -> 46112 | E44: =TEXT('P&L Mensal'!$F$1,"mmm/yyyy") -> mar/yyyy | F44: Multa + Mora - Crédito Imobiliário | G44: Consignado | H44: Variação % | I44: ='P&L Mensal'!E11 -> - | J44: P&L Mensal | K44: E11 | L44: 11
A45: Mensal | B45: =DATE(YEAR('P&L Mensal'!$F$1),MONTH('P&L Mensal'!$F$1),1) -> 46082 | C45: ='P&L Mensal'!$F$1 -> 46112 | D45: ='P&L Mensal'!$F$1 -> 46112 | E45: =TEXT('P&L Mensal'!$F$1,"mmm/yyyy") -> mar/yyyy | F45: Multa + Mora - Crédito Imobiliário | G45: Imobiliário | H45: Realizado | I45: ='P&L Mensal'!F11 -> 394865.93 | J45: P&L Mensal | K45: F11 | L45: 11
A46: Mensal | B46: =DATE(YEAR('P&L Mensal'!$F$1),MONTH('P&L Mensal'!$F$1),1) -> 46082 | C46: ='P&L Mensal'!$F$1 -> 46112 | D46: ='P&L Mensal'!$F$1 -> 46112 | E46: =TEXT('P&L Mensal'!$F$1,"mmm/yyyy") -> mar/yyyy | F46: Multa + Mora - Crédito Imobiliário | G46: Imobiliário | H46: Orçado | I46: ='P&L Mensal'!G11 -> 372913.43 | J46: P&L Mensal | K46: G11 | L46: 11
A47: Mensal | B47: =DATE(YEAR('P&L Mensal'!$F$1),MONTH('P&L Mensal'!$F$1),1) -> 46082 | C47: ='P&L Mensal'!$F$1 -> 46112 | D47: ='P&L Mensal'!$F$1 -> 46112 | E47: =TEXT('P&L Mensal'!$F$1,"mmm/yyyy") -> mar/yyyy | F47: Multa + Mora - Crédito Imobiliário | G47: Imobiliário | H47: Variação % | I47: ='P&L Mensal'!H11 -> 0.058867538 | J47: P&L Mensal | K47: H11 | L47: 11
A48: Mensal | B48: =DATE(YEAR('P&L Mensal'!$F$1),MONTH('P&L Mensal'!$F$1),1) -> 46082 | C48: ='P&L Mensal'!$F$1 -> 46112 | D48: ='P&L Mensal'!$F$1 -> 46112 | E48: =TEXT('P&L Mensal'!$F$1,"mmm/yyyy") -> mar/yyyy | F48: Multa + Mora - Crédito Imobiliário | G48: Total | H48: Realizado | I48: ='P&L Mensal'!I11 -> 394865.93 | J48: P&L Mensal | K48: I11 | L48: 11
A49: Mensal | B49: =DATE(YEAR('P&L Mensal'!$F$1),MONTH('P&L Mensal'!$F$1),1) -> 46082 | C49: ='P&L Mensal'!$F$1 -> 46112 | D49: ='P&L Mensal'!$F$1 -> 46112 | E49: =TEXT('P&L Mensal'!$F$1,"mmm/yyyy") -> mar/yyyy | F49: Multa + Mora - Crédito Imobiliário | G49: Total | H49: Orçado | I49: ='P&L Mensal'!J11 -> 372913.43 | J49: P&L Mensal | K49: J11 | L49: 11
A50: Mensal | B50: =DATE(YEAR('P&L Mensal'!$F$1),MONTH('P&L Mensal'!$F$1),1) -> 46082 | C50: ='P&L Mensal'!$F$1 -> 46112 | D50: ='P&L Mensal'!$F$1 -> 46112 | E50: =TEXT('P&L Mensal'!$F$1,"mmm/yyyy") -> mar/yyyy | F50: Multa + Mora - Crédito Imobiliário | G50: Total | H50: Variação % | I50: ='P&L Mensal'!K11 -> 0.058867538 | J50: P&L Mensal | K50: K11 | L50: 11
A51: Mensal | B51: =DATE(YEAR('P&L Mensal'!$F$1),MONTH('P&L Mensal'!$F$1),1) -> 46082 | C51: ='P&L Mensal'!$F$1 -> 46112 | D51: ='P&L Mensal'!$F$1 -> 46112 | E51: =TEXT('P&L Mensal'!$F$1,"mmm/yyyy") -> mar/yyyy | F51: Multa + Mora - Crédito Imobiliário | G51: Total | H51: Variação R$ | I51: ='P&L Mensal'!L11 -> 21952.496 | J51: P&L Mensal | K51: L11 | L51: 11
A52: Mensal | B52: =DATE(YEAR('P&L Mensal'!$F$1),MONTH('P&L Mensal'!$F$1),1) -> 46082 | C52: ='P&L Mensal'!$F$1 -> 46112 | D52: ='P&L Mensal'!$F$1 -> 46112 | E52: =TEXT('P&L Mensal'!$F$1,"mmm/yyyy") -> mar/yyyy | F52: Receita Juros - Cartão | G52: Consignado | H52: Realizado | I52: ='P&L Mensal'!C12 -> 1827012.7 | J52: P&L Mensal | K52: C12 | L52: 12
A53: Mensal | B53: =DATE(YEAR('P&L Mensal'!$F$1),MONTH('P&L Mensal'!$F$1),1) -> 46082 | C53: ='P&L Mensal'!$F$1 -> 46112 | D53: ='P&L Mensal'!$F$1 -> 46112 | E53: =TEXT('P&L Mensal'!$F$1,"mmm/yyyy") -> mar/yyyy | F53: Receita Juros - Cartão | G53: Consignado | H53: Orçado | I53: ='P&L Mensal'!D12 -> 1700771.4 | J53: P&L Mensal | K53: D12 | L53: 12
A54: Mensal | B54: =DATE(YEAR('P&L Mensal'!$F$1),MONTH('P&L Mensal'!$F$1),1) -> 46082 | C54: ='P&L Mensal'!$F$1 -> 46112 | D54: ='P&L Mensal'!$F$1 -> 46112 | E54: =TEXT('P&L Mensal'!$F$1,"mmm/yyyy") -> mar/yyyy | F54: Receita Juros - Cartão | G54: Consignado | H54: Variação % | I54: ='P&L Mensal'!E12 -> 0.074225863 | J54: P&L Mensal | K54: E12 | L54: 12
A55: Mensal | B55: =DATE(YEAR('P&L Mensal'!$F$1),MONTH('P&L Mensal'!$F$1),1) -> 46082 | C55: ='P&L Mensal'!$F$1 -> 46112 | D55: ='P&L Mensal'!$F$1 -> 46112 | E55: =TEXT('P&L Mensal'!$F$1,"mmm/yyyy") -> mar/yyyy | F55: Receita Juros - Cartão | G55: Imobiliário | H55: Realizado | I55: ='P&L Mensal'!F12 -> 77247.43 | J55: P&L Mensal | K55: F12 | L55: 12
A56: Mensal | B56: =DATE(YEAR('P&L Mensal'!$F$1),MONTH('P&L Mensal'!$F$1),1) -> 46082 | C56: ='P&L Mensal'!$F$1 -> 46112 | D56: ='P&L Mensal'!$F$1 -> 46112 | E56: =TEXT('P&L Mensal'!$F$1,"mmm/yyyy") -> mar/yyyy | F56: Receita Juros - Cartão | G56: Imobiliário | H56: Orçado | I56: ='P&L Mensal'!G12 -> 41452.468 | J56: P&L Mensal | K56: G12 | L56: 12
A57: Mensal | B57: =DATE(YEAR('P&L Mensal'!$F$1),MONTH('P&L Mensal'!$F$1),1) -> 46082 | C57: ='P&L Mensal'!$F$1 -> 46112 | D57: ='P&L Mensal'!$F$1 -> 46112 | E57: =TEXT('P&L Mensal'!$F$1,"mmm/yyyy") -> mar/yyyy | F57: Receita Juros - Cartão | G57: Imobiliário | H57: Variação % | I57: ='P&L Mensal'!H12 -> 0.86351823 | J57: P&L Mensal | K57: H12 | L57: 12
A58: Mensal | B58: =DATE(YEAR('P&L Mensal'!$F$1),MONTH('P&L Mensal'!$F$1),1) -> 46082 | C58: ='P&L Mensal'!$F$1 -> 46112 | D58: ='P&L Mensal'!$F$1 -> 46112 | E58: =TEXT('P&L Mensal'!$F$1,"mmm/yyyy") -> mar/yyyy | F58: Receita Juros - Cartão | G58: Total | H58: Realizado | I58: ='P&L Mensal'!I12 -> 1904260.1 | J58: P&L Mensal | K58: I12 | L58: 12
A59: Mensal | B59: =DATE(YEAR('P&L Mensal'!$F$1),MONTH('P&L Mensal'!$F$1),1) -> 46082 | C59: ='P&L Mensal'!$F$1 -> 46112 | D59: ='P&L Mensal'!$F$1 -> 46112 | E59: =TEXT('P&L Mensal'!$F$1,"mmm/yyyy") -> mar/yyyy | F59: Receita Juros - Cartão | G59: Total | H59: Orçado | I59: ='P&L Mensal'!J12 -> 1742223.9 | J59: P&L Mensal | K59: J12 | L59: 12
A60: Mensal | B60: =DATE(YEAR('P&L Mensal'!$F$1),MONTH('P&L Mensal'!$F$1),1) -> 46082 | C60: ='P&L Mensal'!$F$1 -> 46112 | D60: ='P&L Mensal'!$F$1 -> 46112 | E60: =TEXT('P&L Mensal'!$F$1,"mmm/yyyy") -> mar/yyyy | F60: Receita Juros - Cartão | G60: Total | H60: Variação % | I60: ='P&L Mensal'!K12 -> 0.093005376 | J60: P&L Mensal | K60: K12 | L60: 12
A61: Mensal | B61: =DATE(YEAR('P&L Mensal'!$F$1),MONTH('P&L Mensal'!$F$1),1) -> 46082 | C61: ='P&L Mensal'!$F$1 -> 46112 | D61: ='P&L Mensal'!$F$1 -> 46112 | E61: =TEXT('P&L Mensal'!$F$1,"mmm/yyyy") -> mar/yyyy | F61: Receita Juros - Cartão | G61: Total | H61: Variação R$ | I61: ='P&L Mensal'!L12 -> 162036.19 | J61: P&L Mensal | K61: L12 | L61: 12
A62: Mensal | B62: =DATE(YEAR('P&L Mensal'!$F$1),MONTH('P&L Mensal'!$F$1),1) -> 46082 | C62: ='P&L Mensal'!$F$1 -> 46112 | D62: ='P&L Mensal'!$F$1 -> 46112 | E62: =TEXT('P&L Mensal'!$F$1,"mmm/yyyy") -> mar/yyyy | F62: Receita Serviços | G62: Consignado | H62: Realizado | I62: ='P&L Mensal'!C13 -> 0 | J62: P&L Mensal | K62: C13 | L62: 13
A63: Mensal | B63: =DATE(YEAR('P&L Mensal'!$F$1),MONTH('P&L Mensal'!$F$1),1) -> 46082 | C63: ='P&L Mensal'!$F$1 -> 46112 | D63: ='P&L Mensal'!$F$1 -> 46112 | E63: =TEXT('P&L Mensal'!$F$1,"mmm/yyyy") -> mar/yyyy | F63: Receita Serviços | G63: Consignado | H63: Orçado | I63: ='P&L Mensal'!D13 -> 0 | J63: P&L Mensal | K63: D13 | L63: 13
A64: Mensal | B64: =DATE(YEAR('P&L Mensal'!$F$1),MONTH('P&L Mensal'!$F$1),1) -> 46082 | C64: ='P&L Mensal'!$F$1 -> 46112 | D64: ='P&L Mensal'!$F$1 -> 46112 | E64: =TEXT('P&L Mensal'!$F$1,"mmm/yyyy") -> mar/yyyy | F64: Receita Serviços | G64: Consignado | H64: Variação % | I64: ='P&L Mensal'!E13 -> - | J64: P&L Mensal | K64: E13 | L64: 13
A65: Mensal | B65: =DATE(YEAR('P&L Mensal'!$F$1),MONTH('P&L Mensal'!$F$1),1) -> 46082 | C65: ='P&L Mensal'!$F$1 -> 46112 | D65: ='P&L Mensal'!$F$1 -> 46112 | E65: =TEXT('P&L Mensal'!$F$1,"mmm/yyyy") -> mar/yyyy | F65: Receita Serviços | G65: Imobiliário | H65: Realizado | I65: ='P&L Mensal'!F13 -> 2558364.6 | J65: P&L Mensal | K65: F13 | L65: 13
A66: Mensal | B66: =DATE(YEAR('P&L Mensal'!$F$1),MONTH('P&L Mensal'!$F$1),1) -> 46082 | C66: ='P&L Mensal'!$F$1 -> 46112 | D66: ='P&L Mensal'!$F$1 -> 46112 | E66: =TEXT('P&L Mensal'!$F$1,"mmm/yyyy") -> mar/yyyy | F66: Receita Serviços | G66: Imobiliário | H66: Orçado | I66: ='P&L Mensal'!G13 -> 1754400 | J66: P&L Mensal | K66: G13 | L66: 13
A67: Mensal | B67: =DATE(YEAR('P&L Mensal'!$F$1),MONTH('P&L Mensal'!$F$1),1) -> 46082 | C67: ='P&L Mensal'!$F$1 -> 46112 | D67: ='P&L Mensal'!$F$1 -> 46112 | E67: =TEXT('P&L Mensal'!$F$1,"mmm/yyyy") -> mar/yyyy | F67: Receita Serviços | G67: Imobiliário | H67: Variação % | I67: ='P&L Mensal'!H13 -> 0.45825613 | J67: P&L Mensal | K67: H13 | L67: 13
A68: Mensal | B68: =DATE(YEAR('P&L Mensal'!$F$1),MONTH('P&L Mensal'!$F$1),1) -> 46082 | C68: ='P&L Mensal'!$F$1 -> 46112 | D68: ='P&L Mensal'!$F$1 -> 46112 | E68: =TEXT('P&L Mensal'!$F$1,"mmm/yyyy") -> mar/yyyy | F68: Receita Serviços | G68: Total | H68: Realizado | I68: ='P&L Mensal'!I13 -> 2558364.6 | J68: P&L Mensal | K68: I13 | L68: 13
A69: Mensal | B69: =DATE(YEAR('P&L Mensal'!$F$1),MONTH('P&L Mensal'!$F$1),1) -> 46082 | C69: ='P&L Mensal'!$F$1 -> 46112 | D69: ='P&L Mensal'!$F$1 -> 46112 | E69: =TEXT('P&L Mensal'!$F$1,"mmm/yyyy") -> mar/yyyy | F69: Receita Serviços | G69: Total | H69: Orçado | I69: ='P&L Mensal'!J13 -> 1754400 | J69: P&L Mensal | K69: J13 | L69: 13
A70: Mensal | B70: =DATE(YEAR('P&L Mensal'!$F$1),MONTH('P&L Mensal'!$F$1),1) -> 46082 | C70: ='P&L Mensal'!$F$1 -> 46112 | D70: ='P&L Mensal'!$F$1 -> 46112 | E70: =TEXT('P&L Mensal'!$F$1,"mmm/yyyy") -> mar/yyyy | F70: Receita Serviços | G70: Total | H70: Variação % | I70: ='P&L Mensal'!K13 -> 0.45825613 | J70: P&L Mensal | K70: K13 | L70: 13
A71: Mensal | B71: =DATE(YEAR('P&L Mensal'!$F$1),MONTH('P&L Mensal'!$F$1),1) -> 46082 | C71: ='P&L Mensal'!$F$1 -> 46112 | D71: ='P&L Mensal'!$F$1 -> 46112 | E71: =TEXT('P&L Mensal'!$F$1,"mmm/yyyy") -> mar/yyyy | F71: Receita Serviços | G71: Total | H71: Variação R$ | I71: ='P&L Mensal'!L13 -> 803964.56 | J71: P&L Mensal | K71: L13 | L71: 13
A72: Mensal | B72: =DATE(YEAR('P&L Mensal'!$F$1),MONTH('P&L Mensal'!$F$1),1) -> 46082 | C72: ='P&L Mensal'!$F$1 -> 46112 | D72: ='P&L Mensal'!$F$1 -> 46112 | E72: =TEXT('P&L Mensal'!$F$1,"mmm/yyyy") -> mar/yyyy | F72: Receita Interchange | G72: Consignado | H72: Realizado | I72: ='P&L Mensal'!C14 -> 8879.4971 | J72: P&L Mensal | K72: C14 | L72: 14
A73: Mensal | B73: =DATE(YEAR('P&L Mensal'!$F$1),MONTH('P&L Mensal'!$F$1),1) -> 46082 | C73: ='P&L Mensal'!$F$1 -> 46112 | D73: ='P&L Mensal'!$F$1 -> 46112 | E73: =TEXT('P&L Mensal'!$F$1,"mmm/yyyy") -> mar/yyyy | F73: Receita Interchange | G73: Consignado | H73: Orçado | I73: ='P&L Mensal'!D14 -> 12466.562 | J73: P&L Mensal | K73: D14 | L73: 14
A74: Mensal | B74: =DATE(YEAR('P&L Mensal'!$F$1),MONTH('P&L Mensal'!$F$1),1) -> 46082 | C74: ='P&L Mensal'!$F$1 -> 46112 | D74: ='P&L Mensal'!$F$1 -> 46112 | E74: =TEXT('P&L Mensal'!$F$1,"mmm/yyyy") -> mar/yyyy | F74: Receita Interchange | G74: Consignado | H74: Variação % | I74: ='P&L Mensal'!E14 -> -0.28773487 | J74: P&L Mensal | K74: E14 | L74: 14
A75: Mensal | B75: =DATE(YEAR('P&L Mensal'!$F$1),MONTH('P&L Mensal'!$F$1),1) -> 46082 | C75: ='P&L Mensal'!$F$1 -> 46112 | D75: ='P&L Mensal'!$F$1 -> 46112 | E75: =TEXT('P&L Mensal'!$F$1,"mmm/yyyy") -> mar/yyyy | F75: Receita Interchange | G75: Imobiliário | H75: Realizado | I75: ='P&L Mensal'!F14 -> 11964.393 | J75: P&L Mensal | K75: F14 | L75: 14
A76: Mensal | B76: =DATE(YEAR('P&L Mensal'!$F$1),MONTH('P&L Mensal'!$F$1),1) -> 46082 | C76: ='P&L Mensal'!$F$1 -> 46112 | D76: ='P&L Mensal'!$F$1 -> 46112 | E76: =TEXT('P&L Mensal'!$F$1,"mmm/yyyy") -> mar/yyyy | F76: Receita Interchange | G76: Imobiliário | H76: Orçado | I76: ='P&L Mensal'!G14 -> 16829.858 | J76: P&L Mensal | K76: G14 | L76: 14
A77: Mensal | B77: =DATE(YEAR('P&L Mensal'!$F$1),MONTH('P&L Mensal'!$F$1),1) -> 46082 | C77: ='P&L Mensal'!$F$1 -> 46112 | D77: ='P&L Mensal'!$F$1 -> 46112 | E77: =TEXT('P&L Mensal'!$F$1,"mmm/yyyy") -> mar/yyyy | F77: Receita Interchange | G77: Imobiliário | H77: Variação % | I77: ='P&L Mensal'!H14 -> -0.28909723 | J77: P&L Mensal | K77: H14 | L77: 14
A78: Mensal | B78: =DATE(YEAR('P&L Mensal'!$F$1),MONTH('P&L Mensal'!$F$1),1) -> 46082 | C78: ='P&L Mensal'!$F$1 -> 46112 | D78: ='P&L Mensal'!$F$1 -> 46112 | E78: =TEXT('P&L Mensal'!$F$1,"mmm/yyyy") -> mar/yyyy | F78: Receita Interchange | G78: Total | H78: Realizado | I78: ='P&L Mensal'!I14 -> 20843.89 | J78: P&L Mensal | K78: I14 | L78: 14
A79: Mensal | B79: =DATE(YEAR('P&L Mensal'!$F$1),MONTH('P&L Mensal'!$F$1),1) -> 46082 | C79: ='P&L Mensal'!$F$1 -> 46112 | D79: ='P&L Mensal'!$F$1 -> 46112 | E79: =TEXT('P&L Mensal'!$F$1,"mmm/yyyy") -> mar/yyyy | F79: Receita Interchange | G79: Total | H79: Orçado | I79: ='P&L Mensal'!J14 -> 29296.42 | J79: P&L Mensal | K79: J14 | L79: 14
A80: Mensal | B80: =DATE(YEAR('P&L Mensal'!$F$1),MONTH('P&L Mensal'!$F$1),1) -> 46082 | C80: ='P&L Mensal'!$F$1 -> 46112 | D80: ='P&L Mensal'!$F$1 -> 46112 | E80: =TEXT('P&L Mensal'!$F$1,"mmm/yyyy") -> mar/yyyy | F80: Receita Interchange | G80: Total | H80: Variação % | I80: ='P&L Mensal'!K14 -> -0.2885175 | J80: P&L Mensal | K80: K14 | L80: 14
